Workbook

Sheet Summary
A1: Clarkson PLC (LSE: CKN) — FY2026E Scenario Comparison
A2: All figures link to the Base Case, Bull Case and Bear Case sheets. Change a yellow input cell there and this sheet updates.
A3: FY2026E Summary (£m unless noted)
A4: Metric | B4: Base Case | C4: Bull Case | D4: Bear Case | E4: Spread (Bull − Bear)
A5: Revenue | B5: ='Base Case'!E6 -> 872.11983 | C5: ='Bull Case'!E6 -> 913.21318 | D5: ='Bear Case'!E6 -> 801.986 | E5: =C5-D5 -> 111.22718
A6: Underlying Operating Profit | B6: ='Base Case'!E9 -> 126.9105 | C6: ='Bull Case'!E9 -> 139.46181 | D6: ='Bear Case'!E9 -> 94.226903 | E6: =C6-D6 -> 45.234908
A7: Underlying Operating Margin % | B7: ='Base Case'!E10 -> 0.14551957 | C7: ='Bull Case'!E10 -> 0.1527155 | D7: ='Bear Case'!E10 -> 0.11749195 | E7: =C7-D7 -> 0.035223548
A8: Underlying Net Income | B8: ='Base Case'!E15 -> 104.27753 | C8: ='Bull Case'!E15 -> 113.87928 | D8: ='Bear Case'!E15 -> 79.27458 | E8: =C8-D8 -> 34.604704
A9: NOPAT | B9: ='Base Case'!E16 -> 97.086534 | C9: ='Bull Case'!E16 -> 106.68828 | D9: ='Bear Case'!E16 -> 72.08358 | E9: =C9-D9 -> 34.604704
A10: Real DSO, Dec 2026E (days) | B10: ='Base Case'!D20 -> 81.474002 | C10: ='Bull Case'!D20 -> 81.474002 | D10: ='Bear Case'!D20 -> 81.474002 | E10: =C10-D10 -> 0
A11: ECL Allowance, Dec 2026E | B11: ='Base Case'!D27 -> 39 | C11: ='Bull Case'!D27 -> 40.8 | D11: ='Bear Case'!D27 -> 42.8 | E11: =C11-D11 -> -2
A12: ECL charge / H2 revenue | B12: ='Base Case'!D28 -> 0.016789505 | C12: ='Bull Case'!D28 -> 0.019010905 | D12: ='Bear Case'!D28 -> 0.029602096 | E12: =C12-D12 -> -0.010591191
A13: Net Cash & Available Funds, Dec 2026E | B13: ='Base Case'!D40 -> 223.68698 | C13: ='Bull Case'!D40 -> 224.75784 | D13: ='Bear Case'!D40 -> 204.27903 | E13: =C13-D13 -> 20.478806
A14: Average Invested Capital, FY2026 | B14: ='Base Case'!D46 -> 345.11076 | C14: ='Bull Case'!D46 -> 347.24349 | D14: ='Bear Case'!D46 -> 343.71201 | E14: =C14-D14 -> 3.5314745
A15: ROIC FY2026E | B15: ='Base Case'!D47 -> 0.28131992 | C15: ='Bull Case'!D47 -> 0.30724344 | D15: ='Bear Case'!D47 -> 0.20972086 | E15: =C15-D15 -> 0.097522579
A17: Model Notes & Caveats
A18: 1. Structure: Broking H2 growth is built in two layers (Base and Bull sheets, rows 74-87). Layer 1 follows the Board's guidance of 31 July 2026 (no second-half weighting): organic Broking revenue flat, plus a full half of Link. Layer 2 adds the Yemen–Saudi escalation from 9 September 2026, for Broking only. Financial H2 growth is a separate input (Base 0% so the record H1 is not extrapolated; Bull +8%, the FY2025 H2 vs H1 change). Bear does not use the two layers. Head office costs are held at the H1 2026 actual (£28.6m) because no driver is disclosed for the H1 increase (+32.4% YoY).
A19: 2. Net finance income is held at £4.7m (H1 2026 level) in all scenarios and periods, to avoid a circular link with the cash forecast. A fuller model would tie it to average net cash.
A20: 3. The net assets roll-forward (row 42 on each sheet) leaves out OCI, FX translation and NCI movements to keep it simple.
A21: 4. The main judgments to test: segment H2 growth rates and flow-through choices, the Layer 2 weight (B86: Base 0.5, Bull 1.0), the H2 credit loss charge (B26; the part above the H1 level of £7.7m is taken off H2 operating profit, row 65), H2 M&A spend (D36) and the GBP/USD path (B67). Real DSO, T+2 balances, ESOP, lease payments, head office costs and the cash conversion multiple are based on reported figures and are the same in all scenarios. Each scenario's change in receivables affects cash through D34.
A22: 5. The H2 2026 dividend (£10.8m) is the same in all scenarios because it is the interim dividend already declared (35p per share).
A23: 6. H1 2026, June 2026 and FY2025 figures come from the 2026 Interim Report and the 2025 Annual Report / Preliminary Results (page references in the cell comments).
A24: 7. Basis: operating profit is before acquisition-related costs, as in the segment note (segment results less head office costs; INT26 Note 3 p.25, AR2025 Note 4 p.82). H1 2026 was £56.8m on this basis and £51.0m statutory. H1 2026 acquisition-related costs were £5.8m in operating profit (amortisation £1.4m, transaction costs £0.9m, charges linked to acquisitions £3.5m; INT26 Note 4 p.25) plus £0.1m of interest, £5.9m before tax (INT26 p.19). They are not forecast for H2. They will continue: the Link escrow (£12.6m) and share awards (Link £4.1m, Zuma £1.9m) are expensed over four years, about £2.3m per half, and amortisation of the £38.1m of acquired intangibles comes on top. Statutory H2 profit will therefore be lower than shown.
A25: 8. Segment margins use flow-through margins (change in operating profit ÷ change in revenue, from my margin analysis and AR2024 for Financial's decline year). Margins therefore move with the revenue assumptions. Support's flow-through was negative in both periods observed, so faster Support growth lowers its margin.
A26: 9. Average invested capital (row 46) uses three points (Dec 2025, Jun 2026, Dec 2026E) so that the June 2026 step-up from acquisitions (371.0) is included. A two-point average would leave it out and overstate ROIC, by about 2.3pp in the Base case.
A27: 10. FX uses the company's own hedged sensitivity from the 2025 Annual Report (Note 27 p.93: a 5% stronger USD adds £5.6m to PBT, a 5% weaker USD takes off £5.1m), which is about 1.24% / 1.13% of FY2025 underlying PBT (£90.6m) per 1% move. It is applied to an assumed GBP/USD path for H2. This is an approximation: the company's figure is a translation effect in £, applied here as a % of H2 profit.
A28: 11. Bear H2 2026E group margin (about 9.6%) is below the lowest half-year margin reported (H1 2025: 32.7 ÷ 297.8 = 11.0%, INT26 p.19). FY2026E Bear is higher (about 11.8%) because it includes the record H1 2026. There is no separate severe-downside case.
... A34: H2 2026E Segment Snapshot (£m) — live links to rows 52-56 of each scenario sheet
A35: Segment / metric | B35: Base Case | C35: Bull Case | D35: Bear Case | E35: H1 2026A 📄
A36: Broking — H2 Revenue | B36: ='Base Case'!H52 -> 351.16283 | C36: ='Bull Case'!H52 -> 385.55518 | D36: ='Bear Case'!H52 -> 285.476 | E36: 310.3
A37: Broking — H2 Op Profit | B37: ='Base Case'!I52 -> 75.465198 | C37: ='Bull Case'!I52 -> 84.441602 | D37: ='Bear Case'!I52 -> 51.444688 | E37: 64.8
A38: Broking — H2 Margin | B38: ='Base Case'!J52 -> 0.21490087 | C38: ='Bull Case'!J52 -> 0.21901301 | D38: ='Bear Case'!J52 -> 0.1802067 | E38: 0.20883016
A39: Financial — H2 Revenue | B39: ='Base Case'!H53 -> 48.1 | C39: ='Bull Case'!H53 -> 51.948 | D39: ='Bear Case'!H53 -> 46.657 | E39: 48.1
A40: Financial — H2 Op Profit | B40: ='Base Case'!I53 -> 11.7 | C40: ='Bull Case'!I53 -> 13.39312 | D40: ='Bear Case'!I53 -> 10.353681 | E40: 11.7
A41: Financial — H2 Margin | B41: ='Base Case'!J53 -> 0.24324324 | C41: ='Bull Case'!J53 -> 0.25781782 | D41: ='Bear Case'!J53 -> 0.22191056 | E41: 0.24324324
A42: Support — H2 Revenue | B42: ='Base Case'!H54 -> 43.2 | C42: ='Bull Case'!H54 -> 45.6 | D42: ='Bear Case'!H54 -> 40.8 | E42: 40
A43: Support — H2 Op Profit | B43: ='Base Case'!I54 -> 2.4496 | C43: ='Bull Case'!I54 -> 2.6 | D43: ='Bear Case'!I54 -> 2.44 | E43: 2.6
A44: Support — H2 Margin | B44: ='Base Case'!J54 -> 0.056703704 | C44: ='Bull Case'!J54 -> 0.057017544 | D44: ='Bear Case'!J54 -> 0.059803922 | E44: 0.065
A45: Research — H2 Revenue | B45: ='Base Case'!H55 -> 16.157 | C45: ='Bull Case'!H55 -> 16.61 | D45: ='Bear Case'!H55 -> 15.553 | E45: 15.1
A46: Research — H2 Op Profit | B46: ='Base Case'!I55 -> 6.9342 | C46: ='Bull Case'!I55 -> 7.206 | D46: ='Bear Case'!I55 -> 6.484371 | E46: 6.3
A47: Research — H2 Margin | B47: ='Base Case'!J55 -> 0.42917621 | C47: ='Bull Case'!J55 -> 0.43383504 | D47: ='Bear Case'!J55 -> 0.41692092 | E47: 0.41721854
A48: Total Segment — H2 Revenue | B48: ='Base Case'!H56 -> 458.61983 | C48: ='Bull Case'!H56 -> 499.71318 | D48: ='Bear Case'!H56 -> 388.486 | E48: 413.5
A49: Total Segment — H2 Op Profit | B49: ='Base Case'!I56 -> 96.548998 | C49: ='Bull Case'!I56 -> 107.64072 | D49: ='Bear Case'!I56 -> 70.72274 | E49: 85.4
A50: Total Segment — H2 Margin | B50: ='Base Case'!J56 -> 0.21052077 | C50: ='Bull Case'!J56 -> 0.21540501 | D50: ='Bear Case'!J56 -> 0.18204708 | E50: 0.20652963
A51: Head office cost, H2 | B51: ='Base Case'!D61 -> -28.6 | C51: ='Bull Case'!D61 -> -28.6 | D51: ='Bear Case'!D61 -> -28.6 | E51: -28.6
A52: FX effect on op. profit (%) | B52: ='Base Case'!D70 -> 3.181067 | C52: ='Bull Case'!D70 -> 6.8586011 | D52: ='Bear Case'!D70 -> -2.1267311
A53: Group op. profit H2 (before acq. costs) | B53: ='Base Case'!D71 -> 70.110501 | C53: ='Bull Case'!D71 -> 82.66181 | D53: ='Bear Case'!D71 -> 37.426903 | E53: 56.8
A55: Base case: sensitivity to the Layer 2 (escalation) weight (links to Base Case rows 119-137)
A56: Layer 2 weight | B56: ='Base Case'!B119 -> 0 | C56: ='Base Case'!C119 -> 0.25 | D56: ='Base Case'!D119 -> 0.5 | E56: ='Base Case'!E119 -> 0.75 | F56: ='Base Case'!F119 -> 1
A57: H2 operating profit (£m) | B57: ='Base Case'!B123 -> 60.848552 | C57: ='Base Case'!C123 -> 65.479527 | D57: ='Base Case'!D123 -> 70.110501 | E57: ='Base Case'!E123 -> 74.741476 | F57: ='Base Case'!F123 -> 79.372451
A58: H2 vs H1 2026A | B58: ='Base Case'!B124 -> 0.071277324 | C58: ='Base Case'!C124 -> 0.15280857 | D58: ='Base Case'!D124 -> 0.23433981 | E58: ='Base Case'!E124 -> 0.31587106 | F58: ='Base Case'!F124 -> 0.3974023
A59: FY operating profit (£m) | B59: ='Base Case'!B125 -> 117.64855 | C59: ='Base Case'!C125 -> 122.27953 | D59: ='Base Case'!D125 -> 126.9105 | E59: ='Base Case'!E125 -> 131.54148 | F59: ='Base Case'!F125 -> 136.17245
A60: ROIC FY2026E | B60: ='Base Case'!B135 -> 0.26146236 | C60: ='Base Case'!C135 -> 0.27140394 | D60: ='Base Case'!D135 -> 0.28131992 | E60: ='Base Case'!E135 -> 0.29121041 | F60: ='Base Case'!F135 -> 0.30107549
A61: Escalation-dependent H2 op. profit (0.5 vs 0) | B61: ='Base Case'!B137 -> 9.2619494
A62: Base uses 0.5 because the September escalation is judged to be about half the size of the H1 shock (the closure of the Strait of Hormuz, INT26 p.4). Bull's 1.0 assumes it becomes as large, as an upper bound. No data sets the weight exactly, so the full range is shown.
A64: Bull vs Base — H2 2026E operating profit bridge (£m, live formulas; FX shown separately)
A65: Driver | B65: Base | C65: Bull | D65: Δ Bull − Base | E65: Share of gap
A66: Broking segment op. profit (growth 13.2% → 24.3%, Layer 2 weight 0.5 → 1.0) | B66: ='Base Case'!I52 -> 75.465198 | C66: ='Bull Case'!I52 -> 84.441602 | D66: =C66-B66 -> 8.976404 | E66: =D66/$D$73 -> 0.71517674
A67: Financial segment op. profit (growth 0% → 8%) | B67: ='Base Case'!I53 -> 11.7 | C67: ='Bull Case'!I53 -> 13.39312 | D67: =C67-B67 -> 1.69312 | E67: =D67/$D$73 -> 0.13489589
A68: Support segment op. profit | B68: ='Base Case'!I54 -> 2.4496 | C68: ='Bull Case'!I54 -> 2.6 | D68: =C68-B68 -> 0.1504 | E68: =D68/$D$73 -> 0.011982814
A69: Research segment op. profit | B69: ='Base Case'!I55 -> 6.9342 | C69: ='Bull Case'!I55 -> 7.206 | D69: =C69-B69 -> 0.2718 | E69: =D69/$D$73 -> 0.021655112
A70: Head office cost (same in both) | B70: ='Base Case'!D61 -> -28.6 | C70: ='Bull Case'!D61 -> -28.6 | D70: =C70-B70 -> 0 | E70: =D70/$D$73 -> 0
A71: Extra H2 credit loss charge (Bull only) | B71: ='Base Case'!D65 -> 0 | C71: ='Bull Case'!D65 -> -1.8 | D71: =C71-B71 -> -1.8 | E71: =D71/$D$73 -> -0.14341134
A72: FX translation (op. profit before FX × FX %; GBP/USD 1.31 → 1.27) | B72: ='Base Case'!D64*'Base Case'!D70/100 -> 2.1615032 | C72: ='Bull Case'!D64*'Bull Case'!D70/100 -> 5.4210879 | D72: =C72-B72 -> 3.2595847 | E72: =D72/$D$73 -> 0.25970078
A73: Group op. profit H2 2026E (= sum; ties to row 53) | B73: =SUM(B66:B72) -> 70.110501 | C73: =SUM(C66:C72) -> 82.66181 | D73: =SUM(D66:D72) -> 12.551309 | E73: =SUM(E66:E72) -> 1
A74: Check: bridge total minus row 53 (should be 0) | B74: =B73-B53 -> 0 | C74: =C73-C53 -> 0
A75: Reading: about 72% of the £12.6m Bull − Base gap comes from Broking, i.e. mainly from one judgment — the Layer 2 weight (0.5 vs 1.0). FX adds about £3.3m (a weaker pound on a larger profit base) and the Bull-only credit loss charge takes back £1.8m. Broking's flow-through is asymmetric: 0.261 on growth (Base, Bull) but 0.538 on decline (Bear), so each £1 of lost Broking revenue costs about twice as much profit as £1 of extra revenue adds. Downside risk is therefore larger than upside for the same revenue move.
A77: This model will be updated when H2 2026 actuals are released. An H1 2027 extension is also planned.

Sheet Base Case
A1: Clarkson PLC (LSE: CKN) — H2 2026E / FY2026E Scenario Model: Base Case
A2: £m unless noted. Blue = input. Black = formula. Green = link to another sheet.
A3: Tags: 📄 = from the filings (page given in the comment); 🔵 = my assumption; 🔢 = calculation; 🌐 = news source, not in the filings.
A4: P&L Forecast (£m)
A5: Item | B5: Assumption | C5: H1 2026A 📄 | D5: H2 2026E | E5: FY2026E | F5: Note / Source
A6: Revenue | C6: 413.5 | D6: =H56 -> 458.61983 | E6: =C6+D6 -> 872.11983 | F6: H2 Revenue = Total Segment H2 2026E Revenue (row 56) — see segment detail below
A7: H2 revenue growth vs. H1 2026 (computed, from segment roll-up) | B7: =D6/C6-1 -> 0.10911688
A8: Underlying Operating Margin, H2 (computed, from segment + HO + FX roll-up) | B8: =D9/D6 -> 0.15287281
A9: Underlying Operating Profit | C9: 56.8 | D9: =D71 -> 70.110501 | E9: =C9+D9 -> 126.9105 | F9: From row 71 (group operating profit after head office costs, FX and extra credit losses). Before acquisition-related costs, like the H1 figure of 56.8 (Summary note 7).
A10: Implied Operating Margin % (check) | C10: =C9/C6 -> 0.13736397 | D10: =D9/D6 -> 0.15287281 | E10: =E9/E6 -> 0.14551957
A11: Net Finance Income (🔵 held constant — see model notes) | B11: 4.7 | C11: 4.7 | D11: =B11 -> 4.7 | E11: =C11+D11 -> 9.4 | F11: £4.7m = H1 2026 underlying PBT (61.5) − underlying operating profit (56.8). This matches the income statement: finance income 6.0, finance costs (1.7) and pension income 0.4 (INT26 p.19). Held flat in H2 and in all scenarios to avoid a circular link with cash (Summary note 2).
A12: Underlying Profit Before Tax | C12: =C9+C11 -> 61.5 | D12: =D9+D11 -> 74.810501 | E12: =C12+D12 -> 136.3105
A13: Tax rate (📄 INT26 Note 5 p.25: expected FY2026 rate excluding acquisition-related costs) | B13: 0.235
A14: Tax | C14: =C12*$B$13 -> 14.4525 | D14: =D12*$B$13 -> 17.580468 | E14: =C14+D14 -> 32.032968
A15: Underlying Net Income | C15: =C12-C14 -> 47.0475 | D15: =D12-D14 -> 57.230034 | E15: =E12-E14 -> 104.27753
A16: NOPAT (operating basis, for ROIC only) | C16: =C9*(1-$B$13) -> 43.452 | D16: =D9*(1-$B$13) -> 53.634534 | E16: =E9*(1-$B$13) -> 97.086534
A18: Receivables, DSO & Credit Losses (£m / days)
A19: Item | B19: Assumption | C19: Jun 2026A 📄 | D19: Dec 2026E | F19: Note / Source
A20: Real DSO (days, ex-T+2 settlement) | B20: =C20 -> 81.474002 | C20: =C22/(C6*2)*365 -> 81.474002 | D20: =B20 -> 81.474002 | F20: Same in all scenarios, at the H1 2026 actual: 184.6 ÷ 827.0 × 365 = 81.47 days (ex-settlement receivables ÷ annualised H1 revenue). There is no evidence that collection differs by scenario.
A21: T+2 Settlement Accounts (🔢 = Jun 2026A × (1 + Financial H2 growth, D53)) | B21: =C21*(1+D53) -> 84.2 | C21: 84.2 | D21: =B21 -> 84.2 | F21: The £84.2m of T+2 settlement balances sit in the Financial division and usually settle two days after the trade (INT26 Note 10 p.29). They are matched by an £84.1m payable, so they are a pass-through, not a credit risk. The balance grows with Financial H2 revenue (D53).
A22: Ex-settlement receivables (trade and other receivables less T+2; the interim balance sheet does not split trade and other) | C22: 184.6 | D22: =D20/365*E6 -> 194.67149 | F22: Dec26E uses FY2026E revenue (E6) — DSO convention per report §5-1
A23: Total Current Receivables | C23: =C21+C22 -> 268.8 | D23: =D21+D22 -> 278.87149
A24: Surface DSO (days, check) | C24: =C23/(C6*2)*365 -> 118.63603 | D24: =D23/E6*365 -> 116.71343
A25: ECL Allowance, opening balance | C25: 31.3
A26: H2 Net Impairment Loss / ECL charge (🔵 assumption) | B26: 7.7
A27: ECL Allowance, closing balance | D27: =C25+B26 -> 39
A28: ECL charge / H2 revenue | D28: =B26/D6 -> 0.016789505
A29: Allowance / Ex-Settlement Receivables (coverage) | C29: =C25/C22 -> 0.1695558 | D29: =D27/D22 -> 0.2003375
A31: Cash Flow & ROIC (£m)
A32: Item | B32: Assumption | C32: Jun 2026A 📄 | D32: Dec 2026E | F32: Note / Source
A33: Net Cash & Available Funds, opening | C33: 178.8
A34: H2 operating cash flow (🔢 = H2 op. profit × B34 − change in ex-settlement receivables, D22 − C22) | B34: =E115 -> 1.2472406 | D34: =D9*B34-(D22-C22) -> 77.373177 | F34: Formula: D9 × B34 − (D22 − C22). B34 is the H2 2025 conversion before working capital (about 1.25x, row 115). T+2 balances (row 21) are left out because they are matched by payables (INT26 Note 10 p.29).
A35: H2 CAPEX (% of H2 revenue, 🔵 assumption) | B35: 0.01 | D35: =D6*B35 -> 4.5861983
A36: H2 M&A spend (🔵 assumption) | D36: 10
A37: H2 Dividend paid (📄 disclosed: 2026 interim 35p = £10.8m) | D37: 10.8
A38: H2 ESOP buybacks (📄 anchored to H2 2025 actual, row 102) | D38: =E102 -> 1.8
A39: H2 Lease principal repayment (📄 held at H1 2026A actual) | D39: 5.3
A40: Net Cash & Available Funds, closing | D40: =C33+D34-D35-D36-D37-D38-D39 -> 223.68698
A41: Net Assets, opening (derived: Invested Capital + Net Cash) | C41: 549.8 | F41: Simplified: excludes OCI/FX/NCI — see model notes
A42: Net Assets, closing (simplified roll-forward) | D42: =C41+D15-D37-D38 -> 594.43003
A43: Invested Capital, opening (Jun 2026A) | C43: 371
A44: Invested Capital, closing (Dec 2026E) | D44: =D42-D40 -> 370.74305
A45: Invested Capital, FY2025 closing (anchor) | C45: 267.7
A46: Average invested capital, FY2026 (three points: Dec 2025, Jun 2026, Dec 2026E) | D46: =(C45 + 2*C43 + D44)/4 -> 345.11076
A47: ROIC FY2026E (= FY NOPAT ÷ Average Invested Capital) | D47: =E16/D46 -> 0.28131992
A50: Segment revenue and operating profit, H2 2026E (flow-through margin method)
A51: Segment | B51: H1 2026A Revenue 📄 | C51: H1 2026A Op Profit 📄 | D51: H2 Growth % 🔵 | E51: Flow-through Margin % (📄 source) | F51: ΔRevenue | G51: ΔOp Profit | H51: H2 2026E Revenue | I51: H2 2026E Op Profit | J51: H2 2026E Margin %
A52: Broking | B52: 310.3 | C52: 64.8 | D52: =C87 -> 0.13168814 | E52: 0.261 | F52: =B52*D52 -> 40.862829 | G52: =F52*E52 -> 10.665198 | H52: =B52+F52 -> 351.16283 | I52: =C52+G52 -> 75.465198 | J52: =I52/H52 -> 0.21490087
A53: Financial | B53: 48.1 | C53: 11.7 | D53: 0 | E53: 0.375 | F53: =B53*D53 -> 0 | G53: =F53*E53 -> 0 | H53: =B53+F53 -> 48.1 | I53: =C53+G53 -> 11.7 | J53: =I53/H53 -> 0.24324324
A54: Support | B54: 40 | C54: 2.6 | D54: 0.08 | E54: -0.047 | F54: =B54*D54 -> 3.2 | G54: =F54*E54 -> -0.1504 | H54: =B54+F54 -> 43.2 | I54: =C54+G54 -> 2.4496 | J54: =I54/H54 -> 0.056703704
A55: Research | B55: 15.1 | C55: 6.3 | D55: 0.07 | E55: 0.6 | F55: =B55*D55 -> 1.057 | G55: =F55*E55 -> 0.6342 | H55: =B55+F55 -> 16.157 | I55: =C55+G55 -> 6.9342 | J55: =I55/H55 -> 0.42917621
A56: Total Segment | B56: =SUM(B52:B55) -> 413.5 | C56: =SUM(C52:C55) -> 85.4 | H56: =SUM(H52:H55) -> 458.61983 | I56: =SUM(I52:I55) -> 96.548998 | J56: =I56/H56 -> 0.21052077
A58: Head Office Costs & FX Overlay (Group-Level, applied once after segment roll-up)
A59: H1 2026A Head Office Cost (📄 interim Note 3) | C59: -28.6
A60: H2 Head Office Cost growth vs H1 2026A (🔵 assumption) | B60: 0
A61: H2 2026E Head Office Cost | D61: =C59*(1+B60) -> -28.6
A63: Total Segment Operating Profit, H2 2026E (= I56) | D63: =I56 -> 96.548998
A64: Group Operating Profit before FX, H2 2026E (before acquisition-related costs) | D64: =D63+D61 -> 67.948998
A65: Extra H2 credit loss charge vs H1 2026 (🔢 = −(B26 − C65); C65 = H1 2026 net impairment losses, £7.7m, INT26 p.19) | C65: 7.7 | D65: =-(B26-C65) -> 0
A66: GBP/USD H1 2026 average (📄 interim results presentation p.5) | C66: 1.3446
A67: GBP/USD H2 2026E rate path assumption (🔵) | B67: 1.31
A68: Implied USD move vs H1 2026A avg (%) | D68: =(C66-B67)/C66*100 -> 2.573256
A69: FX sensitivity: % change in profit per 1% USD move (📄 AR2025 Note 27, rows 90-94) | B69: =IF(D68>=0,C93,C94) -> 1.2362031
A70: FX effect on Group Operating Profit (%) | D70: =D68*B69 -> 3.181067
A71: Group operating profit, H2 2026E (before acquisition-related costs; after FX and extra credit losses) | D71: =D64*(1+D70/100)+D65 -> 70.110501
A73: Financial H2 growth is 0%. H1 2026 Financial revenue (£48.1m, +66% YoY) was a record half (INT26 p.10: 'a record period for the division'; INT26 p.5: revenue 'approaching the level achieved across the whole of the prior year'), so it is held flat rather than grown further. Financial's own H2 outlook is positive (INT26 p.10: 'Activity levels have remained healthy entering the second half'). This is not based on the Board's group-level comment on H2 weighting.
A74: Two-layer Broking H2 growth (feeds D52)
A75: Layer 1 = in line with the Board's guidance of 31 July 2026 (INT26 p.1, p.6: 'the usual second-half weighting is unlikely this year'; Note 2.4: not significantly seasonal). Layer 2 = the Yemen–Saudi escalation from 9 September 2026, after the Board's statement.
A76: H1 2025 Broking revenue (📄 AR2025/INT26 comparatives) | C76: 222.2 | F76: 222.2 = H1 2025 Broking revenue (INT26 p.7: 'Revenue: £310.3m (2025: £222.2m)'; INT26 Note 3 p.25). Not to be confused with H2 2025 (253.8 = FY 476.0 − H1 222.2; 2025 Prelim Results p.25).
A77: Link H1 2026 revenue contribution (📄 INT26 Note 8) | C77: 8.6
A78: Link days owned in H1 2026 (📄 revenue 'for the period from 18 March 2026', INT26 Note 8 p.28; 18 March to 30 June, counting both ends) | C78: =DATE(2026,6,30)-DATE(2026,3,18)+1 -> 105
A79: H2 2026 total days (🔢 calendar, 1 Jul – 31 Dec 2026 inclusive) | C79: =DATE(2026,12,31)-DATE(2026,7,1)+1 -> 184
A80: Days of H2 affected by the Yemen–Saudi escalation (🌐 start date from news: 9 Sep to 31 Dec 2026, counting both ends) | C80: =DATE(2026,12,31)-DATE(2026,9,9)+1 -> 114
A81: H1 organic Broking growth, YoY, excluding Link (🔢 = (B52 − Link revenue) ÷ H1 2025 Broking revenue − 1) | C81: =(B52-C77)/C76-1 -> 0.35778578
A82: Link revenue for a full H2 (🔢 = Link H1 revenue ÷ days owned × H2 days) | C82: =C77/C78*C79 -> 15.070476
A83: Link annualisation, pp of H1 2026A Broking revenue (🔢) | C83: =(C82-C77)/B52 -> 0.020852324
A84: Escalation-affected fraction of H2 (🔢 = affected days ÷ H2 days) | C84: =C80/C79 -> 0.61956522
A85: Layer 1 — Board-consistent H2 growth (🔢 = 0% organic + Link annualisation) | C85: =0+C83 -> 0.020852324
A86: Layer 2 — escalation overlay (🔵 weight B86 = 0.5: the September escalation is taken as about half the size of the H1 shock, the closure of the Strait of Hormuz) | B86: 0.5 | C86: =C81*C84*B86 -> 0.11083581
A87: Broking H2 growth % — Layer 1 + Layer 2 (feeds D52) | C87: =C85+C86 -> 0.13168814
A89: Source inputs: FX sensitivity and H2 cash-flow anchors
A90: AR2025 Note 27: effect on PBT of a 5% USD strengthening (£m) 📄 AR2025 p.93 | C90: 5.6
A91: AR2025 Note 27: effect on PBT of a 5% USD weakening (£m, absolute) 📄 AR2025 p.93 | C91: 5.1
A92: FY2025 underlying profit before tax (£m) 📄 PRE25 p.1 | C92: 90.6
A93: Sensitivity per 1% USD strengthening (% of PBT) 🔢 = C90 ÷ C92 ÷ 5 × 100 | C93: =C90/C92/5*100 -> 1.2362031
A94: Sensitivity per 1% USD weakening (% of PBT) 🔢 = C91 ÷ C92 ÷ 5 × 100 | C94: =C91/C92/5*100 -> 1.1258278
A96: H2 2025 implied cash conversion (anchor for B34 and D38)
A97: Item (£m, cash outflows shown positive) | C97: FY2025 📄 PRE25 p.23 | D97: H1 2025 📄 INT26 p.22 | E97: H2 2025 🔢 = FY − H1
A98: Purchase of property, plant and equipment | C98: 5.5 | D98: 2.1 | E98: =C98-D98 -> 3.4
A99: Purchase of intangible assets | C99: 1.9 | D99: 0.5 | E99: =C99-D99 -> 1.4
A100: Acquisition of subsidiaries, net of cash acquired | C100: 2.3 | D100: 2.3 | E100: =C100-D100 -> 0
A101: Dividends paid (to parent shareholders) | C101: 33 | D101: 23.1 | E101: =C101-D101 -> 9.9
A102: ESOP shares acquired | C102: 33.4 | D102: 31.6 | E102: =C102-D102 -> 1.8
A103: Principal elements of lease payments | C103: 11.2 | D103: 5.6 | E103: =C103-D103 -> 5.6
A104: Operating profit before acquisition-related costs (📄 PRE25 p.25 / INT26 p.19) | C104: 78 | D104: 32.7 | E104: =C104-D104 -> 45.3
A105: Net cash & available funds, 30 Jun 2025 (📄 INT26 p.30) | C105: 227.1
A106: Net cash & available funds, 31 Dec 2025 (📄 INT26 p.30) | C106: 260.1
A107: H2 2025 cash generated (🔢 = change in net cash + capex + M&A + dividends + ESOP + lease payments, the same items the H2 2026E cash forecast deducts) | E107: =(C106-C105)+SUM(E98:E103) -> 55.1
A108: H2 2025 conversion multiple as reported (🔢 = row 107 ÷ H2 2025 operating profit); for reference, B34 uses row 115 | E108: =E107/E104 -> 1.2163355
A109: Why H2 2025: 'net cash and available funds' is measured after deducting accrued bonuses (INT26 p.30), so the timing of bonus payments does not move it. H2 2025 is the only second half reported on the same basis. The multiple includes interest, tax, FX on cash, NCI flows and share issues, which the forecast does not show separately. It is the same in all scenarios; each scenario's change in receivables is deducted separately (rows 111-116, D34). H1 2026 on the same basis gives about 0.55x (a half with large acquisitions), so 1.22x is not a floor.
...

Sheet Bull Case
A1: Clarkson PLC (LSE: CKN) — H2 2026E / FY2026E Scenario Model: Bull Case
A2: £m unless noted. Blue = input. Black = formula. Green = link to another sheet.
A3: Tags: 📄 = from the filings (page given in the comment); 🔵 = my assumption; 🔢 = calculation; 🌐 = news source, not in the filings.
A4: P&L Forecast (£m)
A5: Item | B5: Assumption | C5: H1 2026A 📄 | D5: H2 2026E | E5: FY2026E | F5: Note / Source
A6: Revenue | C6: 413.5 | D6: =H56 -> 499.71318 | E6: =C6+D6 -> 913.21318 | F6: H2 Revenue = Total Segment H2 2026E Revenue (row 56) — see segment detail below
A7: H2 revenue growth vs. H1 2026 (computed, from segment roll-up) | B7: =D6/C6-1 -> 0.20849621
A8: Underlying Operating Margin, H2 (computed, from segment + HO + FX roll-up) | B8: =D9/D6 -> 0.16541851
A9: Underlying Operating Profit | C9: 56.8 | D9: =D71 -> 82.66181 | E9: =C9+D9 -> 139.46181 | F9: From row 71 (group operating profit after head office costs, FX and extra credit losses). Before acquisition-related costs, like the H1 figure of 56.8 (Summary note 7).
A10: Implied Operating Margin % (check) | C10: =C9/C6 -> 0.13736397 | D10: =D9/D6 -> 0.16541851 | E10: =E9/E6 -> 0.1527155
A11: Net Finance Income (🔵 held constant — see model notes) | B11: 4.7 | C11: 4.7 | D11: =B11 -> 4.7 | E11: =C11+D11 -> 9.4 | F11: £4.7m = H1 2026 underlying PBT (61.5) − underlying operating profit (56.8). This matches the income statement: finance income 6.0, finance costs (1.7) and pension income 0.4 (INT26 p.19). Held flat in H2 and in all scenarios to avoid a circular link with cash (Summary note 2).
A12: Underlying Profit Before Tax | C12: =C9+C11 -> 61.5 | D12: =D9+D11 -> 87.36181 | E12: =C12+D12 -> 148.86181
A13: Tax rate (📄 INT26 Note 5 p.25: expected FY2026 rate excluding acquisition-related costs) | B13: 0.235
A14: Tax | C14: =C12*$B$13 -> 14.4525 | D14: =D12*$B$13 -> 20.530025 | E14: =C14+D14 -> 34.982525
A15: Underlying Net Income | C15: =C12-C14 -> 47.0475 | D15: =D12-D14 -> 66.831785 | E15: =E12-E14 -> 113.87928
A16: NOPAT (operating basis, for ROIC only) | C16: =C9*(1-$B$13) -> 43.452 | D16: =D9*(1-$B$13) -> 63.236285 | E16: =E9*(1-$B$13) -> 106.68828
A18: Receivables, DSO & Credit Losses (£m / days)
A19: Item | B19: Assumption | C19: Jun 2026A 📄 | D19: Dec 2026E | F19: Note / Source
A20: Real DSO (days, ex-T+2 settlement) | B20: =C20 -> 81.474002 | C20: =C22/(C6*2)*365 -> 81.474002 | D20: =B20 -> 81.474002 | F20: Same in all scenarios, at the H1 2026 actual: 184.6 ÷ 827.0 × 365 = 81.47 days (ex-settlement receivables ÷ annualised H1 revenue). There is no evidence that collection differs by scenario.
A21: T+2 Settlement Accounts (🔢 = Jun 2026A × (1 + Financial H2 growth, D53)) | B21: =C21*(1+D53) -> 90.936 | C21: 84.2 | D21: =B21 -> 90.936 | F21: The £84.2m of T+2 settlement balances sit in the Financial division and usually settle two days after the trade (INT26 Note 10 p.29). They are matched by an £84.1m payable, so they are a pass-through, not a credit risk. The balance grows with Financial H2 revenue (D53).
A22: Ex-settlement receivables (trade and other receivables less T+2; the interim balance sheet does not split trade and other) | C22: 184.6 | D22: =D20/365*E6 -> 203.8442 | F22: Dec26E uses FY2026E revenue (E6) — DSO convention per report §5-1
A23: Total Current Receivables | C23: =C21+C22 -> 268.8 | D23: =D21+D22 -> 294.7802
A24: Surface DSO (days, check) | C24: =C23/(C6*2)*365 -> 118.63603 | D24: =D23/E6*365 -> 117.82
A25: ECL Allowance, opening balance | C25: 31.3
A26: H2 Net Impairment Loss / ECL charge (🔵 assumption) | B26: 9.5
A27: ECL Allowance, closing balance | D27: =C25+B26 -> 40.8
A28: ECL charge / H2 revenue | D28: =B26/D6 -> 0.019010905
A29: Allowance / Ex-Settlement Receivables (coverage) | C29: =C25/C22 -> 0.1695558 | D29: =D27/D22 -> 0.20015286
A31: Cash Flow & ROIC (£m)
A32: Item | B32: Assumption | C32: Jun 2026A 📄 | D32: Dec 2026E | F32: Note / Source
A33: Net Cash & Available Funds, opening | C33: 178.8
A34: H2 operating cash flow (🔢 = H2 op. profit × B34 − change in ex-settlement receivables, D22 − C22) | B34: =E115 -> 1.2472406 | D34: =D9*B34-(D22-C22) -> 83.854967 | F34: Formula: D9 × B34 − (D22 − C22). B34 is the H2 2025 conversion before working capital (about 1.25x, row 115). T+2 balances (row 21) are left out because they are matched by payables (INT26 Note 10 p.29).
A35: H2 CAPEX (% of H2 revenue, 🔵 assumption) | B35: 0.01 | D35: =D6*B35 -> 4.9971318
A36: H2 M&A spend (🔵 assumption) | D36: 15
A37: H2 Dividend paid (📄 disclosed: 2026 interim 35p = £10.8m) | D37: 10.8
A38: H2 ESOP buybacks (📄 anchored to H2 2025 actual, row 102) | D38: =E102 -> 1.8
A39: H2 Lease principal repayment (📄 held at H1 2026A actual) | D39: 5.3
A40: Net Cash & Available Funds, closing | D40: =C33+D34-D35-D36-D37-D38-D39 -> 224.75784
A41: Net Assets, opening (derived: Invested Capital + Net Cash) | C41: 549.8 | F41: Simplified: excludes OCI/FX/NCI — see model notes
A42: Net Assets, closing (simplified roll-forward) | D42: =C41+D15-D37-D38 -> 604.03178
A43: Invested Capital, opening (Jun 2026A) | C43: 371
A44: Invested Capital, closing (Dec 2026E) | D44: =D42-D40 -> 379.27395
A45: Invested Capital, FY2025 closing (anchor) | C45: 267.7
A46: Average invested capital, FY2026 (three points: Dec 2025, Jun 2026, Dec 2026E) | D46: =(C45 + 2*C43 + D44)/4 -> 347.24349
A47: ROIC FY2026E (= FY NOPAT ÷ Average Invested Capital) | D47: =E16/D46 -> 0.30724344
A50: Segment revenue and operating profit, H2 2026E (flow-through margin method)
A51: Segment | B51: H1 2026A Revenue 📄 | C51: H1 2026A Op Profit 📄 | D51: H2 Growth % 🔵 | E51: Flow-through Margin % (📄 source) | F51: ΔRevenue | G51: ΔOp Profit | H51: H2 2026E Revenue | I51: H2 2026E Op Profit | J51: H2 2026E Margin %
A52: Broking | B52: 310.3 | C52: 64.8 | D52: =C87 -> 0.24252395 | E52: 0.261 | F52: =B52*D52 -> 75.255181 | G52: =F52*E52 -> 19.641602 | H52: =B52+F52 -> 385.55518 | I52: =C52+G52 -> 84.441602 | J52: =I52/H52 -> 0.21901301
A53: Financial | B53: 48.1 | C53: 11.7 | D53: 0.08 | E53: 0.44 | F53: =B53*D53 -> 3.848 | G53: =F53*E53 -> 1.69312 | H53: =B53+F53 -> 51.948 | I53: =C53+G53 -> 13.39312 | J53: =I53/H53 -> 0.25781782
A54: Support | B54: 40 | C54: 2.6 | D54: 0.14 | E54: 0 | F54: =B54*D54 -> 5.6 | G54: =F54*E54 -> 0 | H54: =B54+F54 -> 45.6 | I54: =C54+G54 -> 2.6 | J54: =I54/H54 -> 0.057017544
A55: Research | B55: 15.1 | C55: 6.3 | D55: 0.1 | E55: 0.6 | F55: =B55*D55 -> 1.51 | G55: =F55*E55 -> 0.906 | H55: =B55+F55 -> 16.61 | I55: =C55+G55 -> 7.206 | J55: =I55/H55 -> 0.43383504
A56: Total Segment | B56: =SUM(B52:B55) -> 413.5 | C56: =SUM(C52:C55) -> 85.4 | H56: =SUM(H52:H55) -> 499.71318 | I56: =SUM(I52:I55) -> 107.64072 | J56: =I56/H56 -> 0.21540501
A58: Head Office Costs & FX Overlay (Group-Level, applied once after segment roll-up)
A59: H1 2026A Head Office Cost (📄 interim Note 3) | C59: -28.6
A60: H2 Head Office Cost growth vs H1 2026A (🔵 assumption) | B60: 0
A61: H2 2026E Head Office Cost | D61: =C59*(1+B60) -> -28.6
A63: Total Segment Operating Profit, H2 2026E (= I56) | D63: =I56 -> 107.64072
A64: Group Operating Profit before FX, H2 2026E (before acquisition-related costs) | D64: =D63+D61 -> 79.040722
A65: Extra H2 credit loss charge vs H1 2026 (🔢 = −(B26 − C65); C65 = H1 2026 net impairment losses, £7.7m, INT26 p.19) | C65: 7.7 | D65: =-(B26-C65) -> -1.8
A66: GBP/USD H1 2026 average (📄 interim results presentation p.5) | C66: 1.3446
A67: GBP/USD H2 2026E rate path assumption (🔵) | B67: 1.27
A68: Implied USD move vs H1 2026A avg (%) | D68: =(C66-B67)/C66*100 -> 5.5481184
A69: FX sensitivity: % change in profit per 1% USD move (📄 AR2025 Note 27, rows 90-94) | B69: =IF(D68>=0,C93,C94) -> 1.2362031
A70: FX effect on Group Operating Profit (%) | D70: =D68*B69 -> 6.8586011
A71: Group operating profit, H2 2026E (before acquisition-related costs; after FX and extra credit losses) | D71: =D64*(1+D70/100)+D65 -> 82.66181
A73: Financial H2 growth is +8%: the actual FY2025 change from H1 to H2 (£28.9m to £31.2m, 2025 Prelim Results p.25), applied to the higher H1 2026 base.
A74: Two-layer Broking H2 growth (feeds D52)
A75: Layer 1 = in line with the Board's guidance of 31 July 2026 (INT26 p.1, p.6: 'the usual second-half weighting is unlikely this year'; Note 2.4: not significantly seasonal). Layer 2 = the Yemen–Saudi escalation from 9 September 2026, after the Board's statement.
A76: H1 2025 Broking revenue (📄 AR2025/INT26 comparatives) | C76: 222.2 | F76: 222.2 = H1 2025 Broking revenue (INT26 p.7: 'Revenue: £310.3m (2025: £222.2m)'; INT26 Note 3 p.25). Not to be confused with H2 2025 (253.8 = FY 476.0 − H1 222.2; 2025 Prelim Results p.25).
A77: Link H1 2026 revenue contribution (📄 INT26 Note 8) | C77: 8.6
A78: Link days owned in H1 2026 (📄 revenue 'for the period from 18 March 2026', INT26 Note 8 p.28; 18 March to 30 June, counting both ends) | C78: =DATE(2026,6,30)-DATE(2026,3,18)+1 -> 105
A79: H2 2026 total days (🔢 calendar, 1 Jul – 31 Dec 2026 inclusive) | C79: =DATE(2026,12,31)-DATE(2026,7,1)+1 -> 184
A80: Days of H2 affected by the Yemen–Saudi escalation (🌐 start date from news: 9 Sep to 31 Dec 2026, counting both ends) | C80: =DATE(2026,12,31)-DATE(2026,9,9)+1 -> 114
A81: H1 organic Broking growth, YoY, excluding Link (🔢 = (B52 − Link revenue) ÷ H1 2025 Broking revenue − 1) | C81: =(B52-C77)/C76-1 -> 0.35778578
A82: Link revenue for a full H2 (🔢 = Link H1 revenue ÷ days owned × H2 days) | C82: =C77/C78*C79 -> 15.070476
A83: Link annualisation, pp of H1 2026A Broking revenue (🔢) | C83: =(C82-C77)/B52 -> 0.020852324
A84: Escalation-affected fraction of H2 (🔢 = affected days ÷ H2 days) | C84: =C80/C79 -> 0.61956522
A85: Layer 1 — Board-consistent H2 growth (🔢 = 0% organic + Link annualisation) | C85: =0+C83 -> 0.020852324
A86: Layer 2 — escalation overlay (🔵 weight B86 = 1.0: upper bound, the September escalation becomes as large as the H1 Hormuz closure) | B86: 1 | C86: =C81*C84*B86 -> 0.22167162
A87: Broking H2 growth % — Layer 1 + Layer 2 (feeds D52) | C87: =C85+C86 -> 0.24252395
A89: Source inputs: FX sensitivity and H2 cash-flow anchors
A90: AR2025 Note 27: effect on PBT of a 5% USD strengthening (£m) 📄 AR2025 p.93 | C90: 5.6
A91: AR2025 Note 27: effect on PBT of a 5% USD weakening (£m, absolute) 📄 AR2025 p.93 | C91: 5.1
A92: FY2025 underlying profit before tax (£m) 📄 PRE25 p.1 | C92: 90.6
A93: Sensitivity per 1% USD strengthening (% of PBT) 🔢 = C90 ÷ C92 ÷ 5 × 100 | C93: =C90/C92/5*100 -> 1.2362031
A94: Sensitivity per 1% USD weakening (% of PBT) 🔢 = C91 ÷ C92 ÷ 5 × 100 | C94: =C91/C92/5*100 -> 1.1258278
A96: H2 2025 implied cash conversion (anchor for B34 and D38)
A97: Item (£m, cash outflows shown positive) | C97: FY2025 📄 PRE25 p.23 | D97: H1 2025 📄 INT26 p.22 | E97: H2 2025 🔢 = FY − H1
A98: Purchase of property, plant and equipment | C98: 5.5 | D98: 2.1 | E98: =C98-D98 -> 3.4
A99: Purchase of intangible assets | C99: 1.9 | D99: 0.5 | E99: =C99-D99 -> 1.4
A100: Acquisition of subsidiaries, net of cash acquired | C100: 2.3 | D100: 2.3 | E100: =C100-D100 -> 0
A101: Dividends paid (to parent shareholders) | C101: 33 | D101: 23.1 | E101: =C101-D101 -> 9.9
A102: ESOP shares acquired | C102: 33.4 | D102: 31.6 | E102: =C102-D102 -> 1.8
A103: Principal elements of lease payments | C103: 11.2 | D103: 5.6 | E103: =C103-D103 -> 5.6
A104: Operating profit before acquisition-related costs (📄 PRE25 p.25 / INT26 p.19) | C104: 78 | D104: 32.7 | E104: =C104-D104 -> 45.3
A105: Net cash & available funds, 30 Jun 2025 (📄 INT26 p.30) | C105: 227.1
A106: Net cash & available funds, 31 Dec 2025 (📄 INT26 p.30) | C106: 260.1
A107: H2 2025 cash generated (🔢 = change in net cash + capex + M&A + dividends + ESOP + lease payments, the same items the H2 2026E cash forecast deducts) | E107: =(C106-C105)+SUM(E98:E103) -> 55.1
A108: H2 2025 conversion multiple as reported (🔢 = row 107 ÷ H2 2025 operating profit); for reference, B34 uses row 115 | E108: =E107/E104 -> 1.2163355
A109: Why H2 2025: 'net cash and available funds' is measured after deducting accrued bonuses (INT26 p.30), so the timing of bonus payments does not move it. H2 2025 is the only second half reported on the same basis. The multiple includes interest, tax, FX on cash, NCI flows and share issues, which the forecast does not show separately. It is the same in all scenarios; each scenario's change in receivables is deducted separately (rows 111-116, D34). H1 2026 on the same basis gives about 0.55x (a half with large acquisitions), so 1.22x is not a floor.
...

Sheet Bear Case
A1: Clarkson PLC (LSE: CKN) — H2 2026E / FY2026E Scenario Model: Bear Case
A2: £m unless noted. Blue = input. Black = formula. Green = link to another sheet.
A3: Tags: 📄 = from the filings (page given in the comment); 🔵 = my assumption; 🔢 = calculation; 🌐 = news source, not in the filings.
A4: P&L Forecast (£m)
A5: Item | B5: Assumption | C5: H1 2026A 📄 | D5: H2 2026E | E5: FY2026E | F5: Note / Source
A6: Revenue | C6: 413.5 | D6: =H56 -> 388.486 | E6: =C6+D6 -> 801.986 | F6: H2 Revenue = Total Segment H2 2026E Revenue (row 56) — see segment detail below
A7: H2 revenue growth vs. H1 2026 (computed, from segment roll-up) | B7: =D6/C6-1 -> -0.060493349
A8: Underlying Operating Margin, H2 (computed, from segment + HO + FX roll-up) | B8: =D9/D6 -> 0.096340415
A9: Underlying Operating Profit | C9: 56.8 | D9: =D71 -> 37.426903 | E9: =C9+D9 -> 94.226903 | F9: From row 71 (group operating profit after head office costs, FX and extra credit losses). Before acquisition-related costs, like the H1 figure of 56.8 (Summary note 7).
A10: Implied Operating Margin % (check) | C10: =C9/C6 -> 0.13736397 | D10: =D9/D6 -> 0.096340415 | E10: =E9/E6 -> 0.11749195
A11: Net Finance Income (🔵 held constant — see model notes) | B11: 4.7 | C11: 4.7 | D11: =B11 -> 4.7 | E11: =C11+D11 -> 9.4 | F11: £4.7m = H1 2026 underlying PBT (61.5) − underlying operating profit (56.8). This matches the income statement: finance income 6.0, finance costs (1.7) and pension income 0.4 (INT26 p.19). Held flat in H2 and in all scenarios to avoid a circular link with cash (Summary note 2).
A12: Underlying Profit Before Tax | C12: =C9+C11 -> 61.5 | D12: =D9+D11 -> 42.126903 | E12: =C12+D12 -> 103.6269
A13: Tax rate (📄 INT26 Note 5 p.25: expected FY2026 rate excluding acquisition-related costs) | B13: 0.235
A14: Tax | C14: =C12*$B$13 -> 14.4525 | D14: =D12*$B$13 -> 9.8998221 | E14: =C14+D14 -> 24.352322
A15: Underlying Net Income | C15: =C12-C14 -> 47.0475 | D15: =D12-D14 -> 32.22708 | E15: =E12-E14 -> 79.27458
A16: NOPAT (operating basis, for ROIC only) | C16: =C9*(1-$B$13) -> 43.452 | D16: =D9*(1-$B$13) -> 28.63158 | E16: =E9*(1-$B$13) -> 72.08358
A18: Receivables, DSO & Credit Losses (£m / days)
A19: Item | B19: Assumption | C19: Jun 2026A 📄 | D19: Dec 2026E | F19: Note / Source
A20: Real DSO (days, ex-T+2 settlement) | B20: =C20 -> 81.474002 | C20: =C22/(C6*2)*365 -> 81.474002 | D20: =B20 -> 81.474002 | F20: Same in all scenarios, at the H1 2026 actual: 184.6 ÷ 827.0 × 365 = 81.47 days (ex-settlement receivables ÷ annualised H1 revenue). There is no evidence that collection differs by scenario.
A21: T+2 Settlement Accounts (🔢 = Jun 2026A × (1 + Financial H2 growth, D53)) | B21: =C21*(1+D53) -> 81.674 | C21: 84.2 | D21: =B21 -> 81.674 | F21: The £84.2m of T+2 settlement balances sit in the Financial division and usually settle two days after the trade (INT26 Note 10 p.29). They are matched by an £84.1m payable, so they are a pass-through, not a credit risk. The balance grows with Financial H2 revenue (D53).
A22: Ex-settlement receivables (trade and other receivables less T+2; the interim balance sheet does not split trade and other) | C22: 184.6 | D22: =D20/365*E6 -> 179.01646 | F22: Dec26E uses FY2026E revenue (E6) — DSO convention per report §5-1
A23: Total Current Receivables | C23: =C21+C22 -> 268.8 | D23: =D21+D22 -> 260.69046
A24: Surface DSO (days, check) | C24: =C23/(C6*2)*365 -> 118.63603 | D24: =D23/E6*365 -> 118.64549
A25: ECL Allowance, opening balance | C25: 31.3
A26: H2 Net Impairment Loss / ECL charge (🔵 assumption) | B26: 11.5
A27: ECL Allowance, closing balance | D27: =C25+B26 -> 42.8
A28: ECL charge / H2 revenue | D28: =B26/D6 -> 0.029602096
A29: Allowance / Ex-Settlement Receivables (coverage) | C29: =C25/C22 -> 0.1695558 | D29: =D27/D22 -> 0.23908416
A31: Cash Flow & ROIC (£m)
A32: Item | B32: Assumption | C32: Jun 2026A 📄 | D32: Dec 2026E | F32: Note / Source
A33: Net Cash & Available Funds, opening | C33: 178.8
A34: H2 operating cash flow (🔢 = H2 op. profit × B34 − change in ex-settlement receivables, D22 − C22) | B34: =E115 -> 1.2472406 | D34: =D9*B34-(D22-C22) -> 52.263889 | F34: Formula: D9 × B34 − (D22 − C22). B34 is the H2 2025 conversion before working capital (about 1.25x, row 115). T+2 balances (row 21) are left out because they are matched by payables (INT26 Note 10 p.29).
A35: H2 CAPEX (% of H2 revenue, 🔵 assumption) | B35: 0.01 | D35: =D6*B35 -> 3.88486
A36: H2 M&A spend (🔵 assumption) | D36: 5
A37: H2 Dividend paid (📄 disclosed: 2026 interim 35p = £10.8m) | D37: 10.8
A38: H2 ESOP buybacks (📄 anchored to H2 2025 actual, row 102) | D38: =E102 -> 1.8
A39: H2 Lease principal repayment (📄 held at H1 2026A actual) | D39: 5.3
A40: Net Cash & Available Funds, closing | D40: =C33+D34-D35-D36-D37-D38-D39 -> 204.27903
A41: Net Assets, opening (derived: Invested Capital + Net Cash) | C41: 549.8 | F41: Simplified: excludes OCI/FX/NCI — see model notes
A42: Net Assets, closing (simplified roll-forward) | D42: =C41+D15-D37-D38 -> 569.42708
A43: Invested Capital, opening (Jun 2026A) | C43: 371
A44: Invested Capital, closing (Dec 2026E) | D44: =D42-D40 -> 365.14805
A45: Invested Capital, FY2025 closing (anchor) | C45: 267.7
A46: Average invested capital, FY2026 (three points: Dec 2025, Jun 2026, Dec 2026E) | D46: =(C45 + 2*C43 + D44)/4 -> 343.71201
A47: ROIC FY2026E (= FY NOPAT ÷ Average Invested Capital) | D47: =E16/D46 -> 0.20972086
A50: Segment revenue and operating profit, H2 2026E (flow-through margin method)
A51: Segment | B51: H1 2026A Revenue 📄 | C51: H1 2026A Op Profit 📄 | D51: H2 Growth % 🔵 | E51: Flow-through Margin % (📄 source) | F51: ΔRevenue | G51: ΔOp Profit | H51: H2 2026E Revenue | I51: H2 2026E Op Profit | J51: H2 2026E Margin %
A52: Broking | B52: 310.3 | C52: 64.8 | D52: -0.08 | E52: 0.538 | F52: =B52*D52 -> -24.824 | G52: =F52*E52 -> -13.355312 | H52: =B52+F52 -> 285.476 | I52: =C52+G52 -> 51.444688 | J52: =I52/H52 -> 0.1802067
A53: Financial | B53: 48.1 | C53: 11.7 | D53: -0.03 | E53: 0.933 | F53: =B53*D53 -> -1.443 | G53: =F53*E53 -> -1.346319 | H53: =B53+F53 -> 46.657 | I53: =C53+G53 -> 10.353681 | J53: =I53/H53 -> 0.22191056
A54: Support | B54: 40 | C54: 2.6 | D54: 0.02 | E54: -0.2 | F54: =B54*D54 -> 0.8 | G54: =F54*E54 -> -0.16 | H54: =B54+F54 -> 40.8 | I54: =C54+G54 -> 2.44 | J54: =I54/H54 -> 0.059803922
A55: Research | B55: 15.1 | C55: 6.3 | D55: 0.03 | E55: 0.407 | F55: =B55*D55 -> 0.453 | G55: =F55*E55 -> 0.184371 | H55: =B55+F55 -> 15.553 | I55: =C55+G55 -> 6.484371 | J55: =I55/H55 -> 0.41692092
A56: Total Segment | B56: =SUM(B52:B55) -> 413.5 | C56: =SUM(C52:C55) -> 85.4 | H56: =SUM(H52:H55) -> 388.486 | I56: =SUM(I52:I55) -> 70.72274 | J56: =I56/H56 -> 0.18204708
A58: Head Office Costs & FX Overlay (Group-Level, applied once after segment roll-up)
A59: H1 2026A Head Office Cost (📄 interim Note 3) | C59: -28.6
A60: H2 Head Office Cost growth vs H1 2026A (🔵 assumption) | B60: 0
A61: H2 2026E Head Office Cost | D61: =C59*(1+B60) -> -28.6
A63: Total Segment Operating Profit, H2 2026E (= I56) | D63: =I56 -> 70.72274
A64: Group Operating Profit before FX, H2 2026E (before acquisition-related costs) | D64: =D63+D61 -> 42.12274
A65: Extra H2 credit loss charge vs H1 2026 (🔢 = −(B26 − C65); C65 = H1 2026 net impairment losses, £7.7m, INT26 p.19) | C65: 7.7 | D65: =-(B26-C65) -> -3.8
A66: GBP/USD H1 2026 average (📄 interim results presentation p.5) | C66: 1.3446
A67: GBP/USD H2 2026E rate path assumption (🔵) | B67: 1.37
A68: Implied USD move vs H1 2026A avg (%) | D68: =(C66-B67)/C66*100 -> -1.8890376
A69: FX sensitivity: % change in profit per 1% USD move (📄 AR2025 Note 27, rows 90-94) | B69: =IF(D68>=0,C93,C94) -> 1.1258278
A70: FX effect on Group Operating Profit (%) | D70: =D68*B69 -> -2.1267311
A71: Group operating profit, H2 2026E (before acquisition-related costs; after FX and extra credit losses) | D71: =D64*(1+D70/100)+D65 -> 37.426903
A73: Bear does not use the two layers. It follows the Board's downside path (the Strait reopens, trapped vessels are released and rates normalise), so there is no escalation overlay: Broking −8%, Financial −3%.
A89: Source inputs: FX sensitivity and H2 cash-flow anchors
A90: AR2025 Note 27: effect on PBT of a 5% USD strengthening (£m) 📄 AR2025 p.93 | C90: 5.6
A91: AR2025 Note 27: effect on PBT of a 5% USD weakening (£m, absolute) 📄 AR2025 p.93 | C91: 5.1
A92: FY2025 underlying profit before tax (£m) 📄 PRE25 p.1 | C92: 90.6
A93: Sensitivity per 1% USD strengthening (% of PBT) 🔢 = C90 ÷ C92 ÷ 5 × 100 | C93: =C90/C92/5*100 -> 1.2362031
A94: Sensitivity per 1% USD weakening (% of PBT) 🔢 = C91 ÷ C92 ÷ 5 × 100 | C94: =C91/C92/5*100 -> 1.1258278
A96: H2 2025 implied cash conversion (anchor for B34 and D38)
A97: Item (£m, cash outflows shown positive) | C97: FY2025 📄 PRE25 p.23 | D97: H1 2025 📄 INT26 p.22 | E97: H2 2025 🔢 = FY − H1
A98: Purchase of property, plant and equipment | C98: 5.5 | D98: 2.1 | E98: =C98-D98 -> 3.4
A99: Purchase of intangible assets | C99: 1.9 | D99: 0.5 | E99: =C99-D99 -> 1.4
A100: Acquisition of subsidiaries, net of cash acquired | C100: 2.3 | D100: 2.3 | E100: =C100-D100 -> 0
A101: Dividends paid (to parent shareholders) | C101: 33 | D101: 23.1 | E101: =C101-D101 -> 9.9
A102: ESOP shares acquired | C102: 33.4 | D102: 31.6 | E102: =C102-D102 -> 1.8
A103: Principal elements of lease payments | C103: 11.2 | D103: 5.6 | E103: =C103-D103 -> 5.6
A104: Operating profit before acquisition-related costs (📄 PRE25 p.25 / INT26 p.19) | C104: 78 | D104: 32.7 | E104: =C104-D104 -> 45.3
A105: Net cash & available funds, 30 Jun 2025 (📄 INT26 p.30) | C105: 227.1
A106: Net cash & available funds, 31 Dec 2025 (📄 INT26 p.30) | C106: 260.1
A107: H2 2025 cash generated (🔢 = change in net cash + capex + M&A + dividends + ESOP + lease payments, the same items the H2 2026E cash forecast deducts) | E107: =(C106-C105)+SUM(E98:E103) -> 55.1
A108: H2 2025 conversion multiple as reported (🔢 = row 107 ÷ H2 2025 operating profit); for reference, B34 uses row 115 | E108: =E107/E104 -> 1.2163355
A109: Why H2 2025: 'net cash and available funds' is measured after deducting accrued bonuses (INT26 p.30), so the timing of bonus payments does not move it. H2 2025 is the only second half reported on the same basis. The multiple includes interest, tax, FX on cash, NCI flows and share issues, which the forecast does not show separately. It is the same in all scenarios; each scenario's change in receivables is deducted separately (rows 111-116, D34). H1 2026 on the same basis gives about 0.55x (a half with large acquisitions), so 1.22x is not a floor.
A111: H2 2025 working capital: removes H2 2025's own change in receivables from the multiple
A112: Increase in trade and other receivables, cash flow statement (C = FY2025, PRE25 p.23; D = H1 2025, INT26 p.22) | C112: 67.5 | D112: 22.2 | E112: =C112-D112 -> 45.3
A113: T+2 settlement balances in trade receivables (C = 31 Dec 2025, D = 30 Jun 2025; INT26 Note 10 p.29) | C113: 60.9 | D113: 17 | E113: =C113-D113 -> 43.9
A114: H2 2025 increase in ex-settlement receivables (🔢 = E112 − E113; T+2 balances are matched by payables, so they do not affect cash) | E114: =E112-E113 -> 1.4
A115: H2 2025 conversion multiple before working capital (🔢 = (E107 + E114) ÷ E104), used in B34 | E115: =(E107+E114)/E104 -> 1.2472406
A116: H2 2026E operating cash flow (D34) = H2 operating profit × E115 (about 1.25x) − the change in ex-settlement receivables (D22 − C22), so each scenario's build or release of receivables affects cash. In H2 2025 these receivables hardly moved (+£1.4m: trade and other receivables rose £45.3m, of which £43.9m was T+2 balances), so E115 is close to the reported 1.22x. T+2 balances are left out in both periods because they are matched by payables (£84.2m vs £84.1m at 30 June 2026). Limitation: the multiple rests on one half-year, and payables and the bonus accrual are not modelled by scenario.

Sheet Scenario Charts
A1: Clarkson PLC — FY2026E Scenario Comparison Charts
A2: Data below links live to the Summary sheet.
A4: Revenue (£m) | D4: Profitability (£m)
A5: Scenario | B5: Revenue | D5: Scenario | E5: Operating Profit | F5: Net Income | G5: NOPAT
A6: Base Case | B6: =Summary!B5 -> 872.11983 | D6: Base Case | E6: =Summary!B6 -> 126.9105 | F6: =Summary!B8 -> 104.27753 | G6: =Summary!B9 -> 97.086534
A7: Bull Case | B7: =Summary!C5 -> 913.21318 | D7: Bull Case | E7: =Summary!C6 -> 139.46181 | F7: =Summary!C8 -> 113.87928 | G7: =Summary!C9 -> 106.68828
A8: Bear Case | B8: =Summary!D5 -> 801.986 | D8: Bear Case | E8: =Summary!D6 -> 94.226903 | F8: =Summary!D8 -> 79.27458 | G8: =Summary!D9 -> 72.08358
A10: Margins & Returns (%)
A11: Scenario | B11: Operating Margin % | C11: ROIC %
A12: Base Case | B12: =Summary!B7 -> 0.14551957 | C12: =Summary!B15 -> 0.28131992
A13: Bull Case | B13: =Summary!C7 -> 0.1527155 | C13: =Summary!C15 -> 0.30724344
A14: Bear Case | B14: =Summary!D7 -> 0.11749195 | C14: =Summary!D15 -> 0.20972086
