Workbook

Sheet README_Sources
A1: FX_Data.xlsx — README & source catalog (Step 1: raw data only, no analysis)
A2: As-of date: 2026-10-07 | Retrieval date: 2026-10-07 | Blue font = raw value from source; black = formula.
A3: Scope: USD, KRW, NOK, GBP, EUR (France + Germany share EUR), CNY; BRL and JPY only as reference for one test. History: FX daily 2016-01-01→latest; rates & CPI monthly 2016→latest; annual macro 2010→latest + IMF forecasts 2026-2028. Quote direction is always written as "X per Y" (= units of X for 1 Y).
A5: Sheet | B5: Column / block | C5: Provider | D5: Series ID / table | E5: Description | F5: URL | G5: Unit | H5: Frequency | I5: First obs | J5: Last obs | K5: Retrieval date | L5: Notes
A6: FX_Daily | B6: B (KRW per USD) | C6: FRED (St. Louis Fed); original source Federal Reserve Board H.10 | D6: DEXKOUS | E6: South Korean Won to U.S. Dollar Spot Exchange Rate (DEXKOUS) | F6: https://fred.stlouisfed.org/series/DEXKOUS | G6: South Korean Won to One U.S. Dollar | H6: Daily | I6: =FX_Daily!B10 -> 42373 | J6: =FX_Daily!B11 -> 46297 | K6: 2026-10-07
A7: FX_Daily | B7: C (NOK per USD) | C7: FRED (St. Louis Fed); original source Federal Reserve Board H.10 | D7: DEXNOUS | E7: Norwegian Kroner to U.S. Dollar Spot Exchange Rate (DEXNOUS) | F7: https://fred.stlouisfed.org/series/DEXNOUS | G7: Norwegian Kroner to One U.S. Dollar | H7: Daily | I7: =FX_Daily!C10 -> 42373 | J7: =FX_Daily!C11 -> 46297 | K7: 2026-10-07
A8: FX_Daily | B8: D (USD per GBP) | C8: FRED (St. Louis Fed); original source Federal Reserve Board H.10 | D8: DEXUSUK | E8: U.S. Dollars to U.K. Pound Sterling Spot Exchange Rate (DEXUSUK) | F8: https://fred.stlouisfed.org/series/DEXUSUK | G8: U.S. Dollars to One U.K. Pound Sterling | H8: Daily | I8: =FX_Daily!D10 -> 42373 | J8: =FX_Daily!D11 -> 46297 | K8: 2026-10-07
A9: FX_Daily | B9: E (USD per EUR) | C9: FRED (St. Louis Fed); original source Federal Reserve Board H.10 | D9: DEXUSEU | E9: U.S. Dollars to Euro Spot Exchange Rate (DEXUSEU) | F9: https://fred.stlouisfed.org/series/DEXUSEU | G9: U.S. Dollars to One Euro | H9: Daily | I9: =FX_Daily!E10 -> 42373 | J9: =FX_Daily!E11 -> 46297 | K9: 2026-10-07
A10: FX_Daily | B10: F (CNY per USD) | C10: FRED (St. Louis Fed); original source Federal Reserve Board H.10 | D10: DEXCHUS | E10: Chinese Yuan Renminbi to U.S. Dollar Spot Exchange Rate (DEXCHUS) | F10: https://fred.stlouisfed.org/series/DEXCHUS | G10: Chinese Yuan Renminbi to One U.S. Dollar | H10: Daily | I10: =FX_Daily!F10 -> 42373 | J10: =FX_Daily!F11 -> 46297 | K10: 2026-10-07
A11: FX_Daily | B11: G (BRL per USD (reference only)) | C11: FRED (St. Louis Fed); original source Federal Reserve Board H.10 | D11: DEXBZUS | E11: Brazilian Reals to U.S. Dollar Spot Exchange Rate (DEXBZUS) | F11: https://fred.stlouisfed.org/series/DEXBZUS | G11: Brazilian Reals to One U.S. Dollar | H11: Daily | I11: =FX_Daily!G10 -> 42373 | J11: =FX_Daily!G11 -> 46297 | K11: 2026-10-07
A12: FX_Daily | B12: H (JPY per USD (reference only)) | C12: FRED (St. Louis Fed); original source Federal Reserve Board H.10 | D12: DEXJPUS | E12: Japanese Yen to U.S. Dollar Spot Exchange Rate (DEXJPUS) | F12: https://fred.stlouisfed.org/series/DEXJPUS | G12: Japanese Yen to One U.S. Dollar | H12: Daily | I12: =FX_Daily!H10 -> 42373 | J12: =FX_Daily!H11 -> 46297 | K12: 2026-10-07
A13: FX_Daily | B13: I (USD per EUR (ECB ref.)) | C13: European Central Bank (ECB Data Portal) | D13: EXR.D.USD.EUR.SP00.A | E13: US dollar/Euro ECB reference exchange rate — USD per 1 EUR | F13: https://data.ecb.europa.eu/data/datasets/EXR/EXR.D.USD.EUR.SP00.A | G13: USD per 1 EUR | H13: Daily (TARGET days, 14:15 CET) | I13: =FX_Daily!I10 -> 42373 | J13: =FX_Daily!I11 -> 46301 | K13: 2026-10-07
A14: FX_Daily | B14: J (NOK per EUR (ECB ref.)) | C14: European Central Bank (ECB Data Portal) | D14: EXR.D.NOK.EUR.SP00.A | E14: Norwegian krone/Euro ECB reference exchange rate — NOK per 1 EUR | F14: https://data.ecb.europa.eu/data/datasets/EXR/EXR.D.NOK.EUR.SP00.A | G14: NOK per 1 EUR | H14: Daily (TARGET days, 14:15 CET) | I14: =FX_Daily!J10 -> 42373 | J14: =FX_Daily!J11 -> 46301 | K14: 2026-10-07
A15: FX_Daily | B15: K (KRW per EUR (ECB ref.)) | C15: European Central Bank (ECB Data Portal) | D15: EXR.D.KRW.EUR.SP00.A | E15: South Korean won/Euro ECB reference exchange rate — KRW per 1 EUR | F15: https://data.ecb.europa.eu/data/datasets/EXR/EXR.D.KRW.EUR.SP00.A | G15: KRW per 1 EUR | H15: Daily (TARGET days, 14:15 CET) | I15: =FX_Daily!K10 -> 42373 | J15: =FX_Daily!K11 -> 46301 | K15: 2026-10-07
A16: FX_Daily | B16: L (GBP per EUR (ECB ref.)) | C16: European Central Bank (ECB Data Portal) | D16: EXR.D.GBP.EUR.SP00.A | E16: Pound sterling/Euro ECB reference exchange rate — GBP per 1 EUR | F16: https://data.ecb.europa.eu/data/datasets/EXR/EXR.D.GBP.EUR.SP00.A | G16: GBP per 1 EUR | H16: Daily (TARGET days, 14:15 CET) | I16: =FX_Daily!L10 -> 42373 | J16: =FX_Daily!L11 -> 46301 | K16: 2026-10-07
A17: FX_Daily | B17: M (CNY per EUR (ECB ref.)) | C17: European Central Bank (ECB Data Portal) | D17: EXR.D.CNY.EUR.SP00.A | E17: Chinese yuan renminbi/Euro ECB reference exchange rate — CNY per 1 EUR | F17: https://data.ecb.europa.eu/data/datasets/EXR/EXR.D.CNY.EUR.SP00.A | G17: CNY per 1 EUR | H17: Daily (TARGET days, 14:15 CET) | I17: =FX_Daily!M10 -> 42373 | J17: =FX_Daily!M11 -> 46301 | K17: 2026-10-07
A18: FX_Daily | B18: N (BRL per EUR (ECB ref.)) | C18: European Central Bank (ECB Data Portal) | D18: EXR.D.BRL.EUR.SP00.A | E18: Brazilian real/Euro ECB reference exchange rate — BRL per 1 EUR | F18: https://data.ecb.europa.eu/data/datasets/EXR/EXR.D.BRL.EUR.SP00.A | G18: BRL per 1 EUR | H18: Daily (TARGET days, 14:15 CET) | I18: =FX_Daily!N10 -> 42373 | J18: =FX_Daily!N11 -> 46301 | K18: 2026-10-07
A19: FX_Daily | B19: O (JPY per EUR (ECB ref.)) | C19: European Central Bank (ECB Data Portal) | D19: EXR.D.JPY.EUR.SP00.A | E19: Japanese yen/Euro ECB reference exchange rate — JPY per 1 EUR | F19: https://data.ecb.europa.eu/data/datasets/EXR/EXR.D.JPY.EUR.SP00.A | G19: JPY per 1 EUR | H19: Daily (TARGET days, 14:15 CET) | I19: =FX_Daily!O10 -> 42373 | J19: =FX_Daily!O11 -> 46301 | K19: 2026-10-07
A20: FX_Daily | B20: P (NOK per USD (Norges Bank)) | C20: Norges Bank (data.norges-bank.no) | D20: EXR/B.USD.NOK.SP | E20: Norges Bank daily exchange rate, NOK per 1 USD (midday fixing) | F20: https://data.norges-bank.no/api/data/EXR/B.USD.NOK.SP?format=csv | G20: NOK per 1 USD | H20: Daily (Norwegian business days) | I20: =FX_Daily!P10 -> 42373 | J20: =FX_Daily!P11 -> 46301 | K20: 2026-10-07
A21: FX_Monthly | B21: B:P | C21: Derived (formula) | D21: AVERAGEIFS on FX_Daily | E21: Monthly average of every FX_Daily series; same quote direction as FX_Daily | G21: as FX_Daily | H21: Monthly | I21: =FX_Monthly!B10 -> 42370 | J21: =FX_Monthly!B11 -> 46296 | K21: 2026-10-07 | L21: Derived, not a separate source series. Current month flagged "partial month".
A22: Rates_Daily | B22: B (USD SOFR (O/N)) | C22: FRED (St. Louis Fed) | D22: SOFR | E22: Secured Overnight Financing Rate (SOFR) | F22: https://fred.stlouisfed.org/series/SOFR | G22: Percent | H22: Daily | I22: =Rates_Daily!B10 -> 43193 | J22: =Rates_Daily!B11 -> 46300 | K22: 2026-10-07
A23: Rates_Daily | B23: C (USD Fed funds target — upper) | C23: FRED (St. Louis Fed) | D23: DFEDTARU | E23: Federal Funds Target Range - Upper Limit (DFEDTARU) | F23: https://fred.stlouisfed.org/series/DFEDTARU | G23: Percent | H23: Daily | I23: =Rates_Daily!C10 -> 42370 | J23: =Rates_Daily!C11 -> 46301 | K23: 2026-10-07
A24: Rates_Daily | B24: D (USD Fed funds target — lower) | C24: FRED (St. Louis Fed) | D24: DFEDTARL | E24: Federal Funds Target Range - Lower Limit (DFEDTARL) | F24: https://fred.stlouisfed.org/series/DFEDTARL | G24: Percent | H24: Daily | I24: =Rates_Daily!D10 -> 42370 | J24: =Rates_Daily!D11 -> 46301 | K24: 2026-10-07
A25: Rates_Daily | B25: E (EUR €STR (O/N)) | C25: European Central Bank (ECB Data Portal) | D25: EST.B.EU000A2X2A25.WT | E25: Euro short-term rate | F25: https://data.ecb.europa.eu/data/datasets/EST/EST.B.EU000A2X2A25.WT | G25: % p.a. | H25: Daily (TARGET days) | I25: =Rates_Daily!E10 -> 43739 | J25: =Rates_Daily!E11 -> 46301 | K25: 2026-10-07
A26: Rates_Daily | B26: F (EUR ECB deposit facility rate) | C26: European Central Bank (ECB Data Portal) | D26: FM.D.U2.EUR.4F.KR.DFR.LEV | E26: Deposit facility - date of changes (raw data) - Level | F26: https://data.ecb.europa.eu/data/datasets/FM/FM.D.U2.EUR.4F.KR.DFR.LEV | G26: % p.a. | H26: Daily (calendar) | I26: =Rates_Daily!F10 -> 42370 | J26: =Rates_Daily!F11 -> 46302 | K26: 2026-10-07
A27: Rates_Daily | B27: G (GBP Bank Rate) | C27: Bank of England (IADB) | D27: IUDBEDR | E27: Official Bank Rate, daily | F27: https://www.bankofengland.co.uk/boeapps/database/?SeriesCodes=IUDBEDR | G27: % p.a. | H27: Daily | I27: =Rates_Daily!G10 -> 42373 | J27: =Rates_Daily!G11 -> 46301 | K27: 2026-10-07
A28: Rates_Daily | B28: H (GBP SONIA (O/N)) | C28: Bank of England (IADB) | D28: IUDSOIA | E28: Sterling Overnight Index Average, daily | F28: https://www.bankofengland.co.uk/boeapps/database/?SeriesCodes=IUDSOIA | G28: % p.a. | H28: Daily | I28: =Rates_Daily!H10 -> 42373 | J28: =Rates_Daily!H11 -> 46300 | K28: 2026-10-07
A29: Rates_Daily | B29: I (GBP OIS spot 1M) | C29: Bank of England (yield curve data) | D29: UK OIS spot curve, 1M maturity | E29: BoE estimated UK OIS (SONIA) spot rate, 1M maturity, continuously compounded per BoE methodology | F29: https://www.bankofengland.co.uk/statistics/yield-curves (files: oisddata.zip, latest-yield-curve-data.zip; sheet "3. spot, short end") | G29: % p.a. | H29: Daily | I29: =Rates_Daily!I10 -> 42373 | J29: =Rates_Daily!I11 -> 46300 | K29: 2026-10-07
A30: Rates_Daily | B30: J (GBP OIS spot 3M) | C30: Bank of England (yield curve data) | D30: UK OIS spot curve, 3M maturity | E30: BoE estimated UK OIS (SONIA) spot rate, 3M maturity, continuously compounded per BoE methodology | F30: https://www.bankofengland.co.uk/statistics/yield-curves (files: oisddata.zip, latest-yield-curve-data.zip; sheet "3. spot, short end") | G30: % p.a. | H30: Daily | I30: =Rates_Daily!J10 -> 42373 | J30: =Rates_Daily!J11 -> 46300 | K30: 2026-10-07
A31: Rates_Daily | B31: K (GBP OIS spot 6M) | C31: Bank of England (yield curve data) | D31: UK OIS spot curve, 6M maturity | E31: BoE estimated UK OIS (SONIA) spot rate, 6M maturity, continuously compounded per BoE methodology | F31: https://www.bankofengland.co.uk/statistics/yield-curves (files: oisddata.zip, latest-yield-curve-data.zip; sheet "3. spot, short end") | G31: % p.a. | H31: Daily | I31: =Rates_Daily!K10 -> 42373 | J31: =Rates_Daily!K11 -> 46300 | K31: 2026-10-07
A32: Rates_Daily | B32: L (GBP OIS spot 12M) | C32: Bank of England (yield curve data) | D32: UK OIS spot curve, 12M maturity | E32: BoE estimated UK OIS (SONIA) spot rate, 12M maturity, continuously compounded per BoE methodology | F32: https://www.bankofengland.co.uk/statistics/yield-curves (files: oisddata.zip, latest-yield-curve-data.zip; sheet "3. spot, short end") | G32: % p.a. | H32: Daily | I32: =Rates_Daily!L10 -> 42373 | J32: =Rates_Daily!L11 -> 46300 | K32: 2026-10-07
A33: Rates_Daily | B33: M (CNY Shibor 1M) | C33: CFETS / National Interbank Funding Center (chinamoney.com.cn) | D33: Shibor 1M | E33: Shanghai Interbank Offered Rate, 1M tenor | F33: https://www.chinamoney.com.cn/english/bmkshibor/ (API: /ags/ms/cm-u-bk-shibor/ShiborHis) | G33: % p.a. | H33: Daily (China business days) | I33: =Rates_Daily!M10 -> 42373 | J33: =Rates_Daily!M11 -> 46295 | K33: 2026-10-07
A34: Rates_Daily | B34: N (CNY Shibor 3M) | C34: CFETS / National Interbank Funding Center (chinamoney.com.cn) | D34: Shibor 3M | E34: Shanghai Interbank Offered Rate, 3M tenor | F34: https://www.chinamoney.com.cn/english/bmkshibor/ (API: /ags/ms/cm-u-bk-shibor/ShiborHis) | G34: % p.a. | H34: Daily (China business days) | I34: =Rates_Daily!N10 -> 42373 | J34: =Rates_Daily!N11 -> 46295 | K34: 2026-10-07
A35: Rates_Daily | B35: O (CNY Shibor 6M) | C35: CFETS / National Interbank Funding Center (chinamoney.com.cn) | D35: Shibor 6M | E35: Shanghai Interbank Offered Rate, 6M tenor | F35: https://www.chinamoney.com.cn/english/bmkshibor/ (API: /ags/ms/cm-u-bk-shibor/ShiborHis) | G35: % p.a. | H35: Daily (China business days) | I35: =Rates_Daily!O10 -> 42373 | J35: =Rates_Daily!O11 -> 46295 | K35: 2026-10-07
A36: Rates_Daily | B36: P (CNY Shibor 1Y) | C36: CFETS / National Interbank Funding Center (chinamoney.com.cn) | D36: Shibor 1Y | E36: Shanghai Interbank Offered Rate, 1Y tenor | F36: https://www.chinamoney.com.cn/english/bmkshibor/ (API: /ags/ms/cm-u-bk-shibor/ShiborHis) | G36: % p.a. | H36: Daily (China business days) | I36: =Rates_Daily!P10 -> 42373 | J36: =Rates_Daily!P11 -> 46295 | K36: 2026-10-07
A37: Rates_Daily | B37: Q (NOK Norges Bank policy rate) | C37: Norges Bank | D37: IR/B.KPRA.SD. | E37: Key policy rate (sight deposit rate), daily | F37: https://data.norges-bank.no/api/data/IR/B.KPRA.SD.?format=csv | G37: % p.a. | H37: Daily | I37: =Rates_Daily!Q10 -> 42373 | J37: =Rates_Daily!Q11 -> 46301 | K37: 2026-10-07
A38: Rates_Daily | B38: R (NOK NOWA (O/N)) | C38: Norges Bank | D38: SHORT_RATES/B.NOWA.ON.R | E38: Norwegian Overnight Weighted Average, daily | F38: https://data.norges-bank.no/api/data/SHORT_RATES/B.NOWA.ON.R?format=csv | G38: % p.a. | H38: Daily | I38: =Rates_Daily!R10 -> 42373 | J38: =Rates_Daily!R11 -> 46301 | K38: 2026-10-07
A39: Rates_Daily | B39: S (BRL Selic target (reference only)) | C39: Banco Central do Brasil (SGS) | D39: SGS 432 | E39: Meta Selic definida pelo Copom (% a.a.) | F39: https://api.bcb.gov.br/dados/serie/bcdata.sgs.432/dados?formato=json | G39: % p.a. | H39: Daily | I39: =Rates_Daily!S10 -> 42370 | J39: =Rates_Daily!S11 -> 46302 | K39: 2026-10-07
A40: Rates_Monthly | B40: B (USD Fed funds effective) | C40: FRED (St. Louis Fed) | D40: FEDFUNDS | E40: Federal Funds Effective Rate (FEDFUNDS) | F40: https://fred.stlouisfed.org/series/FEDFUNDS | G40: Percent | H40: Monthly | I40: =Rates_Monthly!B10 -> 42370 | J40: =Rates_Monthly!B11 -> 46266 | K40: 2026-10-07
A41: Rates_Monthly | B41: C (USD Fed target upper (month-end)) | C41: FRED (St. Louis Fed) | D41: DFEDTARU → Month-end value (last daily obs <= month end; formula on Rates_Daily) | E41: Federal Funds Target Range - Upper Limit (DFEDTARU) | F41: https://fred.stlouisfed.org/series/DFEDTARU | G41: Percent | H41: Month-end value (last daily obs <= month end; formula on Rates_Daily) | I41: =Rates_Monthly!C10 -> 42370 | J41: =Rates_Monthly!C11 -> 46296 | K41: 2026-10-07
A42: Rates_Monthly | B42: D (USD Fed target lower (month-end)) | C42: FRED (St. Louis Fed) | D42: DFEDTARL → Month-end value (last daily obs <= month end; formula on Rates_Daily) | E42: Federal Funds Target Range - Lower Limit (DFEDTARL) | F42: https://fred.stlouisfed.org/series/DFEDTARL | G42: Percent | H42: Month-end value (last daily obs <= month end; formula on Rates_Daily) | I42: =Rates_Monthly!D10 -> 42370 | J42: =Rates_Monthly!D11 -> 46296 | K42: 2026-10-07
A43: Rates_Monthly | B43: E (USD SOFR (monthly avg)) | C43: FRED (St. Louis Fed) | D43: SOFR → Monthly average of daily obs (formula on Rates_Daily) | E43: Secured Overnight Financing Rate (SOFR) | F43: https://fred.stlouisfed.org/series/SOFR | G43: Percent | H43: Monthly average of daily obs (formula on Rates_Daily) | I43: =Rates_Monthly!E10 -> 43191 | J43: =Rates_Monthly!E11 -> 46296 | K43: 2026-10-07
A44: Rates_Monthly | B44: F (USD T-bill 1M (CMT)) | C44: FRED (St. Louis Fed) | D44: GS1M | E44: Market Yield on U.S. Treasury Securities at 1-Month Constant Maturity, Quoted on an Investment Basis (GS1M) | F44: https://fred.stlouisfed.org/series/GS1M | G44: Percent | H44: Monthly | I44: =Rates_Monthly!F10 -> 42370 | J44: =Rates_Monthly!F11 -> 46266 | K44: 2026-10-07
A45: Rates_Monthly | B45: G (USD T-bill 3M (CMT)) | C45: FRED (St. Louis Fed) | D45: GS3M | E45: Market Yield on U.S. Treasury Securities at 3-Month Constant Maturity, Quoted on an Investment Basis (GS3M) | F45: https://fred.stlouisfed.org/series/GS3M | G45: Percent | H45: Monthly | I45: =Rates_Monthly!G10 -> 42370 | J45: =Rates_Monthly!G11 -> 46266 | K45: 2026-10-07
A46: Rates_Monthly | B46: H (USD T-bill 6M (CMT)) | C46: FRED (St. Louis Fed) | D46: GS6M | E46: Market Yield on U.S. Treasury Securities at 6-Month Constant Maturity, Quoted on an Investment Basis (GS6M) | F46: https://fred.stlouisfed.org/series/GS6M | G46: Percent | H46: Monthly | I46: =Rates_Monthly!H10 -> 42370 | J46: =Rates_Monthly!H11 -> 46266 | K46: 2026-10-07
A47: Rates_Monthly | B47: I (USD Treasury 12M (CMT)) | C47: FRED (St. Louis Fed) | D47: GS1 | E47: Market Yield on U.S. Treasury Securities at 1-Year Constant Maturity, Quoted on an Investment Basis (GS1) | F47: https://fred.stlouisfed.org/series/GS1 | G47: Percent | H47: Monthly | I47: =Rates_Monthly!I10 -> 42370 | J47: =Rates_Monthly!I11 -> 46266 | K47: 2026-10-07
A48: Rates_Monthly | B48: J (USD 3M interbank (OECD)) | C48: FRED; original source OECD Main Economic Indicators | D48: IR3TIB01USM156N | E48: Interest Rates: 3-Month or 90-Day Rates and Yields: Interbank Rates: Total for United States (IR3TIB01USM156N) | F48: https://fred.stlouisfed.org/series/IR3TIB01USM156N | G48: Percent | H48: Monthly | I48: =Rates_Monthly!J10 -> 42370 | J48: =Rates_Monthly!J11 -> 46235 | K48: 2026-10-07
A49: Rates_Monthly | B49: K (EUR ECB deposit rate (month-end)) | C49: European Central Bank (ECB Data Portal) | D49: FM.D.U2.EUR.4F.KR.DFR.LEV → Month-end value (last daily obs <= month end; formula on Rates_Daily) | E49: Deposit facility - date of changes (raw data) - Level | F49: https://data.ecb.europa.eu/data/datasets/FM/FM.D.U2.EUR.4F.KR.DFR.LEV | G49: % p.a. | H49: Month-end value (last daily obs <= month end; formula on Rates_Daily) | I49: =Rates_Monthly!K10 -> 42370 | J49: =Rates_Monthly!K11 -> 46296 | K49: 2026-10-07
A50: Rates_Monthly | B50: L (EUR €STR (monthly avg)) | C50: European Central Bank (ECB Data Portal) | D50: EST.B.EU000A2X2A25.WT → Monthly average of daily obs (formula on Rates_Daily) | E50: Euro short-term rate | F50: https://data.ecb.europa.eu/data/datasets/EST/EST.B.EU000A2X2A25.WT | G50: % p.a. | H50: Monthly average of daily obs (formula on Rates_Daily) | I50: =Rates_Monthly!L10 -> 43739 | J50: =Rates_Monthly!L11 -> 46296 | K50: 2026-10-07
A51: Rates_Monthly | B51: M (EUR Euribor 1M) | C51: European Central Bank (ECB Data Portal); administrator EMMI | D51: FM.M.U2.EUR.RT.MM.EURIBOR1MD_.HSTA | E51: Euribor 1-month - Historical close, average of observations through period | F51: https://data.ecb.europa.eu/data/datasets/FM/FM.M.U2.EUR.RT.MM.EURIBOR1MD_.HSTA | G51: % p.a. | H51: Monthly (average of daily obs, per source) | I51: =Rates_Monthly!M10 -> 42370 | J51: =Rates_Monthly!M11 -> 46266 | K51: 2026-10-07
A52: Rates_Monthly | B52: N (EUR Euribor 3M) | C52: European Central Bank (ECB Data Portal); administrator EMMI | D52: FM.M.U2.EUR.RT.MM.EURIBOR3MD_.HSTA | E52: Euribor 3-month - Historical close, average of observations through period | F52: https://data.ecb.europa.eu/data/datasets/FM/FM.M.U2.EUR.RT.MM.EURIBOR3MD_.HSTA | G52: % p.a. | H52: Monthly (average of daily obs, per source) | I52: =Rates_Monthly!N10 -> 42370 | J52: =Rates_Monthly!N11 -> 46266 | K52: 2026-10-07
A53: Rates_Monthly | B53: O (EUR Euribor 6M) | C53: European Central Bank (ECB Data Portal); administrator EMMI | D53: FM.M.U2.EUR.RT.MM.EURIBOR6MD_.HSTA | E53: Euribor 6-month - Historical close, average of observations through period | F53: https://data.ecb.europa.eu/data/datasets/FM/FM.M.U2.EUR.RT.MM.EURIBOR6MD_.HSTA | G53: % p.a. | H53: Monthly (average of daily obs, per source) | I53: =Rates_Monthly!O10 -> 42370 | J53: =Rates_Monthly!O11 -> 46266 | K53: 2026-10-07
A54: Rates_Monthly | B54: P (EUR Euribor 12M) | C54: European Central Bank (ECB Data Portal); administrator EMMI | D54: FM.M.U2.EUR.RT.MM.EURIBOR1YD_.HSTA | E54: Euribor 1-year - Historical close, average of observations through period | F54: https://data.ecb.europa.eu/data/datasets/FM/FM.M.U2.EUR.RT.MM.EURIBOR1YD_.HSTA | G54: % p.a. | H54: Monthly (average of daily obs, per source) | I54: =Rates_Monthly!P10 -> 42370 | J54: =Rates_Monthly!P11 -> 46266 | K54: 2026-10-07
A55: Rates_Monthly | B55: Q (EUR 3M interbank (OECD)) | C55: FRED; original source OECD Main Economic Indicators | D55: IR3TIB01EZM156N | E55: Interest Rates: 3-Month or 90-Day Rates and Yields: Interbank Rates: Total for Euro Area (19 Countries) (IR3TIB01EZM156N) | F55: https://fred.stlouisfed.org/series/IR3TIB01EZM156N | G55: Percent | H55: Monthly | I55: =Rates_Monthly!Q10 -> 42370 | J55: =Rates_Monthly!Q11 -> 46023 | K55: 2026-10-07 | L55: Stale: last obs 2026-01; superseded by ECB Euribor 3M
A56: Rates_Monthly | B56: R (GBP Bank Rate (monthly avg)) | C56: Bank of England (IADB) | D56: IUMABEDR | E56: Monthly average of official Bank Rate | F56: https://www.bankofengland.co.uk/boeapps/database/?SeriesCodes=IUMABEDR | G56: % p.a. | H56: Monthly (average of daily obs, per source) | I56: =Rates_Monthly!R10 -> 42370 | J56: =Rates_Monthly!R11 -> 46266 | K56: 2026-10-07
A57: Rates_Monthly | B57: S (GBP SONIA (monthly avg)) | C57: Bank of England (IADB) | D57: IUMASOIA | E57: Monthly average of SONIA | F57: https://www.bankofengland.co.uk/boeapps/database/?SeriesCodes=IUMASOIA | G57: % p.a. | H57: Monthly (average of daily obs, per source) | I57: =Rates_Monthly!S10 -> 42370 | J57: =Rates_Monthly!S11 -> 46266 | K57: 2026-10-07
A58: Rates_Monthly | B58: T (GBP OIS 1M (monthly avg)) | C58: Bank of England (yield curve data) | D58: UK OIS spot curve, 1M maturity → Monthly average of daily obs (formula on Rates_Daily) | E58: BoE estimated UK OIS (SONIA) spot rate, 1M maturity, continuously compounded per BoE methodology | F58: https://www.bankofengland.co.uk/statistics/yield-curves (files: oisddata.zip, latest-yield-curve-data.zip; sheet "3. spot, short end") | G58: % p.a. | H58: Monthly average of daily obs (formula on Rates_Daily) | I58: =Rates_Monthly!T10 -> 42370 | J58: =Rates_Monthly!T11 -> 46296 | K58: 2026-10-07
A59: Rates_Monthly | B59: U (GBP OIS 3M (monthly avg)) | C59: Bank of England (yield curve data) | D59: UK OIS spot curve, 3M maturity → Monthly average of daily obs (formula on Rates_Daily) | E59: BoE estimated UK OIS (SONIA) spot rate, 3M maturity, continuously compounded per BoE methodology | F59: https://www.bankofengland.co.uk/statistics/yield-curves (files: oisddata.zip, latest-yield-curve-data.zip; sheet "3. spot, short end") | G59: % p.a. | H59: Monthly average of daily obs (formula on Rates_Daily) | I59: =Rates_Monthly!U10 -> 42370 | J59: =Rates_Monthly!U11 -> 46296 | K59: 2026-10-07
A60: Rates_Monthly | B60: V (GBP OIS 6M (monthly avg)) | C60: Bank of England (yield curve data) | D60: UK OIS spot curve, 6M maturity → Monthly average of daily obs (formula on Rates_Daily) | E60: BoE estimated UK OIS (SONIA) spot rate, 6M maturity, continuously compounded per BoE methodology | F60: https://www.bankofengland.co.uk/statistics/yield-curves (files: oisddata.zip, latest-yield-curve-data.zip; sheet "3. spot, short end") | G60: % p.a. | H60: Monthly average of daily obs (formula on Rates_Daily) | I60: =Rates_Monthly!V10 -> 42370 | J60: =Rates_Monthly!V11 -> 46296 | K60: 2026-10-07
A61: Rates_Monthly | B61: W (GBP OIS 12M (monthly avg)) | C61: Bank of England (yield curve data) | D61: UK OIS spot curve, 12M maturity → Monthly average of daily obs (formula on Rates_Daily) | E61: BoE estimated UK OIS (SONIA) spot rate, 12M maturity, continuously compounded per BoE methodology | F61: https://www.bankofengland.co.uk/statistics/yield-curves (files: oisddata.zip, latest-yield-curve-data.zip; sheet "3. spot, short end") | G61: % p.a. | H61: Monthly average of daily obs (formula on Rates_Daily) | I61: =Rates_Monthly!W10 -> 42370 | J61: =Rates_Monthly!W11 -> 46296 | K61: 2026-10-07
A62: Rates_Monthly | B62: X (GBP 3M interbank (OECD)) | C62: FRED; original source OECD Main Economic Indicators | D62: IR3TIB01GBM156N | E62: Interest Rates: 3-Month or 90-Day Rates and Yields: Interbank Rates: Total for United Kingdom (IR3TIB01GBM156N) | F62: https://fred.stlouisfed.org/series/IR3TIB01GBM156N | G62: Percent | H62: Monthly | I62: =Rates_Monthly!X10 -> 42370 | J62: =Rates_Monthly!X11 -> 46023 | K62: 2026-10-07 | L62: Stale: last obs 2026-01; superseded by BoE OIS 3M
A63: Rates_Monthly | B63: Y (NOK policy rate (monthly avg)) | C63: Norges Bank | D63: IR/M.KPRA.SD. | E63: Key policy rate, monthly average | F63: https://data.norges-bank.no/api/data/IR/M.KPRA.SD.?format=csv | G63: % p.a. | H63: Monthly (average of daily obs, per source) | I63: =Rates_Monthly!Y10 -> 42370 | J63: =Rates_Monthly!Y11 -> 46266 | K63: 2026-10-07
A64: Rates_Monthly | B64: Z (NOK NOWA (monthly avg)) | C64: Norges Bank | D64: SHORT_RATES/M.NOWA.ON.R | E64: NOWA, monthly average | F64: https://data.norges-bank.no/api/data/SHORT_RATES/M.NOWA.ON.R?format=csv | G64: % p.a. | H64: Monthly (average of daily obs, per source) | I64: =Rates_Monthly!Z10 -> 42370 | J64: =Rates_Monthly!Z11 -> 46266 | K64: 2026-10-07
A65: Rates_Monthly | B65: AA (NOK T-bill 3M) | C65: Norges Bank | D65: GOVT_GENERIC_RATES/M.3M.TBIL. | E65: Generic Norwegian Treasury bill yield 3M, monthly | F65: https://data.norges-bank.no/api/data/GOVT_GENERIC_RATES/M.3M.TBIL.?format=csv | G65: % p.a. | H65: Monthly (average of daily obs, per source) | I65: =Rates_Monthly!AA10 -> 43466 | J65: =Rates_Monthly!AA11 -> 46266 | K65: 2026-10-07 | L65: Starts 2019-01 in Norges Bank API
A66: Rates_Monthly | B66: AB (NOK T-bill 6M) | C66: Norges Bank | D66: GOVT_GENERIC_RATES/M.6M.TBIL. | E66: Generic Norwegian Treasury bill yield 6M, monthly | F66: https://data.norges-bank.no/api/data/GOVT_GENERIC_RATES/M.6M.TBIL.?format=csv | G66: % p.a. | H66: Monthly (average of daily obs, per source) | I66: =Rates_Monthly!AB10 -> 43466 | J66: =Rates_Monthly!AB11 -> 46266 | K66: 2026-10-07 | L66: Starts 2019-01
A67: Rates_Monthly | B67: AC (NOK T-bill 12M) | C67: Norges Bank | D67: GOVT_GENERIC_RATES/M.12M.TBIL. | E67: Generic Norwegian Treasury bill yield 12M, monthly | F67: https://data.norges-bank.no/api/data/GOVT_GENERIC_RATES/M.12M.TBIL.?format=csv | G67: % p.a. | H67: Monthly (average of daily obs, per source) | I67: =Rates_Monthly!AC10 -> 43466 | J67: =Rates_Monthly!AC11 -> 46266 | K67: 2026-10-07 | L67: Starts 2019-01
A68: Rates_Monthly | B68: AD (NOK 3M interbank (OECD; NIBOR-based)) | C68: FRED; original source OECD Main Economic Indicators | D68: IR3TIB01NOM156N | E68: Interest Rates: 3-Month or 90-Day Rates and Yields: Interbank Rates: Total for Norway (IR3TIB01NOM156N) | F68: https://fred.stlouisfed.org/series/IR3TIB01NOM156N | G68: Percent | H68: Monthly | I68: =Rates_Monthly!AD10 -> 42370 | J68: =Rates_Monthly!AD11 -> 46235 | K68: 2026-10-07
A69: Rates_Monthly | B69: AE (KRW BoK base rate) | C69: Bank of Korea (ECOS) | D69: 722Y001 / item 0101000 | E69: 1.3.1. 한국은행 기준금리 및 여수신금리 / 한국은행 기준금리 | F69: https://ecos.bok.or.kr/api/StatisticSearch/[KEY]/json/kr/1/1000/722Y001/M/201601/202609/0101000 | G69: % p.a. (연%) | H69: Monthly (average of daily obs, per source) | I69: =Rates_Monthly!AE10 -> 42370 | J69: =Rates_Monthly!AE11 -> 46266 | K69: 2026-10-07
A70: Rates_Monthly | B70: AF (KRW call rate (O/N)) | C70: Bank of Korea (ECOS) | D70: 721Y001 / item 1010000 | E70: 1.3.2.2. 시장금리(월,분기,년) / 무담보콜금리(1일) | F70: https://ecos.bok.or.kr/api/StatisticSearch/[KEY]/json/kr/1/1000/721Y001/M/201601/202609/1010000 | G70: % p.a. (연%) | H70: Monthly (average of daily obs, per source) | I70: =Rates_Monthly!AF10 -> 42370 | J70: =Rates_Monthly!AF11 -> 46266 | K70: 2026-10-07
A71: Rates_Monthly | B71: AG (KRW CD 91-day) | C71: Bank of Korea (ECOS) | D71: 721Y001 / item 2010000 | E71: 1.3.2.2. 시장금리(월,분기,년) / CD(91일) | F71: https://ecos.bok.or.kr/api/StatisticSearch/[KEY]/json/kr/1/1000/721Y001/M/201601/202609/2010000 | G71: % p.a. (연%) | H71: Monthly (average of daily obs, per source) | I71: =Rates_Monthly!AG10 -> 42370 | J71: =Rates_Monthly!AG11 -> 46266 | K71: 2026-10-07
A72: Rates_Monthly | B72: AH (KRW KORIBOR 3M) | C72: Bank of Korea (ECOS) | D72: 721Y001 / item 1025000 | E72: 1.3.2.2. 시장금리(월,분기,년) / KORIBOR(3개월) | F72: https://ecos.bok.or.kr/api/StatisticSearch/[KEY]/json/kr/1/1000/721Y001/M/201601/202609/1025000 | G72: % p.a. (연%) | H72: Monthly (average of daily obs, per source) | I72: =Rates_Monthly!AH10 -> 42370 | J72: =Rates_Monthly!AH11 -> 46266 | K72: 2026-10-07
A73: Rates_Monthly | B73: AI (KRW KORIBOR 6M) | C73: Bank of Korea (ECOS) | D73: 721Y001 / item 1026000 | E73: 1.3.2.2. 시장금리(월,분기,년) / KORIBOR(6개월) | F73: https://ecos.bok.or.kr/api/StatisticSearch/[KEY]/json/kr/1/1000/721Y001/M/201601/202609/1026000 | G73: % p.a. (연%) | H73: Monthly (average of daily obs, per source) | I73: =Rates_Monthly!AI10 -> 42370 | J73: =Rates_Monthly!AI11 -> 46266 | K73: 2026-10-07
A74: Rates_Monthly | B74: AJ (KRW KORIBOR 12M) | C74: Bank of Korea (ECOS) | D74: 721Y001 / item 1027000 | E74: 1.3.2.2. 시장금리(월,분기,년) / KORIBOR(12개월) | F74: https://ecos.bok.or.kr/api/StatisticSearch/[KEY]/json/kr/1/1000/721Y001/M/201601/202609/1027000 | G74: % p.a. (연%) | H74: Monthly (average of daily obs, per source) | I74: =Rates_Monthly!AJ10 -> 42370 | J74: =Rates_Monthly!AJ11 -> 46266 | K74: 2026-10-07
A75: Rates_Monthly | B75: AK (KRW MSB 91-day) | C75: Bank of Korea (ECOS) | D75: 721Y001 / item 6010300 | E75: 1.3.2.2. 시장금리(월,분기,년) / 통안증권(91일) | F75: https://ecos.bok.or.kr/api/StatisticSearch/[KEY]/json/kr/1/1000/721Y001/M/201601/202609/6010300 | G75: % p.a. (연%) | H75: Monthly (average of daily obs, per source) | I75: =Rates_Monthly!AK10 -> 42370 | J75: =Rates_Monthly!AK11 -> 46266 | K75: 2026-10-07
A76: Rates_Monthly | B76: AL (KRW MSB 1Y) | C76: Bank of Korea (ECOS) | D76: 721Y001 / item 6010100 | E76: 1.3.2.2. 시장금리(월,분기,년) / 통안증권(1년) | F76: https://ecos.bok.or.kr/api/StatisticSearch/[KEY]/json/kr/1/1000/721Y001/M/201601/202609/6010100 | G76: % p.a. (연%) | H76: Monthly (average of daily obs, per source) | I76: =Rates_Monthly!AL10 -> 42370 | J76: =Rates_Monthly!AL11 -> 46266 | K76: 2026-10-07
A77: Rates_Monthly | B77: AM (KRW KTB 1Y) | C77: Bank of Korea (ECOS) | D77: 721Y001 / item 5030000 | E77: 1.3.2.2. 시장금리(월,분기,년) / 국고채(1년) | F77: https://ecos.bok.or.kr/api/StatisticSearch/[KEY]/json/kr/1/1000/721Y001/M/201601/202609/5030000 | G77: % p.a. (연%) | H77: Monthly (average of daily obs, per source) | I77: =Rates_Monthly!AM10 -> 42370 | J77: =Rates_Monthly!AM11 -> 46266 | K77: 2026-10-07
A78: Rates_Monthly | B78: AN (KRW 3M interbank (OECD)) | C78: FRED; original source OECD Main Economic Indicators | D78: IR3TIB01KRM156N | E78: Interest Rates: 3-Month or 90-Day Rates and Yields: Interbank Rates: Total for Korea (IR3TIB01KRM156N) | F78: https://fred.stlouisfed.org/series/IR3TIB01KRM156N | G78: Percent | H78: Monthly | I78: =Rates_Monthly!AN10 -> 42370 | J78: =Rates_Monthly!AN11 -> 46235 | K78: 2026-10-07
A79: Rates_Monthly | B79: AO (CNY Shibor 1M (monthly avg)) | C79: CFETS / National Interbank Funding Center (chinamoney.com.cn) | D79: Shibor 1M → Monthly average of daily obs (formula on Rates_Daily) | E79: Shanghai Interbank Offered Rate, 1M tenor | F79: https://www.chinamoney.com.cn/english/bmkshibor/ (API: /ags/ms/cm-u-bk-shibor/ShiborHis) | G79: % p.a. | H79: Monthly average of daily obs (formula on Rates_Daily) | I79: =Rates_Monthly!AO10 -> 42370 | J79: =Rates_Monthly!AO11 -> 46266 | K79: 2026-10-07
A80: Rates_Monthly | B80: AP (CNY Shibor 3M (monthly avg)) | C80: CFETS / National Interbank Funding Center (chinamoney.com.cn) | D80: Shibor 3M → Monthly average of daily obs (formula on Rates_Daily) | E80: Shanghai Interbank Offered Rate, 3M tenor | F80: https://www.chinamoney.com.cn/english/bmkshibor/ (API: /ags/ms/cm-u-bk-shibor/ShiborHis) | G80: % p.a. | H80: Monthly average of daily obs (formula on Rates_Daily) | I80: =Rates_Monthly!AP10 -> 42370 | J80: =Rates_Monthly!AP11 -> 46266 | K80: 2026-10-07
A81: Rates_Monthly | B81: AQ (CNY Shibor 6M (monthly avg)) | C81: CFETS / National Interbank Funding Center (chinamoney.com.cn) | D81: Shibor 6M → Monthly average of daily obs (formula on Rates_Daily) | E81: Shanghai Interbank Offered Rate, 6M tenor | F81: https://www.chinamoney.com.cn/english/bmkshibor/ (API: /ags/ms/cm-u-bk-shibor/ShiborHis) | G81: % p.a. | H81: Monthly average of daily obs (formula on Rates_Daily) | I81: =Rates_Monthly!AQ10 -> 42370 | J81: =Rates_Monthly!AQ11 -> 46266 | K81: 2026-10-07
A82: Rates_Monthly | B82: AR (CNY Shibor 1Y (monthly avg)) | C82: CFETS / National Interbank Funding Center (chinamoney.com.cn) | D82: Shibor 1Y → Monthly average of daily obs (formula on Rates_Daily) | E82: Shanghai Interbank Offered Rate, 1Y tenor | F82: https://www.chinamoney.com.cn/english/bmkshibor/ (API: /ags/ms/cm-u-bk-shibor/ShiborHis) | G82: % p.a. | H82: Monthly average of daily obs (formula on Rates_Daily) | I82: =Rates_Monthly!AR10 -> 42370 | J82: =Rates_Monthly!AR11 -> 46266 | K82: 2026-10-07
A83: Rates_Monthly | B83: AS (CNY LPR 1Y (monthly fixing)) | C83: PBoC / NIFC via CFETS (chinamoney.com.cn) | D83: LPR 1Y | E83: Loan Prime Rate 1-year, monthly fixing (value of that month's fixing) | F83: https://www.chinamoney.com.cn/english/bmklpr/ (API: /ags/ms/cm-u-bk-currency/LprHis) | G83: % p.a. | H83: Monthly fixing (~20th) | I83: =Rates_Monthly!AS10 -> 43678 | J83: =Rates_Monthly!AS11 -> 46266 | K83: 2026-10-07 | L83: Starts 2019-08 (LPR reform)
A84: Rates_Monthly | B84: AT (CNY LPR 5Y (monthly fixing)) | C84: PBoC / NIFC via CFETS (chinamoney.com.cn) | D84: LPR 5Y | E84: Loan Prime Rate 5-year, monthly fixing | F84: https://www.chinamoney.com.cn/english/bmklpr/ | G84: % p.a. | H84: Monthly fixing (~20th) | I84: =Rates_Monthly!AT10 -> 43678 | J84: =Rates_Monthly!AT11 -> 46266 | K84: 2026-10-07 | L84: Starts 2019-08
A85: Rates_Monthly | B85: AU (CNY 3M interbank (OECD)) | C85: FRED; original source OECD Main Economic Indicators | D85: IR3TIB01CNM156N | E85: Interest Rates: 3-Month or 90-Day Rates and Yields: Interbank Rates: Total for China (IR3TIB01CNM156N) | F85: https://fred.stlouisfed.org/series/IR3TIB01CNM156N | G85: Percent | H85: Monthly | I85: =Rates_Monthly!AU10 -> 42370 | J85: =Rates_Monthly!AU11 -> 46204 | K85: 2026-10-07
A86: Rates_Monthly | B86: AV (BRL Selic (monthly, annualized) — reference) | C86: Banco Central do Brasil (SGS) | D86: SGS 4189 | E86: Taxa de juros Selic acumulada no mês, anualizada base 252 | F86: https://api.bcb.gov.br/dados/serie/bcdata.sgs.4189/dados?formato=json | G86: % p.a. | H86: Monthly | I86: =Rates_Monthly!AV10 -> 42370 | J86: =Rates_Monthly!AV11 -> 46266 | K86: 2026-10-07
A87: Rates_Monthly | B87: AW (BRL call money (OECD) — reference) | C87: FRED; original source OECD Main Economic Indicators | D87: IRSTCI01BRM156N | E87: Interest Rates: Immediate Rates (< 24 Hours): Call Money/Interbank Rate: Total for Brazil (IRSTCI01BRM156N) | F87: https://fred.stlouisfed.org/series/IRSTCI01BRM156N | G87: Percent | H87: Monthly | I87: =Rates_Monthly!AW10 -> 42370 | J87: =Rates_Monthly!AW11 -> 46235 | K87: 2026-10-07
A88: Rates_Monthly | B88: AX (JPY 3M interbank (OECD) — reference) | C88: FRED; original source OECD Main Economic Indicators | D88: IR3TIB01JPM156N | E88: Interest Rates: 3-Month or 90-Day Rates and Yields: Interbank Rates: Total for Japan (IR3TIB01JPM156N) | F88: https://fred.stlouisfed.org/series/IR3TIB01JPM156N | G88: Percent | H88: Monthly | I88: =Rates_Monthly!AX10 -> 42370 | J88: =Rates_Monthly!AX11 -> 46204 | K88: 2026-10-07
A89: Rates_Monthly | B89: AY (JPY call money (OECD) — reference) | C89: FRED; original source OECD Main Economic Indicators | D89: IRSTCI01JPM156N | E89: Interest Rates: Immediate Rates (< 24 Hours): Call Money/Interbank Rate: Total for Japan (IRSTCI01JPM156N) | F89: https://fred.stlouisfed.org/series/IRSTCI01JPM156N | G89: Percent | H89: Monthly | I89: =Rates_Monthly!AY10 -> 42370 | J89: =Rates_Monthly!AY11 -> 46235 | K89: 2026-10-07
A90: Inflation | B90: B (USA CPI-U index (NSA)) | C90: FRED; original source U.S. Bureau of Labor Statistics | D90: CPIAUCNS | E90: CPI for All Urban Consumers: All Items in U.S. City Average, not seasonally adjusted | F90: https://fred.stlouisfed.org/series/CPIAUCNS | G90: Index 1982-84=100 | H90: Monthly | I90: =Inflation!B10 -> 42005 | J90: =Inflation!B11 -> 46235 | K90: 2026-10-07 | L90: 2025-10 not published by BLS (2025 federal government shutdown)
A91: Inflation | B91: D (USA CPI y/y (OECD)) | C91: OECD (Data Explorer, Prices) — compiled from national statistics office | D91: DF_PRICES_ALL USA.M.N.CPI.PA._T.N.GY | E91: National CPI, all items, growth over 1 year (same month previous year), USA | F91: https://sdmx.oecd.org/public/rest/data/OECD.SDD.TPS,DSD_PRICES@DF_PRICES_ALL,1.0/USA.M.N.CPI.PA._T.N.GY | G91: % y/y | H91: Monthly | I91: =Inflation!D10 -> 42005 | J91: =Inflation!D11 -> 46235 | K91: 2026-10-07
A92: Inflation | B92: E (KOR CPI y/y (OECD)) | C92: OECD (Data Explorer, Prices) — compiled from national statistics office | D92: DF_PRICES_ALL KOR.M.N.CPI.PA._T.N.GY | E92: National CPI, all items, growth over 1 year (same month previous year), KOR | F92: https://sdmx.oecd.org/public/rest/data/OECD.SDD.TPS,DSD_PRICES@DF_PRICES_ALL,1.0/KOR.M.N.CPI.PA._T.N.GY | G92: % y/y | H92: Monthly | I92: =Inflation!E10 -> 42005 | J92: =Inflation!E11 -> 46266 | K92: 2026-10-07
A93: Inflation | B93: F (GBR CPIH y/y (OECD) — = ONS CPIH, not headline CPI) | C93: OECD (Data Explorer, Prices) — compiled from national statistics office | D93: DF_PRICES_ALL GBR.M.N.CPI.PA._T.N.GY | E93: National CPI, all items, growth over 1 year (same month previous year), GBR | F93: https://sdmx.oecd.org/public/rest/data/OECD.SDD.TPS,DSD_PRICES@DF_PRICES_ALL,1.0/GBR.M.N.CPI.PA._T.N.GY | G93: % y/y | H93: Monthly | I93: =Inflation!F10 -> 42005 | J93: =Inflation!F11 -> 46235 | K93: 2026-10-07 | L93: OECD national CPI for GBR equals ONS CPIH (L55O), not headline CPI (D7G7)
A94: Inflation | B94: G (CHN CPI y/y (OECD)) | C94: OECD (Data Explorer, Prices) — compiled from national statistics office | D94: DF_PRICES_ALL CHN.M.N.CPI.PA._T.N.GY | E94: National CPI, all items, growth over 1 year (same month previous year), CHN | F94: https://sdmx.oecd.org/public/rest/data/OECD.SDD.TPS,DSD_PRICES@DF_PRICES_ALL,1.0/CHN.M.N.CPI.PA._T.N.GY | G94: % y/y | H94: Monthly | I94: =Inflation!G10 -> 42005 | J94: =Inflation!G11 -> 46235 | K94: 2026-10-07
A95: Inflation | B95: H (DEU CPI y/y (OECD, national VPI)) | C95: OECD (Data Explorer, Prices) — compiled from national statistics office | D95: DF_PRICES_ALL DEU.M.N.CPI.PA._T.N.GY | E95: National CPI, all items, growth over 1 year (same month previous year), DEU | F95: https://sdmx.oecd.org/public/rest/data/OECD.SDD.TPS,DSD_PRICES@DF_PRICES_ALL,1.0/DEU.M.N.CPI.PA._T.N.GY | G95: % y/y | H95: Monthly | I95: =Inflation!H10 -> 42005 | J95: =Inflation!H11 -> 46235 | K95: 2026-10-07
A96: Inflation | B96: I (FRA CPI y/y (OECD) — ends 2025-12) | C96: OECD (Data Explorer, Prices) — compiled from national statistics office | D96: DF_PRICES_ALL FRA.M.N.CPI.PA._T.N.GY | E96: National CPI, all items, growth over 1 year (same month previous year), FRA | F96: https://sdmx.oecd.org/public/rest/data/OECD.SDD.TPS,DSD_PRICES@DF_PRICES_ALL,1.0/FRA.M.N.CPI.PA._T.N.GY | G96: % y/y | H96: Monthly | I96: =Inflation!I10 -> 42005 | J96: =Inflation!I11 -> 45992 | K96: 2026-10-07 | L96: Discontinued after 2025-12 (COICOP 2018 transition); use HICP FR
A97: Inflation | B97: J (NOR CPI y/y (OECD) — ends 2025-12) | C97: OECD (Data Explorer, Prices) — compiled from national statistics office | D97: DF_PRICES_ALL NOR.M.N.CPI.PA._T.N.GY | E97: National CPI, all items, growth over 1 year (same month previous year), NOR | F97: https://sdmx.oecd.org/public/rest/data/OECD.SDD.TPS,DSD_PRICES@DF_PRICES_ALL,1.0/NOR.M.N.CPI.PA._T.N.GY | G97: % y/y | H97: Monthly | I97: =Inflation!J10 -> 42005 | J97: =Inflation!J11 -> 45992 | K97: 2026-10-07 | L97: Discontinued after 2025-12; use SSB 14710 index
A98: Inflation | B98: K (NOR CPI index (SSB, 2025=100)) | C98: Statistics Norway (SSB) | D98: Table 14710 (KpiIndMnd) | E98: Consumer price index (2025=100), all items | F98: https://data.ssb.no/api/pxwebapi/v2/tables/14710/data?lang=en | G98: Index 2025=100 | H98: Monthly | I98: =Inflation!K10 -> 42005 | J98: =Inflation!K11 -> 46235 | K98: 2026-10-07
A99: Inflation | B99: M (FRA HICP y/y (Eurostat)) | C99: Eurostat | D99: prc_hicp_minr (unit=RCH_A, coicop18=TOTAL, geo=FR) | E99: HICP (ECOICOP ver.2) all items, annual rate of change, FR | F99: https://ec.europa.eu/eurostat/api/dissemination/statistics/1.0/data/prc_hicp_minr?geo=FR&unit=RCH_A&coicop18=TOTAL | G99: % y/y | H99: Monthly | I99: =Inflation!M10 -> 42005 | J99: =Inflation!M11 -> 46266 | K99: 2026-10-07
A100: Inflation | B100: N (DEU HICP y/y (Eurostat)) | C100: Eurostat | D100: prc_hicp_minr (unit=RCH_A, coicop18=TOTAL, geo=DE) | E100: HICP (ECOICOP ver.2) all items, annual rate of change, DE | F100: https://ec.europa.eu/eurostat/api/dissemination/statistics/1.0/data/prc_hicp_minr?geo=DE&unit=RCH_A&coicop18=TOTAL | G100: % y/y | H100: Monthly | I100: =Inflation!N10 -> 42005 | J100: =Inflation!N11 -> 46266 | K100: 2026-10-07
A101: Inflation | B101: O (NOR HICP y/y (Eurostat)) | C101: Eurostat | D101: prc_hicp_minr (unit=RCH_A, coicop18=TOTAL, geo=NO) | E101: HICP (ECOICOP ver.2) all items, annual rate of change, NO | F101: https://ec.europa.eu/eurostat/api/dissemination/statistics/1.0/data/prc_hicp_minr?geo=NO&unit=RCH_A&coicop18=TOTAL | G101: % y/y | H101: Monthly | I101: =Inflation!O10 -> 42005 | J101: =Inflation!O11 -> 46235 | K101: 2026-10-07
...

Sheet FX_Daily
A1: FX_Daily — daily spot exchange rates (raw)
A2: As-of date: 2026-10-07 | Retrieval date: 2026-10-07 | Blue font = raw value from source; black = formula. Blank cell = no fixing published by that source on that date (market holiday). Quote direction in each header.
A4: Provider | B4: FRED (St. Louis Fed); original source Federal Reserve Board H.10 | C4: FRED (St. Louis Fed); original source Federal Reserve Board H.10 | D4: FRED (St. Louis Fed); original source Federal Reserve Board H.10 | E4: FRED (St. Louis Fed); original source Federal Reserve Board H.10 | F4: FRED (St. Louis Fed); original source Federal Reserve Board H.10 | G4: FRED (St. Louis Fed); original source Federal Reserve Board H.10 | H4: FRED (St. Louis Fed); original source Federal Reserve Board H.10 | I4: European Central Bank (ECB Data Portal) | J4: European Central Bank (ECB Data Portal) | K4: European Central Bank (ECB Data Portal) | L4: European Central Bank (ECB Data Portal) | M4: European Central Bank (ECB Data Portal) | N4: European Central Bank (ECB Data Portal) | O4: European Central Bank (ECB Data Portal) | P4: Norges Bank (data.norges-bank.no)
A5: Series ID / table | B5: DEXKOUS | C5: DEXNOUS | D5: DEXUSUK | E5: DEXUSEU | F5: DEXCHUS | G5: DEXBZUS | H5: DEXJPUS | I5: EXR.D.USD.EUR.SP00.A | J5: EXR.D.NOK.EUR.SP00.A | K5: EXR.D.KRW.EUR.SP00.A | L5: EXR.D.GBP.EUR.SP00.A | M5: EXR.D.CNY.EUR.SP00.A | N5: EXR.D.BRL.EUR.SP00.A | O5: EXR.D.JPY.EUR.SP00.A | P5: EXR/B.USD.NOK.SP
A6: Description (quote direction) | B6: South Korean Won to U.S. Dollar Spot Exchange Rate (DEXKOUS) | C6: Norwegian Kroner to U.S. Dollar Spot Exchange Rate (DEXNOUS) | D6: U.S. Dollars to U.K. Pound Sterling Spot Exchange Rate (DEXUSUK) | E6: U.S. Dollars to Euro Spot Exchange Rate (DEXUSEU) | F6: Chinese Yuan Renminbi to U.S. Dollar Spot Exchange Rate (DEXCHUS) | G6: Brazilian Reals to U.S. Dollar Spot Exchange Rate (DEXBZUS) | H6: Japanese Yen to U.S. Dollar Spot Exchange Rate (DEXJPUS) | I6: US dollar/Euro ECB reference exchange rate — USD per 1 EUR | J6: Norwegian krone/Euro ECB reference exchange rate — NOK per 1 EUR | K6: South Korean won/Euro ECB reference exchange rate — KRW per 1 EUR | L6: Pound sterling/Euro ECB reference exchange rate — GBP per 1 EUR | M6: Chinese yuan renminbi/Euro ECB reference exchange rate — CNY per 1 EUR | N6: Brazilian real/Euro ECB reference exchange rate — BRL per 1 EUR | O6: Japanese yen/Euro ECB reference exchange rate — JPY per 1 EUR | P6: Norges Bank daily exchange rate, NOK per 1 USD (midday fixing)
A7: Unit | B7: South Korean Won to One U.S. Dollar | C7: Norwegian Kroner to One U.S. Dollar | D7: U.S. Dollars to One U.K. Pound Sterling | E7: U.S. Dollars to One Euro | F7: Chinese Yuan Renminbi to One U.S. Dollar | G7: Brazilian Reals to One U.S. Dollar | H7: Japanese Yen to One U.S. Dollar | I7: USD per 1 EUR | J7: NOK per 1 EUR | K7: KRW per 1 EUR | L7: GBP per 1 EUR | M7: CNY per 1 EUR | N7: BRL per 1 EUR | O7: JPY per 1 EUR | P7: NOK per 1 USD
A8: Frequency | B8: Daily | C8: Daily | D8: Daily | E8: Daily | F8: Daily | G8: Daily | H8: Daily | I8: Daily (TARGET days, 14:15 CET) | J8: Daily (TARGET days, 14:15 CET) | K8: Daily (TARGET days, 14:15 CET) | L8: Daily (TARGET days, 14:15 CET) | M8: Daily (TARGET days, 14:15 CET) | N8: Daily (TARGET days, 14:15 CET) | O8: Daily (TARGET days, 14:15 CET) | P8: Daily (Norwegian business days)
A9: URL | B9: https://fred.stlouisfed.org/series/DEXKOUS | C9: https://fred.stlouisfed.org/series/DEXNOUS | D9: https://fred.stlouisfed.org/series/DEXUSUK | E9: https://fred.stlouisfed.org/series/DEXUSEU | F9: https://fred.stlouisfed.org/series/DEXCHUS | G9: https://fred.stlouisfed.org/series/DEXBZUS | H9: https://fred.stlouisfed.org/series/DEXJPUS | I9: https://data.ecb.europa.eu/data/datasets/EXR/EXR.D.USD.EUR.SP00.A | J9: https://data.ecb.europa.eu/data/datasets/EXR/EXR.D.NOK.EUR.SP00.A | K9: https://data.ecb.europa.eu/data/datasets/EXR/EXR.D.KRW.EUR.SP00.A | L9: https://data.ecb.europa.eu/data/datasets/EXR/EXR.D.GBP.EUR.SP00.A | M9: https://data.ecb.europa.eu/data/datasets/EXR/EXR.D.CNY.EUR.SP00.A | N9: https://data.ecb.europa.eu/data/datasets/EXR/EXR.D.BRL.EUR.SP00.A | O9: https://data.ecb.europa.eu/data/datasets/EXR/EXR.D.JPY.EUR.SP00.A | P9: https://data.norges-bank.no/api/data/EXR/B.USD.NOK.SP?format=csv
A10: First observation (formula) | B10: =IFERROR(_xlfn.MINIFS($A$15:$A$2821,B$15:B$2821,">=-1E+99"),"N/A") -> 42373 | C10: =IFERROR(_xlfn.MINIFS($A$15:$A$2821,C$15:C$2821,">=-1E+99"),"N/A") -> 42373 | D10: =IFERROR(_xlfn.MINIFS($A$15:$A$2821,D$15:D$2821,">=-1E+99"),"N/A") -> 42373 | E10: =IFERROR(_xlfn.MINIFS($A$15:$A$2821,E$15:E$2821,">=-1E+99"),"N/A") -> 42373 | F10: =IFERROR(_xlfn.MINIFS($A$15:$A$2821,F$15:F$2821,">=-1E+99"),"N/A") -> 42373 | G10: =IFERROR(_xlfn.MINIFS($A$15:$A$2821,G$15:G$2821,">=-1E+99"),"N/A") -> 42373 | H10: =IFERROR(_xlfn.MINIFS($A$15:$A$2821,H$15:H$2821,">=-1E+99"),"N/A") -> 42373 | I10: =IFERROR(_xlfn.MINIFS($A$15:$A$2821,I$15:I$2821,">=-1E+99"),"N/A") -> 42373 | ... P10: =IFERROR(_xlfn.MINIFS($A$15:$A$2821,P$15:P$2821,">=-1E+99"),"N/A") -> 42373
A11: Last observation (formula) | B11: =IFERROR(_xlfn.MAXIFS($A$15:$A$2821,B$15:B$2821,">=-1E+99"),"N/A") -> 46297 | C11: =IFERROR(_xlfn.MAXIFS($A$15:$A$2821,C$15:C$2821,">=-1E+99"),"N/A") -> 46297 | D11: =IFERROR(_xlfn.MAXIFS($A$15:$A$2821,D$15:D$2821,">=-1E+99"),"N/A") -> 46297 | E11: =IFERROR(_xlfn.MAXIFS($A$15:$A$2821,E$15:E$2821,">=-1E+99"),"N/A") -> 46297 | F11: =IFERROR(_xlfn.MAXIFS($A$15:$A$2821,F$15:F$2821,">=-1E+99"),"N/A") -> 46297 | G11: =IFERROR(_xlfn.MAXIFS($A$15:$A$2821,G$15:G$2821,">=-1E+99"),"N/A") -> 46297 | H11: =IFERROR(_xlfn.MAXIFS($A$15:$A$2821,H$15:H$2821,">=-1E+99"),"N/A") -> 46297 | I11: =IFERROR(_xlfn.MAXIFS($A$15:$A$2821,I$15:I$2821,">=-1E+99"),"N/A") -> 46301 | ... P11: =IFERROR(_xlfn.MAXIFS($A$15:$A$2821,P$15:P$2821,">=-1E+99"),"N/A") -> 46301
A12: Last value (formula) | B12: =IFERROR(INDEX(B$15:B$2821,MATCH(B11,$A$15:$A$2821,0)),"N/A") -> 1345.75 | C12: =IFERROR(INDEX(C$15:C$2821,MATCH(C11,$A$15:$A$2821,0)),"N/A") -> 9.6386 | D12: =IFERROR(INDEX(D$15:D$2821,MATCH(D11,$A$15:$A$2821,0)),"N/A") -> 1.3234 | E12: =IFERROR(INDEX(E$15:E$2821,MATCH(E11,$A$15:$A$2821,0)),"N/A") -> 1.1259 | F12: =IFERROR(INDEX(F$15:F$2821,MATCH(F11,$A$15:$A$2821,0)),"N/A") -> 6.7038 | G12: =IFERROR(INDEX(G$15:G$2821,MATCH(G11,$A$15:$A$2821,0)),"N/A") -> 5.2222 | H12: =IFERROR(INDEX(H$15:H$2821,MATCH(H11,$A$15:$A$2821,0)),"N/A") -> 157.81 | I12: =IFERROR(INDEX(I$15:I$2821,MATCH(I11,$A$15:$A$2821,0)),"N/A") -> 1.1269 | ... P12: =IFERROR(INDEX(P$15:P$2821,MATCH(P11,$A$15:$A$2821,0)),"N/A") -> 9.5643
A13: Observations (count, formula) | B13: =COUNT(B$15:B$2821) -> 2687 | C13: =COUNT(C$15:C$2821) -> 2687 | D13: =COUNT(D$15:D$2821) -> 2687 | E13: =COUNT(E$15:E$2821) -> 2687 | F13: =COUNT(F$15:F$2821) -> 2687 | G13: =COUNT(G$15:G$2821) -> 2687 | H13: =COUNT(H$15:H$2821) -> 2687 | I13: =COUNT(I$15:I$2821) -> 2755 | ... P13: =COUNT(P$15:P$2821) -> 2708
A14: Date | B14: KRW per USD | C14: NOK per USD | D14: USD per GBP | E14: USD per EUR | F14: CNY per USD | G14: BRL per USD (reference only) | H14: JPY per USD (reference only) | I14: USD per EUR (ECB ref.) | J14: NOK per EUR (ECB ref.) | K14: KRW per EUR (ECB ref.) | L14: GBP per EUR (ECB ref.) | M14: CNY per EUR (ECB ref.) | N14: BRL per EUR (ECB ref.) | O14: JPY per EUR (ECB ref.) | P14: NOK per USD (Norges Bank)
A15: 42373 | B15: 1191.46 | C15: 8.9246 | D15: 1.4686 | E15: 1.0803 | F15: 6.5338 | G15: 4.0613 | H15: 119.3 | I15: 1.0898 | J15: 9.6475 | K15: 1297.87 | L15: 0.7381 | M15: 7.1208 | N15: 4.4023 | O15: 129.78 | P15: 8.8525
A16: 42374 | B16: 1190.43 | C16: 8.9165 | D16: 1.4664 | E16: 1.0743 | F16: 6.5219 | G16: 4.0108 | H16: 118.95 | I16: 1.0746 | J16: 9.588 | K16: 1277.02 | L16: 0.73235 | M16: 7.0074 | N16: 4.3023 | O16: 127.88 | P16: 8.9224
A17: 42375 | B17: 1200.16 | C17: 8.9668 | D17: 1.4626 | E17: 1.0762 | F17: 6.5554 | G17: 4.0163 | H17: 118.54 | I17: 1.0742 | J17: 9.6225 | K17: 1289.2 | L17: 0.7344 | M17: 7.0388 | N17: 4.3331 | O17: 127.19 | P17: 8.9578
A18: 42376 | B18: 1193.05 | C18: 8.919 | D18: 1.4579 | E18: 1.086 | F18: 6.5926 | G18: 4.0504 | H18: 118 | I18: 1.0868 | J18: 9.6975 | K18: 1306.87 | L18: 0.74545 | M18: 7.1672 | N18: 4.4001 | O18: 127.74 | P18: 8.923
A19: 42377 | B19: 1206.97 | C19: 8.9045 | D19: 1.4523 | E19: 1.0885 | F19: 6.5932 | G19: 4.048 | H19: 117.74 | I19: 1.0861 | J19: 9.681 | K19: 1304.78 | L19: 0.74519 | M19: 7.1577 | N19: 4.3685 | O19: 128.51 | P19: 8.9135
A20: 42380 | B20: 1206.55 | C20: 8.9399 | D20: 1.4564 | E20: 1.0878 | F20: 6.5675 | G20: 4.0464 | H20: 117.48 | I20: 1.0888 | J20: 9.677 | K20: 1309.12 | L20: 0.74705 | M20: 7.1554 | N20: 4.3786 | O20: 128.33 | P20: 8.8878
A21: 42381 | B21: 1208.95 | C21: 8.9039 | D21: 1.4403 | E21: 1.0837 | F21: 6.57 | G21: 4.0454 | H21: 117.78 | I21: 1.0836 | J21: 9.6388 | K21: 1308.87 | L21: 0.7508 | M21: 7.1276 | N21: 4.3704 | O21: 127.79 | P21: 8.8952
A22: 42382 | B22: 1208.95 | C22: 8.8019 | D22: 1.447 | E22: 1.0862 | F22: 6.57 | G22: 3.9893 | H22: 118.06 | I22: 1.0816 | J22: 9.5588 | K22: 1301.18 | L22: 0.7502 | M22: 7.1121 | N22: 4.3214 | O22: 127.74 | P22: 8.8376
A23: 42383 | B23: 1211.28 | C23: 8.7635 | D23: 1.4409 | E23: 1.0862 | F23: 6.5891 | G23: 4.0032 | H23: 118.03 | I23: 1.0893 | J23: 9.6071 | K23: 1320.77 | L23: 0.75703 | M23: 7.1809 | N23: 4.373 | O23: 128.26 | P23: 8.8195
A24: 42384 | B24: 1216.95 | C24: 8.8195 | D24: 1.4289 | E24: 1.0964 | F24: 6.584 | G24: 4.048 | H24: 116.78 | I24: 1.0914 | J24: 9.6085 | K24: 1328.97 | L24: 0.7615 | M24: 7.1888 | N24: 4.4139 | O24: 127.8 | P24: 8.8038
A25: 42387 | I25: 1.0892 | J25: 9.6878 | K25: 1317.44 | L25: 0.76263 | M25: 7.1658 | N25: 4.3929 | O25: 127.78 | P25: 8.8944
A26: 42388 | B26: 1205.61 | C26: 8.7946 | D26: 1.4171 | E26: 1.0906 | F26: 6.5783 | G26: 4.042 | H26: 117.66 | I26: 1.0868 | J26: 9.6209 | K26: 1306.89 | L26: 0.76473 | M26: 7.1496 | N26: 4.3758 | O26: 128.12 | P26: 8.8525
A27: 42389 | B27: 1215.4 | C27: 8.898 | D27: 1.4167 | E27: 1.0908 | F27: 6.5781 | G27: 4.1103 | H27: 116.38 | I27: 1.0907 | J27: 9.665 | K27: 1326.46 | L27: 0.77 | M27: 7.1768 | N27: 4.4559 | O27: 127.28 | P27: 8.8613
A28: 42390 | B28: 1204.31 | C28: 8.8153 | D28: 1.4198 | E28: 1.0833 | F28: 6.5794 | G28: 4.1299 | H28: 117.61 | I28: 1.0893 | J28: 9.7033 | K28: 1321.64 | L28: 0.77182 | M28: 7.1666 | N28: 4.523 | O28: 127.43 | P28: 8.9078
A29: 42391 | B29: 1195.66 | C29: 8.759 | D29: 1.4308 | E29: 1.0814 | F29: 6.5788 | G29: 4.1061 | H29: 118.37 | I29: 1.0808 | J29: 9.4685 | K29: 1292.83 | L29: 0.75459 | M29: 7.1104 | N29: 4.455 | O29: 127.77 | P29: 8.7606
A30: 42394 | B30: 1194.3 | C30: 8.7447 | D30: 1.4245 | E30: 1.0832 | F30: 6.579 | G30: 4.0887 | H30: 118.55 | I30: 1.0815 | J30: 9.4585 | K30: 1293.53 | L30: 0.7589 | M30: 7.1156 | N30: 4.4276 | O30: 128.07 | P30: 8.7457
A31: 42395 | B31: 1199.64 | C31: 8.6972 | D31: 1.4342 | E31: 1.0846 | F31: 6.5814 | G31: 4.0701 | H31: 118.5 | I31: 1.0837 | J31: 9.4858 | K31: 1303.82 | L31: 0.76095 | M31: 7.1314 | N31: 4.4465 | O31: 128.22 | P31: 8.7532
A32: 42396 | B32: 1199.25 | C32: 8.6589 | D32: 1.4261 | E32: 1.0867 | F32: 6.5773 | G32: 4.0557 | H32: 118.9 | I32: 1.0888 | J32: 9.4508 | K32: 1308.94 | L32: 0.75965 | M32: 7.1621 | N32: 4.3963 | O32: 128.91 | P32: 8.68
A33: 42397 | B33: 1204.08 | C33: 8.6332 | D33: 1.4351 | E33: 1.0952 | F33: 6.5744 | G33: 4.0979 | H33: 118.61 | I33: 1.0903 | J33: 9.4465 | K33: 1316.36 | L33: 0.76228 | M33: 7.1705 | N33: 4.4753 | O33: 129.62 | P33: 8.6641
A34: 42398 | B34: 1210.04 | C34: 8.7071 | D34: 1.4184 | E34: 1.0832 | F34: 6.5752 | G34: 4.0364 | H34: 121.05 | I34: 1.092 | J34: 9.4845 | K34: 1318.6 | L34: 0.7641 | M34: 7.181 | N34: 4.4294 | O34: 132.25 | P34: 8.6854
A35: 42401 | B35: 1203.19 | C35: 8.7104 | D35: 1.4367 | E35: 1.0888 | F35: 6.5778 | G35: 3.9866 | H35: 121.06 | I35: 1.0884 | J35: 9.416 | K35: 1310.43 | L35: 0.761 | M35: 7.1605 | N35: 4.3511 | O35: 131.99 | P35: 8.6512
A36: 42402 | B36: 1212.01 | C36: 8.7184 | D36: 1.4399 | E36: 1.0908 | F36: 6.5795 | G36: 3.9885 | H36: 120.27 | I36: 1.0919 | J36: 9.5223 | K36: 1322.58 | L36: 0.7586 | M36: 7.1847 | N36: 4.3565 | O36: 131.84 | P36: 8.7209
A37: 42403 | B37: 1211.33 | C37: 8.6074 | D37: 1.4576 | E37: 1.1051 | F37: 6.5765 | G37: 3.9478 | H37: 117.92 | I37: 1.0933 | J37: 9.5138 | K37: 1329.87 | L37: 0.7533 | M37: 7.1916 | N37: 4.328 | O37: 130.58 | P37: 8.7019
... A44: 42412 | B44: 1205.13 | C44: 8.5917 | D44: 1.446 | E44: 1.1235 | F44: 6.571 | G44: 3.9764 | H44: 112.96 | I44: 1.1275 | J44: 9.6773 | K44: 1359.98 | L44: 0.77735 | M44: 7.4114 | N44: 4.5087 | O44: 127.07 | P44: 8.583
A45: 42415 | I45: 1.118 | J45: 9.6313 | K45: 1352.15 | L45: 0.772 | M45: 7.2606 | N45: 4.4567 | O45: 127.6 | P45: 8.6148
A46: 42416 | B46: 1219.44 | C46: 8.6203 | D46: 1.429 | E46: 1.114 | F46: 6.5154 | G46: 4.0564 | H46: 113.9 | I46: 1.1166 | J46: 9.6049 | K46: 1358.7 | L46: 0.7758 | M46: 7.2741 | N46: 4.4833 | O46: 127.02 | P46: 8.6019
A47: 42417 | B47: 1222.32 | C47: 8.5696 | D47: 1.4317 | E47: 1.114 | F47: 6.527 | G47: 3.9856 | H47: 114.14 | I47: 1.1136 | J47: 9.5955 | K47: 1368.24 | L47: 0.77835 | M47: 7.2685 | N47: 4.4866 | O47: 127.1 | P47: 8.6166
A48: 42418 | B48: 1231.15 | C48: 8.5961 | D48: 1.4333 | E48: 1.1092 | F48: 6.5163 | G48: 4.0191 | H48: 113.62 | I48: 1.1084 | J48: 9.5235 | K48: 1362.2 | L48: 0.77143 | M48: 7.2242 | N48: 4.4527 | O48: 126.17 | P48: 8.5921
A49: 42419 | B49: 1231.09 | C49: 8.5654 | D49: 1.4343 | E49: 1.1127 | F49: 6.5202 | G49: 4.0428 | H49: 112.42 | I49: 1.1096 | J49: 9.5358 | K49: 1368.69 | L49: 0.77715 | M49: 7.2378 | N49: 4.4854 | O49: 125.4 | P49: 8.5939
A50: 42422 | B50: 1223.32 | C50: 8.5997 | D50: 1.4157 | E50: 1.1018 | F50: 6.5197 | G50: 3.933 | H50: 113.12 | I50: 1.1026 | J50: 9.493 | K50: 1351.19 | L50: 0.78243 | M50: 7.1909 | N50: 4.3755 | O50: 124.85 | P50: 8.6096
A51: 42423 | B51: 1230.05 | C51: 8.5984 | D51: 1.404 | E51: 1.1016 | F51: 6.5263 | G51: 3.974 | H51: 112.17 | I51: 1.1002 | J51: 9.459 | K51: 1353.46 | L51: 0.77985 | M51: 7.1814 | N51: 4.357 | O51: 123.12 | P51: 8.5975
A52: 42424 | B52: 1234.6 | C52: 8.6713 | D52: 1.3932 | E52: 1.1021 | F52: 6.529 | G52: 3.9774 | H52: 111.36 | I52: 1.0981 | J52: 9.5858 | K52: 1359.58 | L52: 0.78935 | M52: 7.1794 | N52: 4.3793 | O52: 122.86 | P52: 8.7294
A53: 42425 | B53: 1237.39 | C53: 8.6532 | D53: 1.3937 | E53: 1.1026 | F53: 6.532 | G53: 3.929 | H53: 112.7 | I53: 1.1027 | J53: 9.5413 | K53: 1366.74 | L53: 0.7892 | M53: 7.2026 | N53: 4.3527 | O53: 124.01 | P53: 8.6527
A54: 42426 | B54: 1242.59 | C54: 8.6826 | D54: 1.3867 | E54: 1.0932 | F54: 6.539 | G54: 4.012 | H54: 113.78 | I54: 1.1006 | J54: 9.5245 | K54: 1360.34 | L54: 0.78745 | M54: 7.1954 | N54: 4.3356 | O54: 124.42 | P54: 8.6539
A55: 42429 | B55: 1238.09 | C55: 8.6919 | D55: 1.3926 | E55: 1.0868 | F55: 6.5525 | G55: 3.9793 | H55: 112.9 | I55: 1.0888 | J55: 9.5043 | K55: 1347.54 | L55: 0.7858 | M55: 7.1351 | N55: 4.3394 | O55: 123.14 | P55: 8.7292
A56: 42430 | B56: 1229.56 | C56: 8.6574 | D56: 1.3948 | E56: 1.0847 | F56: 6.55 | G56: 3.9475 | H56: 113.94 | I56: 1.0872 | J56: 9.407 | K56: 1340.06 | L56: 0.778 | M56: 7.123 | N56: 4.3519 | O56: 122.94 | P56: 8.6525
A57: 42431 | B57: 1227.59 | C57: 8.7023 | D57: 1.4059 | E57: 1.0845 | F57: 6.5499 | G57: 3.8948 | H57: 113.81 | I57: 1.0856 | J57: 9.422 | K57: 1334.29 | L57: 0.7741 | M57: 7.1125 | N57: 4.2523 | O57: 124.07 | P57: 8.6791
... A72: 42452 | B72: 1166.59 | C72: 8.4854 | D72: 1.4111 | E72: 1.1174 | F72: 6.5035 | G72: 3.6735 | H72: 112.63 | I72: 1.1171 | J72: 9.4863 | K72: 1300.58 | L72: 0.78985 | M72: 7.2648 | N72: 4.06 | O72: 126.01 | P72: 8.4364
A73: 42453 | B73: 1168.09 | C73: 8.4995 | D73: 1.4143 | E73: 1.1163 | F73: 6.5124 | G73: 3.7043 | H73: 112.64 | I73: 1.1154 | J73: 9.494 | K73: 1302.21 | L73: 0.78938 | M73: 7.2662 | N73: 4.1316 | O73: 125.41
A74: 42454 | B74: 1168.19 | C74: 8.4853 | D74: 1.4131 | E74: 1.1164 | F74: 6.5131 | G74: 3.7028 | H74: 113.05
A75: 42457 | B75: 1163.39 | C75: 8.4195 | D75: 1.425 | E75: 1.121 | F75: 6.5051 | G75: 3.639 | H75: 113.29
A76: 42458 | B76: 1164.69 | C76: 8.4597 | D76: 1.4281 | E76: 1.1204 | F76: 6.5063 | G76: 3.6726 | H76: 113.33 | I76: 1.1194 | J76: 9.4839 | K76: 1306.67 | L76: 0.7845 | M76: 7.2873 | N76: 4.0795 | O76: 127.13 | P76: 8.4723
A77: 42459 | B77: 1142.02 | C77: 8.3215 | D77: 1.439 | E77: 1.133 | F77: 6.4648 | G77: 3.6145 | H77: 112.6 | I77: 1.1324 | J77: 9.43 | K77: 1293.67 | L77: 0.7858 | M77: 7.3366 | N77: 4.1275 | O77: 127.37 | P77: 8.3274
A78: 42460 | B78: 1138.86 | C78: 8.252 | D78: 1.4381 | E78: 1.139 | F78: 6.448 | G78: 3.55 | H78: 112.42 | I78: 1.1385 | J78: 9.4145 | K78: 1294.88 | L78: 0.79155 | M78: 7.3514 | N78: 4.1174 | O78: 127.9 | P78: 8.2692
A79: 42461 | B79: 1147.15 | C79: 8.3127 | D79: 1.4204 | E79: 1.1385 | F79: 6.4776 | G79: 3.541 | H79: 112.06 | I79: 1.1432 | J79: 9.4401 | K79: 1315.78 | L79: 0.7989 | M79: 7.3903 | N79: 4.1296 | O79: 128.07 | P79: 8.2576
A80: 42464 | B80: 1151.35 | C80: 8.3098 | D80: 1.4279 | E80: 1.1386 | F80: 6.4776 | G80: 3.5994 | H80: 111.18 | I80: 1.138 | J80: 9.4359 | K80: 1308.19 | L80: 0.79738 | M80: 7.3696 | N80: 4.042 | O80: 126.97 | P80: 8.2917
A81: 42465 | B81: 1158.39 | C81: 8.3486 | D81: 1.4149 | E81: 1.1374 | F81: 6.476 | G81: 3.6659 | H81: 110.26 | I81: 1.1367 | J81: 9.4995 | K81: 1317.17 | L81: 0.8016 | M81: 7.3595 | N81: 4.1395 | O81: 125.81 | P81: 8.3571
A82: 42466 | B82: 1155.28 | C82: 8.2844 | D82: 1.4162 | E82: 1.143 | F82: 6.478 | G82: 3.6538 | H82: 109.63 | I82: 1.1336 | J82: 9.476 | K82: 1318.35 | L82: 0.80808 | M82: 7.355 | N82: 4.2 | O82: 125.13 | P82: 8.3592
A83: 42467 | B83: 1156.81 | C83: 8.3254 | D83: 1.4082 | E83: 1.1386 | F83: 6.4599 | G83: 3.7106 | H83: 107.98 | I83: 1.1364 | J83: 9.4546 | K83: 1318.1 | L83: 0.80728 | M83: 7.3535 | N83: 4.1617 | O83: 123.15 | P83: 8.3198
A84: 42468 | B84: 1148.89 | C84: 8.223 | D84: 1.4105 | E84: 1.1406 | F84: 6.4628 | G84: 3.6288 | H84: 108.36 | I84: 1.1363 | J84: 9.4183 | K84: 1310.43 | L84: 0.8073 | M84: 7.357 | N84: 4.1554 | O84: 123.36 | P84: 8.2886
A85: 42471 | B85: 1141.97 | C85: 8.1972 | D85: 1.424 | E85: 1.1412 | F85: 6.458 | G85: 3.516 | H85: 107.96 | I85: 1.139 | J85: 9.3809 | K85: 1306.55 | L85: 0.8006 | M85: 7.3709 | N85: 4.0647 | O85: 123.28 | P85: 8.2361
A86: 42472 | B86: 1144.53 | C86: 8.1703 | D86: 1.4244 | E86: 1.1395 | F86: 6.4639 | G86: 3.552 | H86: 108.54 | I86: 1.1396 | J86: 9.3515 | K86: 1302.88 | L86: 0.7984 | M86: 7.3632 | N86: 4.0034 | O86: 123.44 | P86: 8.2059
A87: 42473 | B87: 1146.29 | C87: 8.2299 | D87: 1.4223 | E87: 1.1281 | F87: 6.4768 | G87: 3.5606 | H87: 109.21 | I87: 1.1298 | J87: 9.3113 | K87: 1298.14 | L87: 0.79388 | M87: 7.3172 | N87: 3.969 | O87: 123.47 | P87: 8.2415
... A102: 42494 | B102: 1164.59 | C102: 8.1466 | D102: 1.4475 | E102: 1.1486 | F102: 6.4945 | G102: 3.5339 | H102: 107.12 | I102: 1.1505 | J102: 9.341 | K102: 1338.14 | L102: 0.79284 | M102: 7.4789 | N102: 4.1091 | O102: 122.62 | P102: 8.1191
A103: 42495 | B103: 1165.93 | C103: 8.1613 | D103: 1.4486 | E103: 1.1404 | F103: 6.5032 | G103: 3.526 | H103: 107.32 | I103: 1.1439 | J103: 9.2985 | K103: 1333.95 | L103: 0.7886 | M103: 7.441 | N103: 4.0282 | O103: 122.51
A104: 42496 | B104: 1167.29 | C104: 8.1868 | D104: 1.4439 | E104: 1.1421 | F104: 6.497 | G104: 3.5255 | H104: 106.66 | I104: 1.1427 | J104: 9.3513 | K104: 1339.64 | L104: 0.7885 | M104: 7.43 | N104: 4.065 | O104: 122.23 | P104: 8.1835
A105: 42499 | B105: 1174.25 | C105: 8.2147 | D105: 1.4409 | E105: 1.1402 | F105: 6.514 | G105: 3.556 | H105: 108.39 | I105: 1.1395 | J105: 9.333 | K105: 1337.36 | L105: 0.78998 | M105: 7.4207 | N105: 3.9971 | O105: 123.39 | P105: 8.1904
A106: 42500 | B106: 1169.89 | C106: 8.2055 | D106: 1.4454 | E106: 1.1386 | F106: 6.515 | G106: 3.4742 | H106: 109.22 | I106: 1.1375 | J106: 9.352 | K106: 1334.99 | L106: 0.7876 | M106: 7.413 | N106: 3.9647 | O106: 124.12 | P106: 8.2215
A107: 42501 | B107: 1162.47 | C107: 8.1339 | D107: 1.448 | E107: 1.1444 | F107: 6.491 | G107: 3.4594 | H107: 108.48 | I107: 1.1409 | J107: 9.3475 | K107: 1332.79 | L107: 0.78958 | M107: 7.4212 | N107: 3.9517 | O107: 124.09 | P107: 8.1931
A108: 42502 | B108: 1168.7 | C108: 8.1522 | D108: 1.4452 | E108: 1.138 | F108: 6.514 | G108: 3.4942 | H108: 108.73 | I108: 1.1389 | J108: 9.232 | K108: 1331.57 | L108: 0.78888 | M108: 7.4242 | N108: 3.9419 | O108: 124.5 | P108: 8.1061
A109: 42503 | B109: 1176.85 | C109: 8.2157 | D109: 1.4369 | E109: 1.1294 | F109: 6.5285 | G109: 3.5075 | H109: 109.14 | I109: 1.1348 | J109: 9.2678 | K109: 1330.91 | L109: 0.78758 | M109: 7.4001 | N109: 3.9559 | O109: 123.56 | P109: 8.1669
A110: 42506 | B110: 1177.21 | C110: 8.1476 | D110: 1.4411 | E110: 1.1328 | F110: 6.5184 | G110: 3.5034 | H110: 108.89 | I110: 1.1324 | J110: 9.237 | K110: 1335.9 | L110: 0.788 | M110: 7.3865 | N110: 3.9999 | O110: 123.27
A111: 42507 | B111: 1173.67 | C111: 8.1578 | D111: 1.4485 | E111: 1.1337 | F111: 6.517 | G111: 3.4942 | H111: 109.02 | I111: 1.1318 | J111: 9.2558 | K111: 1331.66 | L111: 0.7815 | M111: 7.3867 | N111: 3.9451 | O111: 123.93
A112: 42508 | B112: 1185.77 | C112: 8.2253 | D112: 1.4615 | E112: 1.1276 | F112: 6.537 | G112: 3.5268 | H112: 109.65 | I112: 1.1279 | J112: 9.2785 | K112: 1340.31 | L112: 0.77485 | M112: 7.3714 | N112: 3.9891 | O112: 123.38 | P112: 8.2263
A113: 42509 | B113: 1189.25 | C113: 8.3497 | D113: 1.4608 | E113: 1.1214 | F113: 6.544 | G113: 3.6051 | H113: 109.81 | I113: 1.1197 | J113: 9.3593 | K113: 1333.5 | L113: 0.76585 | M113: 7.3318 | N113: 4.0146 | O113: 123.17 | P113: 8.3588
A114: 42510 | B114: 1186.93 | C114: 8.3272 | D114: 1.4513 | E114: 1.1207 | F114: 6.5485 | G114: 3.5386 | H114: 110.52 | I114: 1.1219 | J114: 9.3355 | K114: 1332.02 | L114: 0.77008 | M114: 7.3456 | N114: 3.9797 | O114: 123.81 | P114: 8.3212
A115: 42513 | B115: 1183.39 | C115: 8.365 | D115: 1.4444 | E115: 1.1192 | F115: 6.5533 | G115: 3.5753 | H115: 109.47 | I115: 1.1215 | J115: 9.3658 | K115: 1329.78 | L115: 0.77443 | M115: 7.3507 | N115: 3.9832 | O115: 122.7 | P115: 8.3511
A116: 42514 | B116: 1186.39 | C116: 8.3515 | D116: 1.4623 | E116: 1.1145 | F116: 6.5552 | G116: 3.5518 | H116: 110 | I116: 1.1168 | J116: 9.3355 | K116: 1329.32 | L116: 0.76513 | M116: 7.3226 | N116: 3.9639 | O116: 122.56 | P116: 8.3592
A117: 42515 | B117: 1182.21 | C117: 8.3389 | D117: 1.4694 | E117: 1.1154 | F117: 6.5538 | G117: 3.6072 | H117: 110.22 | I117: 1.1146 | J117: 9.2945 | K117: 1317.16 | L117: 0.75925 | M117: 7.3136 | N117: 3.9681 | O117: 122.79 | P117: 8.3389
A118: 42516 | B118: 1178.09 | C118: 8.2705 | D118: 1.4673 | E118: 1.1184 | F118: 6.554 | G118: 3.5775 | H118: 109.74 | I118: 1.1168 | J118: 9.247 | K118: 1317.87 | L118: 0.7597 | M118: 7.3237 | N118: 4.0004 | O118: 122.93 | P118: 8.2799
A119: 42517 | B119: 1180.59 | C119: 8.3221 | D119: 1.4644 | E119: 1.114 | F119: 6.5615 | G119: 3.6122 | H119: 109.86 | I119: 1.1168 | J119: 9.282 | K119: 1316.98 | L119: 0.76245 | M119: 7.3281 | N119: 4.031 | O119: 122.46 | P119: 8.3112
A120: 42520 | I120: 1.1139 | J120: 9.3025 | K120: 1326.59 | L120: 0.76125 | M120: 7.3314 | N120: 4.0148 | O120: 123.85 | P120: 8.3513
A121: 42521 | B121: 1188.99 | C121: 8.3678 | D121: 1.453 | E121: 1.1135 | F121: 6.5798 | G121: 3.6074 | H121: 110.75 | I121: 1.1154 | J121: 9.32 | K121: 1326.11 | L121: 0.76185 | M121: 7.3363 | N121: 3.985 | O121: 123.83 | P121: 8.3557
A122: 42522 | B122: 1192.09 | C122: 8.3099 | D122: 1.4395 | E122: 1.1165 | F122: 6.5748 | G122: 3.603 | H122: 109.55 | I122: 1.1174 | J122: 9.3083 | K122: 1331.53 | L122: 0.77358 | M122: 7.3498 | N122: 4.0211 | O122: 122.07 | P122: 8.3303
A123: 42523 | B123: 1186.69 | C123: 8.3355 | D123: 1.4419 | E123: 1.1157 | F123: 6.5815 | G123: 3.5978 | H123: 108.75 | I123: 1.1188 | J123: 9.336 | K123: 1329.35 | L123: 0.77335 | M123: 7.3639 | N123: 4.0235 | O123: 121.96 | P123: 8.3447
A124: 42524 | B124: 1167.79 | C124: 8.2017 | D124: 1.4521 | E124: 1.133 | F124: 6.5638 | G124: 3.5332 | H124: 106.88 | I124: 1.1154 | J124: 9.2853 | K124: 1322.41 | L124: 0.77285 | M124: 7.3468 | N124: 3.9973 | O124: 121.47 | P124: 8.3246
A125: 42527 | B125: 1162.28 | C125: 8.1761 | D125: 1.445 | E125: 1.1354 | F125: 6.5611 | G125: 3.5094 | H125: 107.33 | I125: 1.1349 | J125: 9.2935 | K125: 1323 | L125: 0.7872 | M125: 7.452 | N125: 3.9934 | O125: 121.58 | P125: 8.1888
A126: 42528 | B126: 1154.8 | C126: 8.1332 | D126: 1.4564 | E126: 1.135 | F126: 6.571 | G126: 3.4604 | H126: 107.3 | I126: 1.1348 | J126: 9.2225 | K126: 1311.68 | L126: 0.7788 | M126: 7.4579 | N126: 3.9788 | O126: 122.16 | P126: 8.127
A127: 42529 | B127: 1153.83 | C127: 8.1101 | D127: 1.4546 | E127: 1.14 | F127: 6.56 | G127: 3.377 | H127: 106.68 | I127: 1.1378 | J127: 9.2055 | K127: 1311.38 | L127: 0.78048 | M127: 7.4727 | N127: 3.8786 | O127: 121.77 | P127: 8.0906
A128: 42530 | B128: 1159.29 | C128: 8.1486 | D128: 1.4467 | E128: 1.1329 | F128: 6.559 | G128: 3.3934 | H128: 106.54 | I128: 1.1343 | J128: 9.2489 | K128: 1316.56 | L128: 0.78438 | M128: 7.4405 | N128: 3.8378 | O128: 120.72 | P128: 8.1538
A129: 42531 | B129: 1167.61 | C129: 8.2325 | D129: 1.4342 | E129: 1.1281 | F129: 6.559 | G129: 3.4298 | H129: 107.06 | I129: 1.1304 | J129: 9.2725 | K129: 1316.14 | L129: 0.7848 | M129: 7.4143 | N129: 3.8662 | O129: 120.79 | P129: 8.2028
A130: 42534 | B130: 1169.74 | C130: 8.2787 | D130: 1.4223 | E130: 1.1282 | F130: 6.5823 | G130: 3.4599 | H130: 106.07 | I130: 1.1268 | J130: 9.3265 | K130: 1322.63 | L130: 0.79515 | M130: 7.4212 | N130: 3.876 | O130: 119.51 | P130: 8.277
A131: 42535 | B131: 1176.78 | C131: 8.3513 | D131: 1.413 | E131: 1.1206 | F131: 6.593 | G131: 3.4959 | H131: 106.02 | I131: 1.1225 | J131: 9.3655 | K131: 1324.26 | L131: 0.79478 | M131: 7.4015 | N131: 3.9273 | O131: 118.98 | P131: 8.3434
A132: 42536 | B132: 1167.53 | C132: 8.313 | D132: 1.4185 | E132: 1.1239 | F132: 6.5785 | G132: 3.4715 | H132: 105.87 | I132: 1.123 | J132: 9.3415 | K132: 1316.08 | L132: 0.79158 | M132: 7.3905 | N132: 3.8945 | O132: 119.29 | P132: 8.3183
... A144: 42552 | B144: 1146.49 | C144: 8.3279 | D144: 1.3281 | E144: 1.1145 | F144: 6.6547 | G144: 3.2448 | H144: 102.55 | I144: 1.1135 | J144: 9.2975 | K144: 1275.76 | L144: 0.8383 | M144: 7.4111 | N144: 3.5837 | O144: 114.29 | P144: 8.3498
A145: 42555 | I145: 1.1138 | J145: 9.2538 | K145: 1278.83 | L145: 0.83905 | M145: 7.4229 | N145: 3.6131 | O145: 114.29 | P145: 8.3083
A146: 42556 | B146: 1156.79 | C146: 8.4065 | D146: 1.3021 | E146: 1.108 | F146: 6.677 | G146: 3.2964 | H146: 101.58 | I146: 1.1146 | J146: 9.3197 | K146: 1289.88 | L146: 0.84997 | M146: 7.4379 | N146: 3.6655 | O146: 113.5 | P146: 8.3615
...

Sheet FX_Monthly
A1: FX_Monthly — monthly average exchange rates (formulas on FX_Daily)
A2: As-of date: 2026-10-07 | Retrieval date: 2026-10-07 | Blue font = raw value from source; black = formula. All values are AVERAGEIFS formulas over FX_Daily.
A4: Provider | B4: FRED (St. Louis Fed); original source Federal Reserve Board H.10 | C4: FRED (St. Louis Fed); original source Federal Reserve Board H.10 | D4: FRED (St. Louis Fed); original source Federal Reserve Board H.10 | E4: FRED (St. Louis Fed); original source Federal Reserve Board H.10 | F4: FRED (St. Louis Fed); original source Federal Reserve Board H.10 | G4: FRED (St. Louis Fed); original source Federal Reserve Board H.10 | H4: FRED (St. Louis Fed); original source Federal Reserve Board H.10 | I4: European Central Bank (ECB Data Portal) | J4: European Central Bank (ECB Data Portal) | K4: European Central Bank (ECB Data Portal) | L4: European Central Bank (ECB Data Portal) | M4: European Central Bank (ECB Data Portal) | N4: European Central Bank (ECB Data Portal) | O4: European Central Bank (ECB Data Portal) | P4: Norges Bank (data.norges-bank.no) | Q4: Formula | R4: Formula
A5: Series ID / table | B5: DEXKOUS (monthly average computed from FX_Daily) | C5: DEXNOUS (monthly average computed from FX_Daily) | D5: DEXUSUK (monthly average computed from FX_Daily) | E5: DEXUSEU (monthly average computed from FX_Daily) | F5: DEXCHUS (monthly average computed from FX_Daily) | G5: DEXBZUS (monthly average computed from FX_Daily) | H5: DEXJPUS (monthly average computed from FX_Daily) | I5: EXR.D.USD.EUR.SP00.A (monthly average computed from FX_Daily) | J5: EXR.D.NOK.EUR.SP00.A (monthly average computed from FX_Daily) | K5: EXR.D.KRW.EUR.SP00.A (monthly average computed from FX_Daily) | L5: EXR.D.GBP.EUR.SP00.A (monthly average computed from FX_Daily) | M5: EXR.D.CNY.EUR.SP00.A (monthly average computed from FX_Daily) | N5: EXR.D.BRL.EUR.SP00.A (monthly average computed from FX_Daily) | O5: EXR.D.JPY.EUR.SP00.A (monthly average computed from FX_Daily) | P5: EXR/B.USD.NOK.SP (monthly average computed from FX_Daily) | Q5: COUNTIFS on FX_Daily
A6: Description (quote direction) | B6: Arithmetic mean of available daily observations in the calendar month (formula on FX_Daily) | C6: Arithmetic mean of available daily observations in the calendar month (formula on FX_Daily) | D6: Arithmetic mean of available daily observations in the calendar month (formula on FX_Daily) | E6: Arithmetic mean of available daily observations in the calendar month (formula on FX_Daily) | F6: Arithmetic mean of available daily observations in the calendar month (formula on FX_Daily) | G6: Arithmetic mean of available daily observations in the calendar month (formula on FX_Daily) | H6: Arithmetic mean of available daily observations in the calendar month (formula on FX_Daily) | I6: Arithmetic mean of available daily observations in the calendar month (formula on FX_Daily) | J6: Arithmetic mean of available daily observations in the calendar month (formula on FX_Daily) | K6: Arithmetic mean of available daily observations in the calendar month (formula on FX_Daily) | L6: Arithmetic mean of available daily observations in the calendar month (formula on FX_Daily) | M6: Arithmetic mean of available daily observations in the calendar month (formula on FX_Daily) | N6: Arithmetic mean of available daily observations in the calendar month (formula on FX_Daily) | O6: Arithmetic mean of available daily observations in the calendar month (formula on FX_Daily) | P6: Arithmetic mean of available daily observations in the calendar month (formula on FX_Daily) | Q6: Number of FRED H.10 daily obs used | R6: "partial" if the month is not complete at the last FRED observation
A7: Unit | B7: South Korean Won to One U.S. Dollar | C7: Norwegian Kroner to One U.S. Dollar | D7: U.S. Dollars to One U.K. Pound Sterling | E7: U.S. Dollars to One Euro | F7: Chinese Yuan Renminbi to One U.S. Dollar | G7: Brazilian Reals to One U.S. Dollar | H7: Japanese Yen to One U.S. Dollar | I7: USD per 1 EUR | J7: NOK per 1 EUR | K7: KRW per 1 EUR | L7: GBP per 1 EUR | M7: CNY per 1 EUR | N7: BRL per 1 EUR | O7: JPY per 1 EUR | P7: NOK per 1 USD | Q7: days
A8: Frequency | B8: Monthly (average of daily) | C8: Monthly (average of daily) | D8: Monthly (average of daily) | E8: Monthly (average of daily) | F8: Monthly (average of daily) | G8: Monthly (average of daily) | H8: Monthly (average of daily) | I8: Monthly (average of daily) | J8: Monthly (average of daily) | K8: Monthly (average of daily) | L8: Monthly (average of daily) | M8: Monthly (average of daily) | N8: Monthly (average of daily) | O8: Monthly (average of daily) | P8: Monthly (average of daily) | Q8: Monthly | R8: Monthly
A9: URL | B9: https://fred.stlouisfed.org/series/DEXKOUS | C9: https://fred.stlouisfed.org/series/DEXNOUS | D9: https://fred.stlouisfed.org/series/DEXUSUK | E9: https://fred.stlouisfed.org/series/DEXUSEU | F9: https://fred.stlouisfed.org/series/DEXCHUS | G9: https://fred.stlouisfed.org/series/DEXBZUS | H9: https://fred.stlouisfed.org/series/DEXJPUS | I9: https://data.ecb.europa.eu/data/datasets/EXR/EXR.D.USD.EUR.SP00.A | J9: https://data.ecb.europa.eu/data/datasets/EXR/EXR.D.NOK.EUR.SP00.A | K9: https://data.ecb.europa.eu/data/datasets/EXR/EXR.D.KRW.EUR.SP00.A | L9: https://data.ecb.europa.eu/data/datasets/EXR/EXR.D.GBP.EUR.SP00.A | M9: https://data.ecb.europa.eu/data/datasets/EXR/EXR.D.CNY.EUR.SP00.A | N9: https://data.ecb.europa.eu/data/datasets/EXR/EXR.D.BRL.EUR.SP00.A | O9: https://data.ecb.europa.eu/data/datasets/EXR/EXR.D.JPY.EUR.SP00.A | P9: https://data.norges-bank.no/api/data/EXR/B.USD.NOK.SP?format=csv
A10: First observation (formula) | B10: =IFERROR(_xlfn.MINIFS($A$15:$A$144,B$15:B$144,">=-1E+99"),"N/A") -> 42370 | C10: =IFERROR(_xlfn.MINIFS($A$15:$A$144,C$15:C$144,">=-1E+99"),"N/A") -> 42370 | D10: =IFERROR(_xlfn.MINIFS($A$15:$A$144,D$15:D$144,">=-1E+99"),"N/A") -> 42370 | E10: =IFERROR(_xlfn.MINIFS($A$15:$A$144,E$15:E$144,">=-1E+99"),"N/A") -> 42370 | F10: =IFERROR(_xlfn.MINIFS($A$15:$A$144,F$15:F$144,">=-1E+99"),"N/A") -> 42370 | G10: =IFERROR(_xlfn.MINIFS($A$15:$A$144,G$15:G$144,">=-1E+99"),"N/A") -> 42370 | H10: =IFERROR(_xlfn.MINIFS($A$15:$A$144,H$15:H$144,">=-1E+99"),"N/A") -> 42370 | I10: =IFERROR(_xlfn.MINIFS($A$15:$A$144,I$15:I$144,">=-1E+99"),"N/A") -> 42370 | ... R10: =IFERROR(_xlfn.MINIFS($A$15:$A$144,R$15:R$144,">=-1E+99"),"N/A") -> 0
A11: Last observation (formula) | B11: =IFERROR(_xlfn.MAXIFS($A$15:$A$144,B$15:B$144,">=-1E+99"),"N/A") -> 46296 | C11: =IFERROR(_xlfn.MAXIFS($A$15:$A$144,C$15:C$144,">=-1E+99"),"N/A") -> 46296 | D11: =IFERROR(_xlfn.MAXIFS($A$15:$A$144,D$15:D$144,">=-1E+99"),"N/A") -> 46296 | E11: =IFERROR(_xlfn.MAXIFS($A$15:$A$144,E$15:E$144,">=-1E+99"),"N/A") -> 46296 | F11: =IFERROR(_xlfn.MAXIFS($A$15:$A$144,F$15:F$144,">=-1E+99"),"N/A") -> 46296 | G11: =IFERROR(_xlfn.MAXIFS($A$15:$A$144,G$15:G$144,">=-1E+99"),"N/A") -> 46296 | H11: =IFERROR(_xlfn.MAXIFS($A$15:$A$144,H$15:H$144,">=-1E+99"),"N/A") -> 46296 | I11: =IFERROR(_xlfn.MAXIFS($A$15:$A$144,I$15:I$144,">=-1E+99"),"N/A") -> 46296 | ... R11: =IFERROR(_xlfn.MAXIFS($A$15:$A$144,R$15:R$144,">=-1E+99"),"N/A") -> 0
A12: Last value (formula) | B12: =IFERROR(INDEX(B$15:B$144,MATCH(B11,$A$15:$A$144,0)),"N/A") -> 1355.29 | C12: =IFERROR(INDEX(C$15:C$144,MATCH(C11,$A$15:$A$144,0)),"N/A") -> 9.6386 | D12: =IFERROR(INDEX(D$15:D$144,MATCH(D11,$A$15:$A$144,0)),"N/A") -> 1.3215 | E12: =IFERROR(INDEX(E$15:E$144,MATCH(E11,$A$15:$A$144,0)),"N/A") -> 1.12455 | F12: =IFERROR(INDEX(F$15:F$144,MATCH(F11,$A$15:$A$144,0)),"N/A") -> 6.7038 | G12: =IFERROR(INDEX(G$15:G$144,MATCH(G11,$A$15:$A$144,0)),"N/A") -> 5.22755 | H12: =IFERROR(INDEX(H$15:H$144,MATCH(H11,$A$15:$A$144,0)),"N/A") -> 157.72 | I12: =IFERROR(INDEX(I$15:I$144,MATCH(I11,$A$15:$A$144,0)),"N/A") -> 1.1249 | ... R12: =IFERROR(INDEX(R$15:R$144,MATCH(R11,$A$15:$A$144,0)),"N/A") -> N/A
A13: Observations (count, formula) | B13: =COUNT(B$15:B$144) -> 130 | C13: =COUNT(C$15:C$144) -> 130 | D13: =COUNT(D$15:D$144) -> 130 | E13: =COUNT(E$15:E$144) -> 130 | F13: =COUNT(F$15:F$144) -> 130 | G13: =COUNT(G$15:G$144) -> 130 | H13: =COUNT(H$15:H$144) -> 130 | I13: =COUNT(I$15:I$144) -> 130 | ... R13: =COUNT(R$15:R$144) -> 0
A14: Month (first day) | B14: KRW per USD — monthly avg | C14: NOK per USD — monthly avg | D14: USD per GBP — monthly avg | E14: USD per EUR — monthly avg | F14: CNY per USD — monthly avg | G14: BRL per USD (reference only) — monthly avg | H14: JPY per USD (reference only) — monthly avg | I14: USD per EUR (ECB ref.) — monthly avg | J14: NOK per EUR (ECB ref.) — monthly avg | K14: KRW per EUR (ECB ref.) — monthly avg | L14: GBP per EUR (ECB ref.) — monthly avg | M14: CNY per EUR (ECB ref.) — monthly avg | N14: BRL per EUR (ECB ref.) — monthly avg | O14: JPY per EUR (ECB ref.) — monthly avg | P14: NOK per USD (Norges Bank) — monthly avg | Q14: Trading days in month (DEXNOUS obs) | R14: Month status
A15: 42370 | B15: =IFERROR(AVERAGEIFS(FX_Daily!B$15:B$2821,FX_Daily!$A$15:$A$2821,">="&$A15,FX_Daily!$A$15:$A$2821,"<="&EOMONTH($A15,0)),"") -> 1203.3179 | C15: =IFERROR(AVERAGEIFS(FX_Daily!C$15:C$2821,FX_Daily!$A$15:$A$2821,">="&$A15,FX_Daily!$A$15:$A$2821,"<="&EOMONTH($A15,0)),"") -> 8.8193737 | D15: =IFERROR(AVERAGEIFS(FX_Daily!D$15:D$2821,FX_Daily!$A$15:$A$2821,">="&$A15,FX_Daily!$A$15:$A$2821,"<="&EOMONTH($A15,0)),"") -> 1.4391579 | E15: =IFERROR(AVERAGEIFS(FX_Daily!E$15:E$2821,FX_Daily!$A$15:$A$2821,">="&$A15,FX_Daily!$A$15:$A$2821,"<="&EOMONTH($A15,0)),"") -> 1.0855053 | F15: =IFERROR(AVERAGEIFS(FX_Daily!F$15:F$2821,FX_Daily!$A$15:$A$2821,">="&$A15,FX_Daily!$A$15:$A$2821,"<="&EOMONTH($A15,0)),"") -> 6.5726 | G15: =IFERROR(AVERAGEIFS(FX_Daily!G$15:G$2821,FX_Daily!$A$15:$A$2821,">="&$A15,FX_Daily!$A$15:$A$2821,"<="&EOMONTH($A15,0)),"") -> 4.0555895 | H15: =IFERROR(AVERAGEIFS(FX_Daily!H$15:H$2821,FX_Daily!$A$15:$A$2821,">="&$A15,FX_Daily!$A$15:$A$2821,"<="&EOMONTH($A15,0)),"") -> 118.22579 | I15: =IFERROR(AVERAGEIFS(FX_Daily!I$15:I$2821,FX_Daily!$A$15:$A$2821,">="&$A15,FX_Daily!$A$15:$A$2821,"<="&EOMONTH($A15,0)),"") -> 1.085965 | ... P15: =IFERROR(AVERAGEIFS(FX_Daily!P$15:P$2821,FX_Daily!$A$15:$A$2821,">="&$A15,FX_Daily!$A$15:$A$2821,"<="&EOMONTH($A15,0)),"") -> 8.830905 | Q15: =COUNTIFS(FX_Daily!$A$15:$A$2821,">="&$A15,FX_Daily!$A$15:$A$2821,"<="&EOMONTH($A15,0),FX_Daily!C$15:C$2821,">0") -> 19 | R15: =IF(EOMONTH($A15,0)>FX_Daily!$C$11,"partial month","complete") -> complete
A16: 42401 | B16: =IFERROR(AVERAGEIFS(FX_Daily!B$15:B$2821,FX_Daily!$A$15:$A$2821,">="&$A16,FX_Daily!$A$15:$A$2821,"<="&EOMONTH($A16,0)),"") -> 1216.2285 | C16: =IFERROR(AVERAGEIFS(FX_Daily!C$15:C$2821,FX_Daily!$A$15:$A$2821,">="&$A16,FX_Daily!$A$15:$A$2821,"<="&EOMONTH($A16,0)),"") -> 8.612745 | D16: =IFERROR(AVERAGEIFS(FX_Daily!D$15:D$2821,FX_Daily!$A$15:$A$2821,">="&$A16,FX_Daily!$A$15:$A$2821,"<="&EOMONTH($A16,0)),"") -> 1.429005 | E16: =IFERROR(AVERAGEIFS(FX_Daily!E$15:E$2821,FX_Daily!$A$15:$A$2821,">="&$A16,FX_Daily!$A$15:$A$2821,"<="&EOMONTH($A16,0)),"") -> 1.10923 | F16: =IFERROR(AVERAGEIFS(FX_Daily!F$15:F$2821,FX_Daily!$A$15:$A$2821,">="&$A16,FX_Daily!$A$15:$A$2821,"<="&EOMONTH($A16,0)),"") -> 6.55005 | G16: =IFERROR(AVERAGEIFS(FX_Daily!G$15:G$2821,FX_Daily!$A$15:$A$2821,">="&$A16,FX_Daily!$A$15:$A$2821,"<="&EOMONTH($A16,0)),"") -> 3.964385 | H16: =IFERROR(AVERAGEIFS(FX_Daily!H$15:H$2821,FX_Daily!$A$15:$A$2821,">="&$A16,FX_Daily!$A$15:$A$2821,"<="&EOMONTH($A16,0)),"") -> 114.6155 | I16: =IFERROR(AVERAGEIFS(FX_Daily!I$15:I$2821,FX_Daily!$A$15:$A$2821,">="&$A16,FX_Daily!$A$15:$A$2821,"<="&EOMONTH($A16,0)),"") -> 1.1092952 | ... P16: =IFERROR(AVERAGEIFS(FX_Daily!P$15:P$2821,FX_Daily!$A$15:$A$2821,">="&$A16,FX_Daily!$A$15:$A$2821,"<="&EOMONTH($A16,0)),"") -> 8.6212 | Q16: =COUNTIFS(FX_Daily!$A$15:$A$2821,">="&$A16,FX_Daily!$A$15:$A$2821,"<="&EOMONTH($A16,0),FX_Daily!C$15:C$2821,">0") -> 20 | R16: =IF(EOMONTH($A16,0)>FX_Daily!$C$11,"partial month","complete") -> complete
A17: 42430 | B17: =IFERROR(AVERAGEIFS(FX_Daily!B$15:B$2821,FX_Daily!$A$15:$A$2821,">="&$A17,FX_Daily!$A$15:$A$2821,"<="&EOMONTH($A17,0)),"") -> 1181.573 | C17: =IFERROR(AVERAGEIFS(FX_Daily!C$15:C$2821,FX_Daily!$A$15:$A$2821,">="&$A17,FX_Daily!$A$15:$A$2821,"<="&EOMONTH($A17,0)),"") -> 8.4754087 | D17: =IFERROR(AVERAGEIFS(FX_Daily!D$15:D$2821,FX_Daily!$A$15:$A$2821,">="&$A17,FX_Daily!$A$15:$A$2821,"<="&EOMONTH($A17,0)),"") -> 1.4249304 | E17: =IFERROR(AVERAGEIFS(FX_Daily!E$15:E$2821,FX_Daily!$A$15:$A$2821,">="&$A17,FX_Daily!$A$15:$A$2821,"<="&EOMONTH($A17,0)),"") -> 1.1133522 | F17: =IFERROR(AVERAGEIFS(FX_Daily!F$15:F$2821,FX_Daily!$A$15:$A$2821,">="&$A17,FX_Daily!$A$15:$A$2821,"<="&EOMONTH($A17,0)),"") -> 6.5026913 | G17: =IFERROR(AVERAGEIFS(FX_Daily!G$15:G$2821,FX_Daily!$A$15:$A$2821,">="&$A17,FX_Daily!$A$15:$A$2821,"<="&EOMONTH($A17,0)),"") -> 3.6980217 | H17: =IFERROR(AVERAGEIFS(FX_Daily!H$15:H$2821,FX_Daily!$A$15:$A$2821,">="&$A17,FX_Daily!$A$15:$A$2821,"<="&EOMONTH($A17,0)),"") -> 112.93174 | I17: =IFERROR(AVERAGEIFS(FX_Daily!I$15:I$2821,FX_Daily!$A$15:$A$2821,">="&$A17,FX_Daily!$A$15:$A$2821,"<="&EOMONTH($A17,0)),"") -> 1.1099667 | ... P17: =IFERROR(AVERAGEIFS(FX_Daily!P$15:P$2821,FX_Daily!$A$15:$A$2821,">="&$A17,FX_Daily!$A$15:$A$2821,"<="&EOMONTH($A17,0)),"") -> 8.49374 | Q17: =COUNTIFS(FX_Daily!$A$15:$A$2821,">="&$A17,FX_Daily!$A$15:$A$2821,"<="&EOMONTH($A17,0),FX_Daily!C$15:C$2821,">0") -> 23 | R17: =IF(EOMONTH($A17,0)>FX_Daily!$C$11,"partial month","complete") -> complete
A18: 42461 | B18: =IFERROR(AVERAGEIFS(FX_Daily!B$15:B$2821,FX_Daily!$A$15:$A$2821,">="&$A18,FX_Daily!$A$15:$A$2821,"<="&EOMONTH($A18,0)),"") -> 1145.7967 | C18: =IFERROR(AVERAGEIFS(FX_Daily!C$15:C$2821,FX_Daily!$A$15:$A$2821,">="&$A18,FX_Daily!$A$15:$A$2821,"<="&EOMONTH($A18,0)),"") -> 8.2081762 | D18: =IFERROR(AVERAGEIFS(FX_Daily!D$15:D$2821,FX_Daily!$A$15:$A$2821,">="&$A18,FX_Daily!$A$15:$A$2821,"<="&EOMONTH($A18,0)),"") -> 1.4318619 | E18: =IFERROR(AVERAGEIFS(FX_Daily!E$15:E$2821,FX_Daily!$A$15:$A$2821,">="&$A18,FX_Daily!$A$15:$A$2821,"<="&EOMONTH($A18,0)),"") -> 1.1345667 | F18: =IFERROR(AVERAGEIFS(FX_Daily!F$15:F$2821,FX_Daily!$A$15:$A$2821,">="&$A18,FX_Daily!$A$15:$A$2821,"<="&EOMONTH($A18,0)),"") -> 6.4754333 | G18: =IFERROR(AVERAGEIFS(FX_Daily!G$15:G$2821,FX_Daily!$A$15:$A$2821,">="&$A18,FX_Daily!$A$15:$A$2821,"<="&EOMONTH($A18,0)),"") -> 3.5634476 | H18: =IFERROR(AVERAGEIFS(FX_Daily!H$15:H$2821,FX_Daily!$A$15:$A$2821,">="&$A18,FX_Daily!$A$15:$A$2821,"<="&EOMONTH($A18,0)),"") -> 109.5519 | I18: =IFERROR(AVERAGEIFS(FX_Daily!I$15:I$2821,FX_Daily!$A$15:$A$2821,">="&$A18,FX_Daily!$A$15:$A$2821,"<="&EOMONTH($A18,0)),"") -> 1.133919 | ... P18: =IFERROR(AVERAGEIFS(FX_Daily!P$15:P$2821,FX_Daily!$A$15:$A$2821,">="&$A18,FX_Daily!$A$15:$A$2821,"<="&EOMONTH($A18,0)),"") -> 8.2213905 | Q18: =COUNTIFS(FX_Daily!$A$15:$A$2821,">="&$A18,FX_Daily!$A$15:$A$2821,"<="&EOMONTH($A18,0),FX_Daily!C$15:C$2821,">0") -> 21 | R18: =IF(EOMONTH($A18,0)>FX_Daily!$C$11,"partial month","complete") -> complete
A19: 42491 | B19: =IFERROR(AVERAGEIFS(FX_Daily!B$15:B$2821,FX_Daily!$A$15:$A$2821,">="&$A19,FX_Daily!$A$15:$A$2821,"<="&EOMONTH($A19,0)),"") -> 1173.7905 | C19: =IFERROR(AVERAGEIFS(FX_Daily!C$15:C$2821,FX_Daily!$A$15:$A$2821,">="&$A19,FX_Daily!$A$15:$A$2821,"<="&EOMONTH($A19,0)),"") -> 8.226919 | D19: =IFERROR(AVERAGEIFS(FX_Daily!D$15:D$2821,FX_Daily!$A$15:$A$2821,">="&$A19,FX_Daily!$A$15:$A$2821,"<="&EOMONTH($A19,0)),"") -> 1.4524429 | E19: =IFERROR(AVERAGEIFS(FX_Daily!E$15:E$2821,FX_Daily!$A$15:$A$2821,">="&$A19,FX_Daily!$A$15:$A$2821,"<="&EOMONTH($A19,0)),"") -> 1.1312048 | F19: =IFERROR(AVERAGEIFS(FX_Daily!F$15:F$2821,FX_Daily!$A$15:$A$2821,">="&$A19,FX_Daily!$A$15:$A$2821,"<="&EOMONTH($A19,0)),"") -> 6.525881 | G19: =IFERROR(AVERAGEIFS(FX_Daily!G$15:G$2821,FX_Daily!$A$15:$A$2821,">="&$A19,FX_Daily!$A$15:$A$2821,"<="&EOMONTH($A19,0)),"") -> 3.5403048 | H19: =IFERROR(AVERAGEIFS(FX_Daily!H$15:H$2821,FX_Daily!$A$15:$A$2821,">="&$A19,FX_Daily!$A$15:$A$2821,"<="&EOMONTH($A19,0)),"") -> 108.8481 | I19: =IFERROR(AVERAGEIFS(FX_Daily!I$15:I$2821,FX_Daily!$A$15:$A$2821,">="&$A19,FX_Daily!$A$15:$A$2821,"<="&EOMONTH($A19,0)),"") -> 1.1311091 | ... P19: =IFERROR(AVERAGEIFS(FX_Daily!P$15:P$2821,FX_Daily!$A$15:$A$2821,">="&$A19,FX_Daily!$A$15:$A$2821,"<="&EOMONTH($A19,0)),"") -> 8.2375947 | Q19: =COUNTIFS(FX_Daily!$A$15:$A$2821,">="&$A19,FX_Daily!$A$15:$A$2821,"<="&EOMONTH($A19,0),FX_Daily!C$15:C$2821,">0") -> 21 | R19: =IF(EOMONTH($A19,0)>FX_Daily!$C$11,"partial month","complete") -> complete
A20: 42522 | B20: =IFERROR(AVERAGEIFS(FX_Daily!B$15:B$2821,FX_Daily!$A$15:$A$2821,">="&$A20,FX_Daily!$A$15:$A$2821,"<="&EOMONTH($A20,0)),"") -> 1165.2023 | C20: =IFERROR(AVERAGEIFS(FX_Daily!C$15:C$2821,FX_Daily!$A$15:$A$2821,">="&$A20,FX_Daily!$A$15:$A$2821,"<="&EOMONTH($A20,0)),"") -> 8.3064 | D20: =IFERROR(AVERAGEIFS(FX_Daily!D$15:D$2821,FX_Daily!$A$15:$A$2821,">="&$A20,FX_Daily!$A$15:$A$2821,"<="&EOMONTH($A20,0)),"") -> 1.4197364 | E20: =IFERROR(AVERAGEIFS(FX_Daily!E$15:E$2821,FX_Daily!$A$15:$A$2821,">="&$A20,FX_Daily!$A$15:$A$2821,"<="&EOMONTH($A20,0)),"") -> 1.1231773 | F20: =IFERROR(AVERAGEIFS(FX_Daily!F$15:F$2821,FX_Daily!$A$15:$A$2821,">="&$A20,FX_Daily!$A$15:$A$2821,"<="&EOMONTH($A20,0)),"") -> 6.5892227 | G20: =IFERROR(AVERAGEIFS(FX_Daily!G$15:G$2821,FX_Daily!$A$15:$A$2821,">="&$A20,FX_Daily!$A$15:$A$2821,"<="&EOMONTH($A20,0)),"") -> 3.4234455 | H20: =IFERROR(AVERAGEIFS(FX_Daily!H$15:H$2821,FX_Daily!$A$15:$A$2821,">="&$A20,FX_Daily!$A$15:$A$2821,"<="&EOMONTH($A20,0)),"") -> 105.35091 | I20: =IFERROR(AVERAGEIFS(FX_Daily!I$15:I$2821,FX_Daily!$A$15:$A$2821,">="&$A20,FX_Daily!$A$15:$A$2821,"<="&EOMONTH($A20,0)),"") -> 1.1228909 | ... P20: =IFERROR(AVERAGEIFS(FX_Daily!P$15:P$2821,FX_Daily!$A$15:$A$2821,">="&$A20,FX_Daily!$A$15:$A$2821,"<="&EOMONTH($A20,0)),"") -> 8.3080182 | Q20: =COUNTIFS(FX_Daily!$A$15:$A$2821,">="&$A20,FX_Daily!$A$15:$A$2821,"<="&EOMONTH($A20,0),FX_Daily!C$15:C$2821,">0") -> 22 | R20: =IF(EOMONTH($A20,0)>FX_Daily!$C$11,"partial month","complete") -> complete
A21: 42552 | B21: =IFERROR(AVERAGEIFS(FX_Daily!B$15:B$2821,FX_Daily!$A$15:$A$2821,">="&$A21,FX_Daily!$A$15:$A$2821,"<="&EOMONTH($A21,0)),"") -> 1140.865 | C21: =IFERROR(AVERAGEIFS(FX_Daily!C$15:C$2821,FX_Daily!$A$15:$A$2821,">="&$A21,FX_Daily!$A$15:$A$2821,"<="&EOMONTH($A21,0)),"") -> 8.479475 | D21: =IFERROR(AVERAGEIFS(FX_Daily!D$15:D$2821,FX_Daily!$A$15:$A$2821,">="&$A21,FX_Daily!$A$15:$A$2821,"<="&EOMONTH($A21,0)),"") -> 1.31341 | E21: =IFERROR(AVERAGEIFS(FX_Daily!E$15:E$2821,FX_Daily!$A$15:$A$2821,">="&$A21,FX_Daily!$A$15:$A$2821,"<="&EOMONTH($A21,0)),"") -> 1.105495 | F21: =IFERROR(AVERAGEIFS(FX_Daily!F$15:F$2821,FX_Daily!$A$15:$A$2821,">="&$A21,FX_Daily!$A$15:$A$2821,"<="&EOMONTH($A21,0)),"") -> 6.677105 | G21: =IFERROR(AVERAGEIFS(FX_Daily!G$15:G$2821,FX_Daily!$A$15:$A$2821,">="&$A21,FX_Daily!$A$15:$A$2821,"<="&EOMONTH($A21,0)),"") -> 3.27814 | H21: =IFERROR(AVERAGEIFS(FX_Daily!H$15:H$2821,FX_Daily!$A$15:$A$2821,">="&$A21,FX_Daily!$A$15:$A$2821,"<="&EOMONTH($A21,0)),"") -> 104.191 | I21: =IFERROR(AVERAGEIFS(FX_Daily!I$15:I$2821,FX_Daily!$A$15:$A$2821,">="&$A21,FX_Daily!$A$15:$A$2821,"<="&EOMONTH($A21,0)),"") -> 1.1068524 | ... P21: =IFERROR(AVERAGEIFS(FX_Daily!P$15:P$2821,FX_Daily!$A$15:$A$2821,">="&$A21,FX_Daily!$A$15:$A$2821,"<="&EOMONTH($A21,0)),"") -> 8.4648286 | Q21: =COUNTIFS(FX_Daily!$A$15:$A$2821,">="&$A21,FX_Daily!$A$15:$A$2821,"<="&EOMONTH($A21,0),FX_Daily!C$15:C$2821,">0") -> 20 | R21: =IF(EOMONTH($A21,0)>FX_Daily!$C$11,"partial month","complete") -> complete
A22: 42583 | B22: =IFERROR(AVERAGEIFS(FX_Daily!B$15:B$2821,FX_Daily!$A$15:$A$2821,">="&$A22,FX_Daily!$A$15:$A$2821,"<="&EOMONTH($A22,0)),"") -> 1110.0183 | C22: =IFERROR(AVERAGEIFS(FX_Daily!C$15:C$2821,FX_Daily!$A$15:$A$2821,">="&$A22,FX_Daily!$A$15:$A$2821,"<="&EOMONTH($A22,0)),"") -> 8.3009261 | D22: =IFERROR(AVERAGEIFS(FX_Daily!D$15:D$2821,FX_Daily!$A$15:$A$2821,">="&$A22,FX_Daily!$A$15:$A$2821,"<="&EOMONTH($A22,0)),"") -> 1.3101478 | E22: =IFERROR(AVERAGEIFS(FX_Daily!E$15:E$2821,FX_Daily!$A$15:$A$2821,">="&$A22,FX_Daily!$A$15:$A$2821,"<="&EOMONTH($A22,0)),"") -> 1.1206522 | F22: =IFERROR(AVERAGEIFS(FX_Daily!F$15:F$2821,FX_Daily!$A$15:$A$2821,">="&$A22,FX_Daily!$A$15:$A$2821,"<="&EOMONTH($A22,0)),"") -> 6.6465739 | G22: =IFERROR(AVERAGEIFS(FX_Daily!G$15:G$2821,FX_Daily!$A$15:$A$2821,">="&$A22,FX_Daily!$A$15:$A$2821,"<="&EOMONTH($A22,0)),"") -> 3.2085522 | H22: =IFERROR(AVERAGEIFS(FX_Daily!H$15:H$2821,FX_Daily!$A$15:$A$2821,">="&$A22,FX_Daily!$A$15:$A$2821,"<="&EOMONTH($A22,0)),"") -> 101.23826 | I22: =IFERROR(AVERAGEIFS(FX_Daily!I$15:I$2821,FX_Daily!$A$15:$A$2821,">="&$A22,FX_Daily!$A$15:$A$2821,"<="&EOMONTH($A22,0)),"") -> 1.1211739 | ... P22: =IFERROR(AVERAGEIFS(FX_Daily!P$15:P$2821,FX_Daily!$A$15:$A$2821,">="&$A22,FX_Daily!$A$15:$A$2821,"<="&EOMONTH($A22,0)),"") -> 8.298113 | Q22: =COUNTIFS(FX_Daily!$A$15:$A$2821,">="&$A22,FX_Daily!$A$15:$A$2821,"<="&EOMONTH($A22,0),FX_Daily!C$15:C$2821,">0") -> 23 | R22: =IF(EOMONTH($A22,0)>FX_Daily!$C$11,"partial month","complete") -> complete
A23: 42614 | B23: =IFERROR(AVERAGEIFS(FX_Daily!B$15:B$2821,FX_Daily!$A$15:$A$2821,">="&$A23,FX_Daily!$A$15:$A$2821,"<="&EOMONTH($A23,0)),"") -> 1108.3638 | C23: =IFERROR(AVERAGEIFS(FX_Daily!C$15:C$2821,FX_Daily!$A$15:$A$2821,">="&$A23,FX_Daily!$A$15:$A$2821,"<="&EOMONTH($A23,0)),"") -> 8.1957238 | D23: =IFERROR(AVERAGEIFS(FX_Daily!D$15:D$2821,FX_Daily!$A$15:$A$2821,">="&$A23,FX_Daily!$A$15:$A$2821,"<="&EOMONTH($A23,0)),"") -> 1.3140143 | E23: =IFERROR(AVERAGEIFS(FX_Daily!E$15:E$2821,FX_Daily!$A$15:$A$2821,">="&$A23,FX_Daily!$A$15:$A$2821,"<="&EOMONTH($A23,0)),"") -> 1.121781 | F23: =IFERROR(AVERAGEIFS(FX_Daily!F$15:F$2821,FX_Daily!$A$15:$A$2821,">="&$A23,FX_Daily!$A$15:$A$2821,"<="&EOMONTH($A23,0)),"") -> 6.670181 | G23: =IFERROR(AVERAGEIFS(FX_Daily!G$15:G$2821,FX_Daily!$A$15:$A$2821,">="&$A23,FX_Daily!$A$15:$A$2821,"<="&EOMONTH($A23,0)),"") -> 3.253181 | H23: =IFERROR(AVERAGEIFS(FX_Daily!H$15:H$2821,FX_Daily!$A$15:$A$2821,">="&$A23,FX_Daily!$A$15:$A$2821,"<="&EOMONTH($A23,0)),"") -> 101.78429 | I23: =IFERROR(AVERAGEIFS(FX_Daily!I$15:I$2821,FX_Daily!$A$15:$A$2821,">="&$A23,FX_Daily!$A$15:$A$2821,"<="&EOMONTH($A23,0)),"") -> 1.1212091 | ... P23: =IFERROR(AVERAGEIFS(FX_Daily!P$15:P$2821,FX_Daily!$A$15:$A$2821,">="&$A23,FX_Daily!$A$15:$A$2821,"<="&EOMONTH($A23,0)),"") -> 8.2029682 | Q23: =COUNTIFS(FX_Daily!$A$15:$A$2821,">="&$A23,FX_Daily!$A$15:$A$2821,"<="&EOMONTH($A23,0),FX_Daily!C$15:C$2821,">0") -> 21 | R23: =IF(EOMONTH($A23,0)>FX_Daily!$C$11,"partial month","complete") -> complete
A24: 42644 | B24: =IFERROR(AVERAGEIFS(FX_Daily!B$15:B$2821,FX_Daily!$A$15:$A$2821,">="&$A24,FX_Daily!$A$15:$A$2821,"<="&EOMONTH($A24,0)),"") -> 1128.166 | C24: =IFERROR(AVERAGEIFS(FX_Daily!C$15:C$2821,FX_Daily!$A$15:$A$2821,">="&$A24,FX_Daily!$A$15:$A$2821,"<="&EOMONTH($A24,0)),"") -> 8.17221 | D24: =IFERROR(AVERAGEIFS(FX_Daily!D$15:D$2821,FX_Daily!$A$15:$A$2821,">="&$A24,FX_Daily!$A$15:$A$2821,"<="&EOMONTH($A24,0)),"") -> 1.23299 | E24: =IFERROR(AVERAGEIFS(FX_Daily!E$15:E$2821,FX_Daily!$A$15:$A$2821,">="&$A24,FX_Daily!$A$15:$A$2821,"<="&EOMONTH($A24,0)),"") -> 1.10144 | F24: =IFERROR(AVERAGEIFS(FX_Daily!F$15:F$2821,FX_Daily!$A$15:$A$2821,">="&$A24,FX_Daily!$A$15:$A$2821,"<="&EOMONTH($A24,0)),"") -> 6.73031 | G24: =IFERROR(AVERAGEIFS(FX_Daily!G$15:G$2821,FX_Daily!$A$15:$A$2821,">="&$A24,FX_Daily!$A$15:$A$2821,"<="&EOMONTH($A24,0)),"") -> 3.185395 | H24: =IFERROR(AVERAGEIFS(FX_Daily!H$15:H$2821,FX_Daily!$A$15:$A$2821,">="&$A24,FX_Daily!$A$15:$A$2821,"<="&EOMONTH($A24,0)),"") -> 103.9075 | I24: =IFERROR(AVERAGEIFS(FX_Daily!I$15:I$2821,FX_Daily!$A$15:$A$2821,">="&$A24,FX_Daily!$A$15:$A$2821,"<="&EOMONTH($A24,0)),"") -> 1.1026048 | ... P24: =IFERROR(AVERAGEIFS(FX_Daily!P$15:P$2821,FX_Daily!$A$15:$A$2821,">="&$A24,FX_Daily!$A$15:$A$2821,"<="&EOMONTH($A24,0)),"") -> 8.1642 | Q24: =COUNTIFS(FX_Daily!$A$15:$A$2821,">="&$A24,FX_Daily!$A$15:$A$2821,"<="&EOMONTH($A24,0),FX_Daily!C$15:C$2821,">0") -> 20 | R24: =IF(EOMONTH($A24,0)>FX_Daily!$C$11,"partial month","complete") -> complete
A25: 42675 | B25: =IFERROR(AVERAGEIFS(FX_Daily!B$15:B$2821,FX_Daily!$A$15:$A$2821,">="&$A25,FX_Daily!$A$15:$A$2821,"<="&EOMONTH($A25,0)),"") -> 1162.708 | C25: =IFERROR(AVERAGEIFS(FX_Daily!C$15:C$2821,FX_Daily!$A$15:$A$2821,">="&$A25,FX_Daily!$A$15:$A$2821,"<="&EOMONTH($A25,0)),"") -> 8.41466 | D25: =IFERROR(AVERAGEIFS(FX_Daily!D$15:D$2821,FX_Daily!$A$15:$A$2821,">="&$A25,FX_Daily!$A$15:$A$2821,"<="&EOMONTH($A25,0)),"") -> 1.24319 | E25: =IFERROR(AVERAGEIFS(FX_Daily!E$15:E$2821,FX_Daily!$A$15:$A$2821,">="&$A25,FX_Daily!$A$15:$A$2821,"<="&EOMONTH($A25,0)),"") -> 1.07918 | F25: =IFERROR(AVERAGEIFS(FX_Daily!F$15:F$2821,FX_Daily!$A$15:$A$2821,">="&$A25,FX_Daily!$A$15:$A$2821,"<="&EOMONTH($A25,0)),"") -> 6.84016 | G25: =IFERROR(AVERAGEIFS(FX_Daily!G$15:G$2821,FX_Daily!$A$15:$A$2821,">="&$A25,FX_Daily!$A$15:$A$2821,"<="&EOMONTH($A25,0)),"") -> 3.33689 | H25: =IFERROR(AVERAGEIFS(FX_Daily!H$15:H$2821,FX_Daily!$A$15:$A$2821,">="&$A25,FX_Daily!$A$15:$A$2821,"<="&EOMONTH($A25,0)),"") -> 108.443 | I25: =IFERROR(AVERAGEIFS(FX_Daily!I$15:I$2821,FX_Daily!$A$15:$A$2821,">="&$A25,FX_Daily!$A$15:$A$2821,"<="&EOMONTH($A25,0)),"") -> 1.0798955 | ... P25: =IFERROR(AVERAGEIFS(FX_Daily!P$15:P$2821,FX_Daily!$A$15:$A$2821,">="&$A25,FX_Daily!$A$15:$A$2821,"<="&EOMONTH($A25,0)),"") -> 8.4116318 | Q25: =COUNTIFS(FX_Daily!$A$15:$A$2821,">="&$A25,FX_Daily!$A$15:$A$2821,"<="&EOMONTH($A25,0),FX_Daily!C$15:C$2821,">0") -> 20 | R25: =IF(EOMONTH($A25,0)>FX_Daily!$C$11,"partial month","complete") -> complete
A26: 42705 | B26: =IFERROR(AVERAGEIFS(FX_Daily!B$15:B$2821,FX_Daily!$A$15:$A$2821,">="&$A26,FX_Daily!$A$15:$A$2821,"<="&EOMONTH($A26,0)),"") -> 1183.07 | C26: =IFERROR(AVERAGEIFS(FX_Daily!C$15:C$2821,FX_Daily!$A$15:$A$2821,">="&$A26,FX_Daily!$A$15:$A$2821,"<="&EOMONTH($A26,0)),"") -> 8.5617429 | D26: =IFERROR(AVERAGEIFS(FX_Daily!D$15:D$2821,FX_Daily!$A$15:$A$2821,">="&$A26,FX_Daily!$A$15:$A$2821,"<="&EOMONTH($A26,0)),"") -> 1.2482524 | E26: =IFERROR(AVERAGEIFS(FX_Daily!E$15:E$2821,FX_Daily!$A$15:$A$2821,">="&$A26,FX_Daily!$A$15:$A$2821,"<="&EOMONTH($A26,0)),"") -> 1.0544619 | F26: =IFERROR(AVERAGEIFS(FX_Daily!F$15:F$2821,FX_Daily!$A$15:$A$2821,">="&$A26,FX_Daily!$A$15:$A$2821,"<="&EOMONTH($A26,0)),"") -> 6.9197524 | G26: =IFERROR(AVERAGEIFS(FX_Daily!G$15:G$2821,FX_Daily!$A$15:$A$2821,">="&$A26,FX_Daily!$A$15:$A$2821,"<="&EOMONTH($A26,0)),"") -> 3.3539667 | H26: =IFERROR(AVERAGEIFS(FX_Daily!H$15:H$2821,FX_Daily!$A$15:$A$2821,">="&$A26,FX_Daily!$A$15:$A$2821,"<="&EOMONTH($A26,0)),"") -> 115.9981 | I26: =IFERROR(AVERAGEIFS(FX_Daily!I$15:I$2821,FX_Daily!$A$15:$A$2821,">="&$A26,FX_Daily!$A$15:$A$2821,"<="&EOMONTH($A26,0)),"") -> 1.0542905 | ... P26: =IFERROR(AVERAGEIFS(FX_Daily!P$15:P$2821,FX_Daily!$A$15:$A$2821,">="&$A26,FX_Daily!$A$15:$A$2821,"<="&EOMONTH($A26,0)),"") -> 8.5619714 | Q26: =COUNTIFS(FX_Daily!$A$15:$A$2821,">="&$A26,FX_Daily!$A$15:$A$2821,"<="&EOMONTH($A26,0),FX_Daily!C$15:C$2821,">0") -> 21 | R26: =IF(EOMONTH($A26,0)>FX_Daily!$C$11,"partial month","complete") -> complete
... A144: 46296 | B144: =IFERROR(AVERAGEIFS(FX_Daily!B$15:B$2821,FX_Daily!$A$15:$A$2821,">="&$A144,FX_Daily!$A$15:$A$2821,"<="&EOMONTH($A144,0)),"") -> 1355.29 | C144: =IFERROR(AVERAGEIFS(FX_Daily!C$15:C$2821,FX_Daily!$A$15:$A$2821,">="&$A144,FX_Daily!$A$15:$A$2821,"<="&EOMONTH($A144,0)),"") -> 9.6386 | D144: =IFERROR(AVERAGEIFS(FX_Daily!D$15:D$2821,FX_Daily!$A$15:$A$2821,">="&$A144,FX_Daily!$A$15:$A$2821,"<="&EOMONTH($A144,0)),"") -> 1.3215 | E144: =IFERROR(AVERAGEIFS(FX_Daily!E$15:E$2821,FX_Daily!$A$15:$A$2821,">="&$A144,FX_Daily!$A$15:$A$2821,"<="&EOMONTH($A144,0)),"") -> 1.12455 | F144: =IFERROR(AVERAGEIFS(FX_Daily!F$15:F$2821,FX_Daily!$A$15:$A$2821,">="&$A144,FX_Daily!$A$15:$A$2821,"<="&EOMONTH($A144,0)),"") -> 6.7038 | G144: =IFERROR(AVERAGEIFS(FX_Daily!G$15:G$2821,FX_Daily!$A$15:$A$2821,">="&$A144,FX_Daily!$A$15:$A$2821,"<="&EOMONTH($A144,0)),"") -> 5.22755 | H144: =IFERROR(AVERAGEIFS(FX_Daily!H$15:H$2821,FX_Daily!$A$15:$A$2821,">="&$A144,FX_Daily!$A$15:$A$2821,"<="&EOMONTH($A144,0)),"") -> 157.72 | I144: =IFERROR(AVERAGEIFS(FX_Daily!I$15:I$2821,FX_Daily!$A$15:$A$2821,">="&$A144,FX_Daily!$A$15:$A$2821,"<="&EOMONTH($A144,0)),"") -> 1.1249 | ... P144: =IFERROR(AVERAGEIFS(FX_Daily!P$15:P$2821,FX_Daily!$A$15:$A$2821,">="&$A144,FX_Daily!$A$15:$A$2821,"<="&EOMONTH($A144,0)),"") -> 9.6102 | Q144: =COUNTIFS(FX_Daily!$A$15:$A$2821,">="&$A144,FX_Daily!$A$15:$A$2821,"<="&EOMONTH($A144,0),FX_Daily!C$15:C$2821,">0") -> 2 | R144: =IF(EOMONTH($A144,0)>FX_Daily!$C$11,"partial month","complete") -> partial month

Sheet Rates_Daily
A1: Rates_Daily — daily interest rates used to build monthly averages (raw)
A2: As-of date: 2026-10-07 | Retrieval date: 2026-10-07 | Blue font = raw value from source; black = formula. Weekdays + weekend days on which a source published (e.g. China make-up working days for Shibor). Blank = no observation by that source on that date (holiday) or series not yet published (SOFR from 2018-04, €STR from 2019-10).
A4: Provider | B4: FRED (St. Louis Fed) | C4: FRED (St. Louis Fed) | D4: FRED (St. Louis Fed) | E4: European Central Bank (ECB Data Portal) | F4: European Central Bank (ECB Data Portal) | G4: Bank of England (IADB) | H4: Bank of England (IADB) | I4: Bank of England (yield curve data) | J4: Bank of England (yield curve data) | K4: Bank of England (yield curve data) | L4: Bank of England (yield curve data) | M4: CFETS / National Interbank Funding Center (chinamoney.com.cn) | N4: CFETS / National Interbank Funding Center (chinamoney.com.cn) | O4: CFETS / National Interbank Funding Center (chinamoney.com.cn) | P4: CFETS / National Interbank Funding Center (chinamoney.com.cn) | Q4: Norges Bank | R4: Norges Bank | S4: Banco Central do Brasil (SGS)
A5: Series ID / table | B5: SOFR | C5: DFEDTARU | D5: DFEDTARL | E5: EST.B.EU000A2X2A25.WT | F5: FM.D.U2.EUR.4F.KR.DFR.LEV | G5: IUDBEDR | H5: IUDSOIA | I5: UK OIS spot curve, 1M maturity | J5: UK OIS spot curve, 3M maturity | K5: UK OIS spot curve, 6M maturity | L5: UK OIS spot curve, 12M maturity | M5: Shibor 1M | N5: Shibor 3M | O5: Shibor 6M | P5: Shibor 1Y | Q5: IR/B.KPRA.SD. | R5: SHORT_RATES/B.NOWA.ON.R | S5: SGS 432
A6: Description (quote direction) | B6: Secured Overnight Financing Rate (SOFR) | C6: Federal Funds Target Range - Upper Limit (DFEDTARU) | D6: Federal Funds Target Range - Lower Limit (DFEDTARL) | E6: Euro short-term rate | F6: Deposit facility - date of changes (raw data) - Level | G6: Official Bank Rate, daily | H6: Sterling Overnight Index Average, daily | I6: BoE estimated UK OIS (SONIA) spot rate, 1M maturity, continuously compounded per BoE methodology | J6: BoE estimated UK OIS (SONIA) spot rate, 3M maturity, continuously compounded per BoE methodology | K6: BoE estimated UK OIS (SONIA) spot rate, 6M maturity, continuously compounded per BoE methodology | L6: BoE estimated UK OIS (SONIA) spot rate, 12M maturity, continuously compounded per BoE methodology | M6: Shanghai Interbank Offered Rate, 1M tenor | N6: Shanghai Interbank Offered Rate, 3M tenor | O6: Shanghai Interbank Offered Rate, 6M tenor | P6: Shanghai Interbank Offered Rate, 1Y tenor | Q6: Key policy rate (sight deposit rate), daily | R6: Norwegian Overnight Weighted Average, daily | S6: Meta Selic definida pelo Copom (% a.a.)
A7: Unit | B7: Percent | C7: Percent | D7: Percent | E7: % p.a. | F7: % p.a. | G7: % p.a. | H7: % p.a. | I7: % p.a. | J7: % p.a. | K7: % p.a. | L7: % p.a. | M7: % p.a. | N7: % p.a. | O7: % p.a. | P7: % p.a. | Q7: % p.a. | R7: % p.a. | S7: % p.a.
A8: Frequency | B8: Daily | C8: Daily | D8: Daily | E8: Daily (TARGET days) | F8: Daily (calendar) | G8: Daily | H8: Daily | I8: Daily | J8: Daily | K8: Daily | L8: Daily | M8: Daily (China business days) | N8: Daily (China business days) | O8: Daily (China business days) | P8: Daily (China business days) | Q8: Daily | R8: Daily | S8: Daily
A9: URL | B9: https://fred.stlouisfed.org/series/SOFR | C9: https://fred.stlouisfed.org/series/DFEDTARU | D9: https://fred.stlouisfed.org/series/DFEDTARL | E9: https://data.ecb.europa.eu/data/datasets/EST/EST.B.EU000A2X2A25.WT | F9: https://data.ecb.europa.eu/data/datasets/FM/FM.D.U2.EUR.4F.KR.DFR.LEV | G9: https://www.bankofengland.co.uk/boeapps/database/?SeriesCodes=IUDBEDR | H9: https://www.bankofengland.co.uk/boeapps/database/?SeriesCodes=IUDSOIA | I9: https://www.bankofengland.co.uk/statistics/yield-curves (files: oisddata.zip, latest-yield-curve-data.zip; sheet "3. spot, short end") | J9: https://www.bankofengland.co.uk/statistics/yield-curves (files: oisddata.zip, latest-yield-curve-data.zip; sheet "3. spot, short end") | K9: https://www.bankofengland.co.uk/statistics/yield-curves (files: oisddata.zip, latest-yield-curve-data.zip; sheet "3. spot, short end") | L9: https://www.bankofengland.co.uk/statistics/yield-curves (files: oisddata.zip, latest-yield-curve-data.zip; sheet "3. spot, short end") | M9: https://www.chinamoney.com.cn/english/bmkshibor/ (API: /ags/ms/cm-u-bk-shibor/ShiborHis) | N9: https://www.chinamoney.com.cn/english/bmkshibor/ (API: /ags/ms/cm-u-bk-shibor/ShiborHis) | O9: https://www.chinamoney.com.cn/english/bmkshibor/ (API: /ags/ms/cm-u-bk-shibor/ShiborHis) | P9: https://www.chinamoney.com.cn/english/bmkshibor/ (API: /ags/ms/cm-u-bk-shibor/ShiborHis) | Q9: https://data.norges-bank.no/api/data/IR/B.KPRA.SD.?format=csv | R9: https://data.norges-bank.no/api/data/SHORT_RATES/B.NOWA.ON.R?format=csv | S9: https://api.bcb.gov.br/dados/serie/bcdata.sgs.432/dados?formato=json
A10: First observation (formula) | B10: =IFERROR(_xlfn.MINIFS($A$15:$A$2892,B$15:B$2892,">=-1E+99"),"N/A") -> 43193 | C10: =IFERROR(_xlfn.MINIFS($A$15:$A$2892,C$15:C$2892,">=-1E+99"),"N/A") -> 42370 | D10: =IFERROR(_xlfn.MINIFS($A$15:$A$2892,D$15:D$2892,">=-1E+99"),"N/A") -> 42370 | E10: =IFERROR(_xlfn.MINIFS($A$15:$A$2892,E$15:E$2892,">=-1E+99"),"N/A") -> 43739 | F10: =IFERROR(_xlfn.MINIFS($A$15:$A$2892,F$15:F$2892,">=-1E+99"),"N/A") -> 42370 | G10: =IFERROR(_xlfn.MINIFS($A$15:$A$2892,G$15:G$2892,">=-1E+99"),"N/A") -> 42373 | H10: =IFERROR(_xlfn.MINIFS($A$15:$A$2892,H$15:H$2892,">=-1E+99"),"N/A") -> 42373 | I10: =IFERROR(_xlfn.MINIFS($A$15:$A$2892,I$15:I$2892,">=-1E+99"),"N/A") -> 42373 | ... S10: =IFERROR(_xlfn.MINIFS($A$15:$A$2892,S$15:S$2892,">=-1E+99"),"N/A") -> 42370
A11: Last observation (formula) | B11: =IFERROR(_xlfn.MAXIFS($A$15:$A$2892,B$15:B$2892,">=-1E+99"),"N/A") -> 46300 | C11: =IFERROR(_xlfn.MAXIFS($A$15:$A$2892,C$15:C$2892,">=-1E+99"),"N/A") -> 46301 | D11: =IFERROR(_xlfn.MAXIFS($A$15:$A$2892,D$15:D$2892,">=-1E+99"),"N/A") -> 46301 | E11: =IFERROR(_xlfn.MAXIFS($A$15:$A$2892,E$15:E$2892,">=-1E+99"),"N/A") -> 46301 | F11: =IFERROR(_xlfn.MAXIFS($A$15:$A$2892,F$15:F$2892,">=-1E+99"),"N/A") -> 46302 | G11: =IFERROR(_xlfn.MAXIFS($A$15:$A$2892,G$15:G$2892,">=-1E+99"),"N/A") -> 46301 | H11: =IFERROR(_xlfn.MAXIFS($A$15:$A$2892,H$15:H$2892,">=-1E+99"),"N/A") -> 46300 | I11: =IFERROR(_xlfn.MAXIFS($A$15:$A$2892,I$15:I$2892,">=-1E+99"),"N/A") -> 46300 | ... S11: =IFERROR(_xlfn.MAXIFS($A$15:$A$2892,S$15:S$2892,">=-1E+99"),"N/A") -> 46302
A12: Last value (formula) | B12: =IFERROR(INDEX(B$15:B$2892,MATCH(B11,$A$15:$A$2892,0)),"N/A") -> 3.89 | C12: =IFERROR(INDEX(C$15:C$2892,MATCH(C11,$A$15:$A$2892,0)),"N/A") -> 4 | D12: =IFERROR(INDEX(D$15:D$2892,MATCH(D11,$A$15:$A$2892,0)),"N/A") -> 3.75 | E12: =IFERROR(INDEX(E$15:E$2892,MATCH(E11,$A$15:$A$2892,0)),"N/A") -> 2.439 | F12: =IFERROR(INDEX(F$15:F$2892,MATCH(F11,$A$15:$A$2892,0)),"N/A") -> 2.5 | G12: =IFERROR(INDEX(G$15:G$2892,MATCH(G11,$A$15:$A$2892,0)),"N/A") -> 3.75 | H12: =IFERROR(INDEX(H$15:H$2892,MATCH(H11,$A$15:$A$2892,0)),"N/A") -> 3.7323 | I12: =IFERROR(INDEX(I$15:I$2892,MATCH(I11,$A$15:$A$2892,0)),"N/A") -> 3.7501755 | ... S12: =IFERROR(INDEX(S$15:S$2892,MATCH(S11,$A$15:$A$2892,0)),"N/A") -> 13.75
A13: Observations (count, formula) | B13: =COUNT(B$15:B$2892) -> 2125 | C13: =COUNT(C$15:C$2892) -> 2877 | D13: =COUNT(D$15:D$2892) -> 2877 | E13: =COUNT(E$15:E$2892) -> 1797 | F13: =COUNT(F$15:F$2892) -> 2878 | G13: =COUNT(G$15:G$2892) -> 2719 | H13: =COUNT(H$15:H$2892) -> 2718 | I13: =COUNT(I$15:I$2892) -> 2718 | ... S13: =COUNT(S$15:S$2892) -> 2878
A14: Date | B14: USD SOFR (O/N) | C14: USD Fed funds target — upper | D14: USD Fed funds target — lower | E14: EUR €STR (O/N) | F14: EUR ECB deposit facility rate | G14: GBP Bank Rate | H14: GBP SONIA (O/N) | I14: GBP OIS spot 1M | J14: GBP OIS spot 3M | K14: GBP OIS spot 6M | L14: GBP OIS spot 12M | M14: CNY Shibor 1M | N14: CNY Shibor 3M | O14: CNY Shibor 6M | P14: CNY Shibor 1Y | Q14: NOK Norges Bank policy rate | R14: NOK NOWA (O/N) | S14: BRL Selic target (reference only)
A15: 42370 | C15: 0.5 | D15: 0.25 | F15: -0.3 | S15: 14.25
A16: 42373 | C16: 0.5 | D16: 0.25 | F16: -0.3 | G16: 0.5 | H16: 0.4648 | I16: 0.46297083 | J16: 0.46821791 | K16: 0.48505513 | L16: 0.5591523 | M16: 3.001 | N16: 3.086 | O16: 3.2 | P16: 3.35 | Q16: 0.75 | R16: 0.74 | S16: 14.25
A17: 42374 | C17: 0.5 | D17: 0.25 | F17: -0.3 | G17: 0.5 | H17: 0.4676 | I17: 0.46378969 | J17: 0.46842909 | K17: 0.48162969 | L17: 0.54254527 | M17: 3.001 | N17: 3.086 | O17: 3.2 | P17: 3.35 | Q17: 0.75 | R17: 0.74 | S17: 14.25
A18: 42375 | C18: 0.5 | D18: 0.25 | F18: -0.3 | G18: 0.5 | H18: 0.4717 | I18: 0.46261569 | J18: 0.46662731 | K18: 0.47529064 | L18: 0.52581588 | M18: 3 | N18: 3.082 | O18: 3.194 | P18: 3.347 | Q18: 0.75 | R18: 0.77 | S18: 14.25
A19: 42376 | C19: 0.5 | D19: 0.25 | F19: -0.3 | G19: 0.5 | H19: 0.4668 | I19: 0.46532679 | J19: 0.46746827 | K19: 0.47420844 | L19: 0.5149023 | M19: 2.9995 | N19: 3.0746 | O19: 3.191 | P19: 3.346 | Q19: 0.75 | R19: 0.74 | S19: 14.25
A20: 42377 | C20: 0.5 | D20: 0.25 | F20: -0.3 | G20: 0.5 | H20: 0.466 | I20: 0.46360642 | J20: 0.46618779 | K20: 0.47130259 | L20: 0.50314999 | M20: 2.999 | N20: 3.067 | O20: 3.1856 | P20: 3.345 | Q20: 0.75 | R20: 0.73 | S20: 14.25
A21: 42380 | C21: 0.5 | D21: 0.25 | F21: -0.3 | G21: 0.5 | H21: 0.4638 | I21: 0.46478961 | J21: 0.46771986 | K21: 0.47260253 | L21: 0.49939595 | M21: 2.998 | N21: 3.0585 | O21: 3.1783 | P21: 3.344 | Q21: 0.75 | R21: 0.74 | S21: 14.25
A22: 42381 | C22: 0.5 | D22: 0.25 | F22: -0.3 | G22: 0.5 | H22: 0.4636 | I22: 0.46506763 | J22: 0.46673148 | K22: 0.4700663 | L22: 0.49094341 | M22: 2.998 | N22: 3.053 | O22: 3.172 | P22: 3.34 | Q22: 0.75 | R22: 0.75 | S22: 14.25
A23: 42382 | C23: 0.5 | D23: 0.25 | F23: -0.3 | G23: 0.5 | H23: 0.4636 | I23: 0.46450797 | J23: 0.46662487 | K23: 0.47058718 | L23: 0.49620192 | M23: 2.967 | N23: 3.041 | O23: 3.163 | P23: 3.3345 | Q23: 0.75 | R23: 0.73 | S23: 14.25
A24: 42383 | C24: 0.5 | D24: 0.25 | F24: -0.3 | G24: 0.5 | H24: 0.4635 | I24: 0.46345547 | J24: 0.46639506 | K24: 0.47012039 | L24: 0.49295919 | M24: 2.931 | N24: 3.027 | O24: 3.152 | P24: 3.318 | Q24: 0.75 | R24: 0.75 | S24: 14.25
A25: 42384 | C25: 0.5 | D25: 0.25 | F25: -0.3 | G25: 0.5 | H25: 0.468 | I25: 0.46217732 | J25: 0.46176478 | K25: 0.4562003 | L25: 0.45012451 | M25: 2.899 | N25: 3.008 | O25: 3.136 | P25: 3.295 | Q25: 0.75 | R25: 0.74 | S25: 14.25
A26: 42387 | C26: 0.5 | D26: 0.25 | F26: -0.3 | G26: 0.5 | H26: 0.4644 | I26: 0.46296756 | J26: 0.46340294 | K26: 0.46282839 | L26: 0.47122439 | M26: 2.886 | N26: 2.985 | O26: 3.118 | P26: 3.2705 | Q26: 0.75 | R26: 0.74 | S26: 14.25
A27: 42388 | C27: 0.5 | D27: 0.25 | F27: -0.3 | G27: 0.5 | H27: 0.4632 | I27: 0.46269337 | J27: 0.46256877 | K27: 0.46134827 | L27: 0.46446294 | M27: 2.881 | N27: 2.976 | O27: 3.105 | P27: 3.25 | Q27: 0.75 | R27: 0.75 | S27: 14.25
... A40: 42405 | C40: 0.5 | D40: 0.25 | F40: -0.3 | G40: 0.5 | H40: 0.4672 | I40: 0.46279742 | J40: 0.45841186 | K40: 0.44491075 | L40: 0.41782474 | M40: 3.079 | N40: 3.06 | O40: 3.108 | P40: 3.25 | Q40: 0.75 | R40: 0.74 | S40: 14.25
A41: 42406 | C41: 0.5 | D41: 0.25 | F41: -0.3 | M41: 3.044 | N41: 3.058 | O41: 3.1075 | P41: 3.251 | S41: 14.25
A42: 42408 | C42: 0.5 | D42: 0.25 | F42: -0.3 | G42: 0.5 | H42: 0.4674 | I42: 0.46294309 | J42: 0.46056266 | K42: 0.44785882 | L42: 0.41315064 | Q42: 0.75 | R42: 0.74 | S42: 14.25
A43: 42409 | C43: 0.5 | D43: 0.25 | F43: -0.3 | G43: 0.5 | H43: 0.4671 | I43: 0.46300796 | J43: 0.45639964 | K43: 0.43358668 | L43: 0.38522543 | Q43: 0.75 | R43: 0.73 | S43: 14.25
A44: 42410 | C44: 0.5 | D44: 0.25 | F44: -0.3 | G44: 0.5 | H44: 0.4666 | I44: 0.46461959 | J44: 0.45898905 | K44: 0.44265696 | L44: 0.40548321 | Q44: 0.75 | R44: 0.74 | S44: 14.25
A45: 42411 | C45: 0.5 | D45: 0.25 | F45: -0.3 | G45: 0.5 | H45: 0.467 | I45: 0.4628949 | J45: 0.44623536 | K45: 0.40534292 | L45: 0.33799674 | Q45: 0.75 | R45: 0.73 | S45: 14.25
A46: 42412 | C46: 0.5 | D46: 0.25 | F46: -0.3 | G46: 0.5 | H46: 0.4678 | I46: 0.46331716 | J46: 0.45681004 | K46: 0.43545685 | L46: 0.388244 | Q46: 0.75 | R46: 0.72 | S46: 14.25
A47: 42414 | C47: 0.5 | D47: 0.25 | F47: -0.3 | M47: 2.999 | N47: 3.0495 | O47: 3.1065 | P47: 3.251 | S47: 14.25
A48: 42415 | C48: 0.5 | D48: 0.25 | F48: -0.3 | G48: 0.5 | H48: 0.4669 | I48: 0.46327258 | J48: 0.45873362 | K48: 0.43959401 | L48: 0.39962767 | M48: 2.979 | N48: 3.041 | O48: 3.104 | P48: 3.25 | Q48: 0.75 | R48: 0.76 | S48: 14.25
A49: 42416 | C49: 0.5 | D49: 0.25 | F49: -0.3 | G49: 0.5 | H49: 0.472 | I49: 0.46413893 | J49: 0.45976878 | K49: 0.44168907 | L49: 0.39879351 | M49: 2.957 | N49: 3.029 | O49: 3.1 | P49: 3.25 | Q49: 0.75 | R49: 0.74 | S49: 14.25
A50: 42417 | C50: 0.5 | D50: 0.25 | F50: -0.3 | G50: 0.5 | H50: 0.4627 | I50: 0.46458076 | J50: 0.460303 | K50: 0.44593837 | L50: 0.41790149 | M50: 2.938 | N50: 3.014 | O50: 3.1 | P50: 3.25 | Q50: 0.75 | R50: 0.74 | S50: 14.25
A51: 42418 | C51: 0.5 | D51: 0.25 | F51: -0.3 | G51: 0.5 | H51: 0.4618 | I51: 0.4641345 | J51: 0.46135074 | K51: 0.4477782 | L51: 0.42293499 | M51: 2.884 | N51: 3.004 | O51: 3.1 | P51: 3.25 | Q51: 0.75 | R51: 0.74 | S51: 14.25
A52: 42419 | C52: 0.5 | D52: 0.25 | F52: -0.3 | G52: 0.5 | H52: 0.4624 | I52: 0.46384827 | J52: 0.46056971 | K52: 0.44856794 | L52: 0.41930289 | M52: 2.839 | N52: 2.967 | O52: 3.074 | P52: 3.234 | Q52: 0.75 | R52: 0.75 | S52: 14.25
A53: 42422 | C53: 0.5 | D53: 0.25 | F53: -0.3 | G53: 0.5 | H53: 0.4668 | I53: 0.46308543 | J53: 0.45885747 | K53: 0.44656922 | L53: 0.4149524 | M53: 2.801 | N53: 2.947 | O53: 3.056 | P53: 3.219 | Q53: 0.75 | R53: 0.75 | S53: 14.25
A54: 42423 | C54: 0.5 | D54: 0.25 | F54: -0.3 | G54: 0.5 | H54: 0.4608 | I54: 0.4620583 | J54: 0.45915913 | K54: 0.44901087 | L54: 0.42545605 | M54: 2.775 | N54: 2.927 | O54: 3.0402 | P54: 3.21 | Q54: 0.75 | R54: 0.74 | S54: 14.25
A55: 42424 | C55: 0.5 | D55: 0.25 | F55: -0.3 | G55: 0.5 | H55: 0.4637 | I55: 0.46283302 | J55: 0.45907176 | K55: 0.44541358 | L55: 0.4052035 | M55: 2.759 | N55: 2.901 | O55: 3.0255 | P55: 3.204 | Q55: 0.75 | R55: 0.75 | S55: 14.25
A56: 42425 | C56: 0.5 | D56: 0.25 | F56: -0.3 | G56: 0.5 | H56: 0.4632 | I56: 0.46184573 | J56: 0.45916576 | K56: 0.44365735 | L56: 0.39231506 | M56: 2.757 | N56: 2.899 | O56: 3.0252 | P56: 3.197 | Q56: 0.75 | R56: 0.73 | S56: 14.25
A57: 42426 | C57: 0.5 | D57: 0.25 | F57: -0.3 | G57: 0.5 | H57: 0.4728 | I57: 0.46150556 | J57: 0.45927222 | K57: 0.44602202 | L57: 0.40513416 | M57: 2.785 | N57: 2.899 | O57: 3.03 | P57: 3.192 | Q57: 0.75 | R57: 0.74 | S57: 14.25
A58: 42429 | C58: 0.5 | D58: 0.25 | F58: -0.3 | G58: 0.5 | H58: 0.4545 | I58: 0.46259979 | J58: 0.45939678 | K58: 0.44622499 | L58: 0.39954318 | M58: 2.8 | N58: 2.899 | O58: 3.022 | P58: 3.186 | Q58: 0.75 | R58: 0.74 | S58: 14.25
A59: 42430 | C59: 0.5 | D59: 0.25 | F59: -0.3 | G59: 0.5 | H59: 0.4672 | I59: 0.46322635 | J59: 0.45871378 | K59: 0.44368191 | L59: 0.40421409 | M59: 2.795 | N59: 2.8835 | O59: 3.01 | P59: 3.1735 | Q59: 0.75 | R59: 0.73 | S59: 14.25
... A75: 42452 | C75: 0.5 | D75: 0.25 | F75: -0.4 | G75: 0.5 | H75: 0.4694 | I75: 0.46243517 | J75: 0.45666515 | K75: 0.44333913 | L75: 0.42869912 | M75: 2.7025 | N75: 2.798 | O75: 2.884 | P75: 3.0555 | Q75: 0.5 | R75: 0.51 | S75: 14.25
A76: 42453 | C76: 0.5 | D76: 0.25 | F76: -0.4 | G76: 0.5 | H76: 0.4679 | I76: 0.46158628 | J76: 0.45433169 | K76: 0.44099525 | L76: 0.42837571 | M76: 2.704 | N76: 2.799 | O76: 2.8792 | P76: 3.055 | S76: 14.25
A77: 42454 | C77: 0.5 | D77: 0.25 | F77: -0.4 | M77: 2.702 | N77: 2.797 | O77: 2.87 | P77: 3.055 | S77: 14.25
A78: 42457 | C78: 0.5 | D78: 0.25 | F78: -0.4 | M78: 2.706 | N78: 2.797 | O78: 2.868 | P78: 3.055 | S78: 14.25
A79: 42458 | C79: 0.5 | D79: 0.25 | F79: -0.4 | G79: 0.5 | H79: 0.4656 | I79: 0.46302849 | J79: 0.45413212 | K79: 0.43806251 | L79: 0.42335164 | M79: 2.729 | N79: 2.8002 | O79: 2.866 | P79: 3.054 | Q79: 0.5 | R79: 0.48 | S79: 14.25
A80: 42459 | C80: 0.5 | D80: 0.25 | F80: -0.4 | G80: 0.5 | H80: 0.4638 | I80: 0.46500404 | J80: 0.45556356 | K80: 0.43749399 | L80: 0.4249023 | M80: 2.7665 | N80: 2.8115 | O80: 2.869 | P80: 3.052 | Q80: 0.5 | R80: 0.5 | S80: 14.25
A81: 42460 | C81: 0.5 | D81: 0.25 | F81: -0.4 | G81: 0.5 | H81: 0.4128 | I81: 0.46372984 | J81: 0.45594662 | K81: 0.4369831 | L81: 0.41889462 | M81: 2.807 | N81: 2.8248 | O81: 2.87 | P81: 3.051 | Q81: 0.5 | R81: 0.69 | S81: 14.25
A82: 42461 | C82: 0.5 | D82: 0.25 | F82: -0.4 | G82: 0.5 | H82: 0.4651 | I82: 0.463489 | J82: 0.45604984 | K82: 0.43805717 | L82: 0.41788076 | M82: 2.816 | N82: 2.8385 | O82: 2.872 | P82: 3.051 | Q82: 0.5 | R82: 0.47 | S82: 14.25
A83: 42464 | C83: 0.5 | D83: 0.25 | F83: -0.4 | G83: 0.5 | H83: 0.4632 | I83: 0.46295088 | J83: 0.45535959 | K83: 0.43645851 | L83: 0.41856449 | Q83: 0.5 | R83: 0.48 | S83: 14.25
A84: 42465 | C84: 0.5 | D84: 0.25 | F84: -0.4 | G84: 0.5 | H84: 0.4669 | I84: 0.46275323 | J84: 0.45349083 | K84: 0.43157659 | L84: 0.3980089 | M84: 2.8212 | N84: 2.846 | O84: 2.878 | P84: 3.05 | Q84: 0.5 | R84: 0.51 | S84: 14.25
A85: 42466 | C85: 0.5 | D85: 0.25 | F85: -0.4 | G85: 0.5 | H85: 0.4666 | I85: 0.46324666 | J85: 0.45362397 | K85: 0.43105786 | L85: 0.39735982 | M85: 2.8068 | N85: 2.845 | O85: 2.8805 | P85: 3.049 | Q85: 0.5 | R85: 0.48 | S85: 14.25
A86: 42467 | C86: 0.5 | D86: 0.25 | F86: -0.4 | G86: 0.5 | H86: 0.4643 | I86: 0.46292928 | J86: 0.45682359 | K86: 0.43435411 | L86: 0.39589028 | M86: 2.8 | N86: 2.847 | O86: 2.8825 | P86: 3.048 | Q86: 0.5 | R86: 0.49 | S86: 14.25
A87: 42468 | C87: 0.5 | D87: 0.25 | F87: -0.4 | G87: 0.5 | H87: 0.466 | I87: 0.46405527 | J87: 0.45513378 | K87: 0.42850961 | L87: 0.38981443 | M87: 2.798 | N87: 2.8455 | O87: 2.8828 | P87: 3.047 | Q87: 0.5 | R87: 0.48 | S87: 14.25
A88: 42471 | C88: 0.5 | D88: 0.25 | F88: -0.4 | G88: 0.5 | H88: 0.4665 | I88: 0.46328069 | J88: 0.45369914 | K88: 0.42789573 | L88: 0.39458909 | M88: 2.797 | N88: 2.8485 | O88: 2.885 | P88: 3.042 | Q88: 0.5 | R88: 0.52 | S88: 14.25
A89: 42472 | C89: 0.5 | D89: 0.25 | F89: -0.4 | G89: 0.5 | H89: 0.4722 | I89: 0.46352858 | J89: 0.45431259 | K89: 0.43085097 | L89: 0.40713771 | M89: 2.797 | N89: 2.847 | O89: 2.8875 | P89: 3.043 | Q89: 0.5 | R89: 0.48 | S89: 14.25
A90: 42473 | C90: 0.5 | D90: 0.25 | F90: -0.4 | G90: 0.5 | H90: 0.4696 | I90: 0.46487944 | J90: 0.4573262 | K90: 0.4338653 | L90: 0.41090949 | M90: 2.799 | N90: 2.8485 | O90: 2.8905 | P90: 3.042 | Q90: 0.5 | R90: 0.48 | S90: 14.25
A91: 42474 | C91: 0.5 | D91: 0.25 | F91: -0.4 | G91: 0.5 | H91: 0.4717 | I91: 0.46499948 | J91: 0.4569507 | K91: 0.43614165 | L91: 0.41346665 | M91: 2.799 | N91: 2.8487 | O91: 2.8928 | P91: 3.042 | Q91: 0.5 | R91: 0.5 | S91: 14.25
A92: 42475 | C92: 0.5 | D92: 0.25 | F92: -0.4 | G92: 0.5 | H92: 0.4719 | I92: 0.46494076 | J92: 0.45779745 | K92: 0.43609016 | L92: 0.41130949 | M92: 2.799 | N92: 2.848 | O92: 2.894 | P92: 3.044 | Q92: 0.5 | R92: 0.5 | S92: 14.25
A93: 42478 | C93: 0.5 | D93: 0.25 | F93: -0.4 | G93: 0.5 | H93: 0.4699 | I93: 0.46495165 | J93: 0.45675579 | K93: 0.43367653 | L93: 0.41335763 | M93: 2.799 | N93: 2.848 | O93: 2.893 | P93: 3.042 | Q93: 0.5 | R93: 0.49 | S93: 14.25
A94: 42479 | C94: 0.5 | D94: 0.25 | F94: -0.4 | G94: 0.5 | H94: 0.4706 | I94: 0.46495261 | J94: 0.45894617 | K94: 0.44042646 | L94: 0.42946025 | M94: 2.8 | N94: 2.85 | O94: 2.894 | P94: 3.043 | Q94: 0.5 | R94: 0.51 | S94: 14.25
A95: 42480 | C95: 0.5 | D95: 0.25 | F95: -0.4 | G95: 0.5 | H95: 0.4646 | I95: 0.46515896 | J95: 0.46024304 | K95: 0.44407788 | L95: 0.43724295 | M95: 2.803 | N95: 2.851 | O95: 2.894 | P95: 3.042 | Q95: 0.5 | R95: 0.51 | S95: 14.25
... A102: 42489 | C102: 0.5 | D102: 0.25 | F102: -0.4 | G102: 0.5 | H102: 0.4584 | I102: 0.46312631 | J102: 0.45649193 | K102: 0.44025189 | L102: 0.44596431 | M102: 2.853 | N102: 2.908 | O102: 2.927 | P102: 3.042 | Q102: 0.5 | R102: 0.48 | S102: 14.25
A103: 42492 | C103: 0.5 | D103: 0.25 | F103: -0.4 | Q103: 0.5 | R103: 0.49 | S103: 14.25
A104: 42493 | C104: 0.5 | D104: 0.25 | F104: -0.4 | G104: 0.5 | H104: 0.4609 | I104: 0.46264201 | J104: 0.45389608 | K104: 0.43570962 | L104: 0.42970224 | M104: 2.8489 | N104: 2.9044 | O104: 2.93 | P104: 3.0422 | Q104: 0.5 | R104: 0.48 | S104: 14.25
A105: 42494 | C105: 0.5 | D105: 0.25 | F105: -0.4 | G105: 0.5 | H105: 0.4707 | I105: 0.46221848 | J105: 0.448815 | K105: 0.42481734 | L105: 0.41826726 | M105: 2.845 | N105: 2.899 | O105: 2.933 | P105: 3.042 | Q105: 0.5 | R105: 0.47 | S105: 14.25
A106: 42495 | C106: 0.5 | D106: 0.25 | F106: -0.4 | G106: 0.5 | H106: 0.4619 | I106: 0.46243838 | J106: 0.44730989 | K106: 0.42059517 | L106: 0.40287938 | M106: 2.846 | N106: 2.896 | O106: 2.9345 | P106: 3.042 | S106: 14.25
A107: 42496 | C107: 0.5 | D107: 0.25 | F107: -0.4 | G107: 0.5 | H107: 0.4631 | I107: 0.4606805 | J107: 0.44502033 | K107: 0.41513644 | L107: 0.38810016 | M107: 2.842 | N107: 2.894 | O107: 2.9335 | P107: 3.042 | Q107: 0.5 | R107: 0.49 | S107: 14.25
A108: 42499 | C108: 0.5 | D108: 0.25 | F108: -0.4 | G108: 0.5 | H108: 0.463 | I108: 0.46313651 | J108: 0.44314461 | K108: 0.40628699 | L108: 0.37541119 | M108: 2.841 | N108: 2.892 | O108: 2.9325 | P108: 3.042 | Q108: 0.5 | R108: 0.5 | S108: 14.25
A109: 42500 | C109: 0.5 | D109: 0.25 | F109: -0.4 | G109: 0.5 | H109: 0.4606 | I109: 0.46282784 | J109: 0.44306204 | K109: 0.40632029 | L109: 0.37697299 | M109: 2.841 | N109: 2.892 | O109: 2.9345 | P109: 3.042 | Q109: 0.5 | R109: 0.49 | S109: 14.25
A110: 42501 | C110: 0.5 | D110: 0.25 | F110: -0.4 | G110: 0.5 | H110: 0.4609 | I110: 0.46271165 | J110: 0.4417047 | K110: 0.4051628 | L110: 0.37884449 | M110: 2.838 | N110: 2.894 | O110: 2.9385 | P110: 3.043 | Q110: 0.5 | R110: 0.49 | S110: 14.25
A111: 42502 | C111: 0.5 | D111: 0.25 | F111: -0.4 | G111: 0.5 | H111: 0.461 | I111: 0.46340556 | J111: 0.44413849 | K111: 0.4147393 | L111: 0.39947869 | M111: 2.835 | N111: 2.8955 | O111: 2.9418 | P111: 3.044 | Q111: 0.5 | R111: 0.49 | S111: 14.25
A112: 42503 | C112: 0.5 | D112: 0.25 | F112: -0.4 | G112: 0.5 | H112: 0.4635 | I112: 0.46416927 | J112: 0.44541991 | K112: 0.41518465 | L112: 0.39677226 | M112: 2.834 | N112: 2.9035 | O112: 2.9452 | P112: 3.045 | Q112: 0.5 | R112: 0.49 | S112: 14.25
A113: 42506 | C113: 0.5 | D113: 0.25 | F113: -0.4 | G113: 0.5 | H113: 0.4633 | I113: 0.46438758 | J113: 0.44222979 | K113: 0.41086905 | L113: 0.39367742 | M113: 2.834 | N113: 2.9075 | O113: 2.9516 | P113: 3.047 | S113: 14.25
A114: 42507 | C114: 0.5 | D114: 0.25 | F114: -0.4 | G114: 0.5 | H114: 0.4629 | I114: 0.46421406 | J114: 0.44441986 | K114: 0.41766933 | L114: 0.40543704 | M114: 2.835 | N114: 2.9158 | O114: 2.9552 | P114: 3.049 | S114: 14.25
A115: 42508 | C115: 0.5 | D115: 0.25 | F115: -0.4 | G115: 0.5 | H115: 0.4648 | I115: 0.46536568 | J115: 0.44591889 | K115: 0.42288584 | L115: 0.41868512 | M115: 2.839 | N115: 2.9227 | O115: 2.9636 | P115: 3.05 | Q115: 0.5 | R115: 0.55 | S115: 14.25
A116: 42509 | C116: 0.5 | D116: 0.25 | F116: -0.4 | G116: 0.5 | H116: 0.4649 | I116: 0.4627931 | J116: 0.44623572 | K116: 0.42646168 | L116: 0.42547409 | M116: 2.837 | N116: 2.9273 | O116: 2.9655 | P116: 3.05 | Q116: 0.5 | R116: 0.53 | S116: 14.25
A117: 42510 | C117: 0.5 | D117: 0.25 | F117: -0.4 | G117: 0.5 | H117: 0.4642 | I117: 0.46338715 | J117: 0.44642211 | K117: 0.42557962 | L117: 0.42459591 | M117: 2.839 | N117: 2.9288 | O117: 2.9716 | P117: 3.05 | Q117: 0.5 | R117: 0.5 | S117: 14.25
A118: 42513 | C118: 0.5 | D118: 0.25 | F118: -0.4 | G118: 0.5 | H118: 0.4623 | I118: 0.46251361 | J118: 0.44518554 | K118: 0.42522211 | L118: 0.42325711 | M118: 2.84 | N118: 2.93 | O118: 2.9762 | P118: 3.05 | Q118: 0.5 | R118: 0.48 | S118: 14.25
A119: 42514 | C119: 0.5 | D119: 0.25 | F119: -0.4 | G119: 0.5 | H119: 0.4669 | I119: 0.46254262 | J119: 0.44881586 | K119: 0.43447864 | L119: 0.44518787 | M119: 2.842 | N119: 2.933 | O119: 2.9807 | P119: 3.05 | Q119: 0.5 | R119: 0.47 | S119: 14.25
A120: 42515 | C120: 0.5 | D120: 0.25 | F120: -0.4 | G120: 0.5 | H120: 0.4651 | I120: 0.46494185 | J120: 0.45186066 | K120: 0.43680532 | L120: 0.44574151 | M120: 2.842 | N120: 2.9385 | O120: 2.982 | P120: 3.05 | Q120: 0.5 | R120: 0.47 | S120: 14.25
A121: 42516 | C121: 0.5 | D121: 0.25 | F121: -0.4 | G121: 0.5 | H121: 0.4653 | I121: 0.46272463 | J121: 0.45014527 | K121: 0.43525609 | L121: 0.44082957 | M121: 2.845 | N121: 2.941 | O121: 2.981 | P121: 3.05 | Q121: 0.5 | R121: 0.49 | S121: 14.25
A122: 42517 | C122: 0.5 | D122: 0.25 | F122: -0.4 | G122: 0.5 | H122: 0.4666 | I122: 0.46212118 | J122: 0.44918075 | K122: 0.43350013 | L122: 0.43799443 | M122: 2.846 | N122: 2.942 | O122: 2.9822 | P122: 3.05 | Q122: 0.5 | R122: 0.48 | S122: 14.25
A123: 42520 | C123: 0.5 | D123: 0.25 | F123: -0.4 | M123: 2.846 | N123: 2.9455 | O123: 2.9822 | P123: 3.05 | Q123: 0.5 | R123: 0.49 | S123: 14.25
A124: 42521 | C124: 0.5 | D124: 0.25 | F124: -0.4 | G124: 0.5 | H124: 0.4542 | I124: 0.46137033 | J124: 0.44390527 | K124: 0.42354687 | L124: 0.42598092 | M124: 2.846 | N124: 2.946 | O124: 2.9822 | P124: 3.05 | Q124: 0.5 | R124: 0.48 | S124: 14.25
A125: 42522 | C125: 0.5 | D125: 0.25 | F125: -0.4 | G125: 0.5 | H125: 0.4633 | I125: 0.45978739 | J125: 0.43712814 | K125: 0.41123227 | L125: 0.40478009 | M125: 2.842 | N125: 2.946 | O125: 2.9823 | P125: 3.05 | Q125: 0.5 | R125: 0.49 | S125: 14.25
A126: 42523 | C126: 0.5 | D126: 0.25 | F126: -0.4 | G126: 0.5 | H126: 0.461 | I126: 0.46053117 | J126: 0.43767081 | K126: 0.41094469 | L126: 0.39800562 | M126: 2.838 | N126: 2.946 | O126: 2.9823 | P126: 3.05 | Q126: 0.5 | R126: 0.5 | S126: 14.25
A127: 42524 | C127: 0.5 | D127: 0.25 | F127: -0.4 | G127: 0.5 | H127: 0.4651 | I127: 0.45987721 | J127: 0.43694274 | K127: 0.40751868 | L127: 0.37697671 | M127: 2.835 | N127: 2.947 | O127: 2.9833 | P127: 3.05 | Q127: 0.5 | R127: 0.48 | S127: 14.25
A128: 42527 | C128: 0.5 | D128: 0.25 | F128: -0.4 | G128: 0.5 | H128: 0.4624 | I128: 0.45693853 | J128: 0.42696862 | K128: 0.39538037 | L128: 0.36539537 | M128: 2.839 | N128: 2.946 | O128: 2.9833 | P128: 3.05 | Q128: 0.5 | R128: 0.5 | S128: 14.25
A129: 42528 | C129: 0.5 | D129: 0.25 | F129: -0.4 | G129: 0.5 | H129: 0.4632 | I129: 0.45556701 | J129: 0.42096675 | K129: 0.39061797 | L129: 0.36663241 | M129: 2.838 | N129: 2.946 | O129: 2.9834 | P129: 3.05 | Q129: 0.5 | R129: 0.49 | S129: 14.25
A130: 42529 | C130: 0.5 | D130: 0.25 | F130: -0.4 | G130: 0.5 | H130: 0.4607 | I130: 0.45528408 | J130: 0.42289887 | K130: 0.39130468 | L130: 0.36629423 | M130: 2.838 | N130: 2.946 | O130: 2.982 | P130: 3.05 | Q130: 0.5 | R130: 0.47 | S130: 14.25
A131: 42530 | C131: 0.5 | D131: 0.25 | F131: -0.4 | G131: 0.5 | H131: 0.4612 | I131: 0.45690358 | J131: 0.42389871 | K131: 0.39508157 | L131: 0.37616245 | Q131: 0.5 | R131: 0.49 | S131: 14.25
A132: 42531 | C132: 0.5 | D132: 0.25 | F132: -0.4 | G132: 0.5 | H132: 0.4607 | I132: 0.45588111 | J132: 0.42888022 | K132: 0.40573203 | L132: 0.39053762 | Q132: 0.5 | R132: 0.49 | S132: 14.25
A133: 42533 | C133: 0.5 | D133: 0.25 | F133: -0.4 | M133: 2.842 | N133: 2.946 | O133: 2.982 | P133: 3.05 | S133: 14.25
A134: 42534 | C134: 0.5 | D134: 0.25 | F134: -0.4 | G134: 0.5 | H134: 0.4578 | I134: 0.45491644 | J134: 0.42414732 | K134: 0.39616583 | L134: 0.3718698 | M134: 2.844 | N134: 2.9476 | O134: 2.9833 | P134: 3.05 | Q134: 0.5 | R134: 0.49 | S134: 14.25
...

Sheet Rates_Monthly
A1: Rates_Monthly — short-term interest rates by currency, monthly (% p.a.)
A2: As-of date: 2026-10-07 | Retrieval date: 2026-10-07 | Blue font = raw value from source; black = formula. Blue = monthly value published by source; black = formula on Rates_Daily. Blank = series not published for that month (see Data_Quality_Log).
A4: Provider | B4: FRED (St. Louis Fed) | C4: FRED (St. Louis Fed) | D4: FRED (St. Louis Fed) | E4: FRED (St. Louis Fed) | F4: FRED (St. Louis Fed) | G4: FRED (St. Louis Fed) | H4: FRED (St. Louis Fed) | I4: FRED (St. Louis Fed) | J4: FRED; original source OECD Main Economic Indicators | K4: European Central Bank (ECB Data Portal) | L4: European Central Bank (ECB Data Portal) | M4: European Central Bank (ECB Data Portal); administrator EMMI | N4: European Central Bank (ECB Data Portal); administrator EMMI | O4: European Central Bank (ECB Data Portal); administrator EMMI | P4: European Central Bank (ECB Data Portal); administrator EMMI | Q4: FRED; original source OECD Main Economic Indicators | R4: Bank of England (IADB) | S4: Bank of England (IADB) | T4: Bank of England (yield curve data) | U4: Bank of England (yield curve data) | V4: Bank of England (yield curve data) | W4: Bank of England (yield curve data) | X4: FRED; original source OECD Main Economic Indicators | Y4: Norges Bank | Z4: Norges Bank | AA4: Norges Bank | AB4: Norges Bank | AC4: Norges Bank | AD4: FRED; original source OECD Main Economic Indicators | AE4: Bank of Korea (ECOS) | AF4: Bank of Korea (ECOS) | AG4: Bank of Korea (ECOS) | AH4: Bank of Korea (ECOS) | AI4: Bank of Korea (ECOS) | AJ4: Bank of Korea (ECOS) | AK4: Bank of Korea (ECOS) | AL4: Bank of Korea (ECOS) | AM4: Bank of Korea (ECOS) | AN4: FRED; original source OECD Main Economic Indicators | AO4: CFETS / National Interbank Funding Center (chinamoney.com.cn) | AP4: CFETS / National Interbank Funding Center (chinamoney.com.cn) | AQ4: CFETS / National Interbank Funding Center (chinamoney.com.cn) | AR4: CFETS / National Interbank Funding Center (chinamoney.com.cn) | AS4: PBoC / NIFC via CFETS (chinamoney.com.cn) | AT4: PBoC / NIFC via CFETS (chinamoney.com.cn) | AU4: FRED; original source OECD Main Economic Indicators | AV4: Banco Central do Brasil (SGS) | AW4: FRED; original source OECD Main Economic Indicators | AX4: FRED; original source OECD Main Economic Indicators | AY4: FRED; original source OECD Main Economic Indicators | AZ4: Formula
A5: Series ID / table | B5: FEDFUNDS | C5: DFEDTARU → Month-end value (last daily obs <= month end; formula on Rates_Daily) | D5: DFEDTARL → Month-end value (last daily obs <= month end; formula on Rates_Daily) | E5: SOFR → Monthly average of daily obs (formula on Rates_Daily) | F5: GS1M | G5: GS3M | H5: GS6M | I5: GS1 | J5: IR3TIB01USM156N | K5: FM.D.U2.EUR.4F.KR.DFR.LEV → Month-end value (last daily obs <= month end; formula on Rates_Daily) | L5: EST.B.EU000A2X2A25.WT → Monthly average of daily obs (formula on Rates_Daily) | M5: FM.M.U2.EUR.RT.MM.EURIBOR1MD_.HSTA | N5: FM.M.U2.EUR.RT.MM.EURIBOR3MD_.HSTA | O5: FM.M.U2.EUR.RT.MM.EURIBOR6MD_.HSTA | P5: FM.M.U2.EUR.RT.MM.EURIBOR1YD_.HSTA | Q5: IR3TIB01EZM156N | R5: IUMABEDR | S5: IUMASOIA | T5: UK OIS spot curve, 1M maturity → Monthly average of daily obs (formula on Rates_Daily) | U5: UK OIS spot curve, 3M maturity → Monthly average of daily obs (formula on Rates_Daily) | V5: UK OIS spot curve, 6M maturity → Monthly average of daily obs (formula on Rates_Daily) | W5: UK OIS spot curve, 12M maturity → Monthly average of daily obs (formula on Rates_Daily) | X5: IR3TIB01GBM156N | Y5: IR/M.KPRA.SD. | Z5: SHORT_RATES/M.NOWA.ON.R | AA5: GOVT_GENERIC_RATES/M.3M.TBIL. | AB5: GOVT_GENERIC_RATES/M.6M.TBIL. | AC5: GOVT_GENERIC_RATES/M.12M.TBIL. | AD5: IR3TIB01NOM156N | AE5: 722Y001 / item 0101000 | AF5: 721Y001 / item 1010000 | AG5: 721Y001 / item 2010000 | AH5: 721Y001 / item 1025000 | AI5: 721Y001 / item 1026000 | AJ5: 721Y001 / item 1027000 | AK5: 721Y001 / item 6010300 | AL5: 721Y001 / item 6010100 | AM5: 721Y001 / item 5030000 | AN5: IR3TIB01KRM156N | AO5: Shibor 1M → Monthly average of daily obs (formula on Rates_Daily) | AP5: Shibor 3M → Monthly average of daily obs (formula on Rates_Daily) | AQ5: Shibor 6M → Monthly average of daily obs (formula on Rates_Daily) | AR5: Shibor 1Y → Monthly average of daily obs (formula on Rates_Daily) | AS5: LPR 1Y | AT5: LPR 5Y | AU5: IR3TIB01CNM156N | AV5: SGS 4189 | AW5: IRSTCI01BRM156N | AX5: IR3TIB01JPM156N | AY5: IRSTCI01JPM156N
A6: Description (quote direction) | B6: Federal Funds Effective Rate (FEDFUNDS) | C6: Federal Funds Target Range - Upper Limit (DFEDTARU) | D6: Federal Funds Target Range - Lower Limit (DFEDTARL) | E6: Secured Overnight Financing Rate (SOFR) | F6: Market Yield on U.S. Treasury Securities at 1-Month Constant Maturity, Quoted on an Investment Basis (GS1M) | G6: Market Yield on U.S. Treasury Securities at 3-Month Constant Maturity, Quoted on an Investment Basis (GS3M) | H6: Market Yield on U.S. Treasury Securities at 6-Month Constant Maturity, Quoted on an Investment Basis (GS6M) | I6: Market Yield on U.S. Treasury Securities at 1-Year Constant Maturity, Quoted on an Investment Basis (GS1) | J6: Interest Rates: 3-Month or 90-Day Rates and Yields: Interbank Rates: Total for United States (IR3TIB01USM156N) | K6: Deposit facility - date of changes (raw data) - Level | L6: Euro short-term rate | M6: Euribor 1-month - Historical close, average of observations through period | N6: Euribor 3-month - Historical close, average of observations through period | O6: Euribor 6-month - Historical close, average of observations through period | P6: Euribor 1-year - Historical close, average of observations through period | Q6: Interest Rates: 3-Month or 90-Day Rates and Yields: Interbank Rates: Total for Euro Area (19 Countries) (IR3TIB01EZM156N) | R6: Monthly average of official Bank Rate | S6: Monthly average of SONIA | T6: BoE estimated UK OIS (SONIA) spot rate, 1M maturity, continuously compounded per BoE methodology | U6: BoE estimated UK OIS (SONIA) spot rate, 3M maturity, continuously compounded per BoE methodology | V6: BoE estimated UK OIS (SONIA) spot rate, 6M maturity, continuously compounded per BoE methodology | W6: BoE estimated UK OIS (SONIA) spot rate, 12M maturity, continuously compounded per BoE methodology | X6: Interest Rates: 3-Month or 90-Day Rates and Yields: Interbank Rates: Total for United Kingdom (IR3TIB01GBM156N) | Y6: Key policy rate, monthly average | Z6: NOWA, monthly average | AA6: Generic Norwegian Treasury bill yield 3M, monthly | AB6: Generic Norwegian Treasury bill yield 6M, monthly | AC6: Generic Norwegian Treasury bill yield 12M, monthly | AD6: Interest Rates: 3-Month or 90-Day Rates and Yields: Interbank Rates: Total for Norway (IR3TIB01NOM156N) | AE6: 1.3.1. 한국은행 기준금리 및 여수신금리 / 한국은행 기준금리 | AF6: 1.3.2.2. 시장금리(월,분기,년) / 무담보콜금리(1일) | AG6: 1.3.2.2. 시장금리(월,분기,년) / CD(91일) | AH6: 1.3.2.2. 시장금리(월,분기,년) / KORIBOR(3개월) | AI6: 1.3.2.2. 시장금리(월,분기,년) / KORIBOR(6개월) | AJ6: 1.3.2.2. 시장금리(월,분기,년) / KORIBOR(12개월) | AK6: 1.3.2.2. 시장금리(월,분기,년) / 통안증권(91일) | AL6: 1.3.2.2. 시장금리(월,분기,년) / 통안증권(1년) | AM6: 1.3.2.2. 시장금리(월,분기,년) / 국고채(1년) | AN6: Interest Rates: 3-Month or 90-Day Rates and Yields: Interbank Rates: Total for Korea (IR3TIB01KRM156N) | AO6: Shanghai Interbank Offered Rate, 1M tenor | AP6: Shanghai Interbank Offered Rate, 3M tenor | AQ6: Shanghai Interbank Offered Rate, 6M tenor | AR6: Shanghai Interbank Offered Rate, 1Y tenor | AS6: Loan Prime Rate 1-year, monthly fixing (value of that month's fixing) | AT6: Loan Prime Rate 5-year, monthly fixing | AU6: Interest Rates: 3-Month or 90-Day Rates and Yields: Interbank Rates: Total for China (IR3TIB01CNM156N) | AV6: Taxa de juros Selic acumulada no mês, anualizada base 252 | AW6: Interest Rates: Immediate Rates (< 24 Hours): Call Money/Interbank Rate: Total for Brazil (IRSTCI01BRM156N) | AX6: Interest Rates: 3-Month or 90-Day Rates and Yields: Interbank Rates: Total for Japan (IR3TIB01JPM156N) | AY6: Interest Rates: Immediate Rates (< 24 Hours): Call Money/Interbank Rate: Total for Japan (IRSTCI01JPM156N) | AZ6: "partial month" if month not complete at the latest Rates_Daily date
A7: Unit | B7: Percent | C7: Percent | D7: Percent | E7: Percent | F7: Percent | G7: Percent | H7: Percent | I7: Percent | J7: Percent | K7: % p.a. | L7: % p.a. | M7: % p.a. | N7: % p.a. | O7: % p.a. | P7: % p.a. | Q7: Percent | R7: % p.a. | S7: % p.a. | T7: % p.a. | U7: % p.a. | V7: % p.a. | W7: % p.a. | X7: Percent | Y7: % p.a. | Z7: % p.a. | AA7: % p.a. | AB7: % p.a. | AC7: % p.a. | AD7: Percent | AE7: % p.a. (연%) | AF7: % p.a. (연%) | AG7: % p.a. (연%) | AH7: % p.a. (연%) | AI7: % p.a. (연%) | AJ7: % p.a. (연%) | AK7: % p.a. (연%) | AL7: % p.a. (연%) | AM7: % p.a. (연%) | AN7: Percent | AO7: % p.a. | AP7: % p.a. | AQ7: % p.a. | AR7: % p.a. | AS7: % p.a. | AT7: % p.a. | AU7: Percent | AV7: % p.a. | AW7: Percent | AX7: Percent | AY7: Percent
A8: Frequency | B8: Monthly | C8: Month-end value (last daily obs <= month end; formula on Rates_Daily) | D8: Month-end value (last daily obs <= month end; formula on Rates_Daily) | E8: Monthly average of daily obs (formula on Rates_Daily) | F8: Monthly | G8: Monthly | H8: Monthly | I8: Monthly | J8: Monthly | K8: Month-end value (last daily obs <= month end; formula on Rates_Daily) | L8: Monthly average of daily obs (formula on Rates_Daily) | M8: Monthly (average of daily obs, per source) | N8: Monthly (average of daily obs, per source) | O8: Monthly (average of daily obs, per source) | P8: Monthly (average of daily obs, per source) | Q8: Monthly | R8: Monthly (average of daily obs, per source) | S8: Monthly (average of daily obs, per source) | T8: Monthly average of daily obs (formula on Rates_Daily) | U8: Monthly average of daily obs (formula on Rates_Daily) | V8: Monthly average of daily obs (formula on Rates_Daily) | W8: Monthly average of daily obs (formula on Rates_Daily) | X8: Monthly | Y8: Monthly (average of daily obs, per source) | Z8: Monthly (average of daily obs, per source) | AA8: Monthly (average of daily obs, per source) | AB8: Monthly (average of daily obs, per source) | AC8: Monthly (average of daily obs, per source) | AD8: Monthly | AE8: Monthly (average of daily obs, per source) | AF8: Monthly (average of daily obs, per source) | AG8: Monthly (average of daily obs, per source) | AH8: Monthly (average of daily obs, per source) | AI8: Monthly (average of daily obs, per source) | AJ8: Monthly (average of daily obs, per source) | AK8: Monthly (average of daily obs, per source) | AL8: Monthly (average of daily obs, per source) | AM8: Monthly (average of daily obs, per source) | AN8: Monthly | AO8: Monthly average of daily obs (formula on Rates_Daily) | AP8: Monthly average of daily obs (formula on Rates_Daily) | AQ8: Monthly average of daily obs (formula on Rates_Daily) | AR8: Monthly average of daily obs (formula on Rates_Daily) | AS8: Monthly fixing (~20th) | AT8: Monthly fixing (~20th) | AU8: Monthly | AV8: Monthly | AW8: Monthly | AX8: Monthly | AY8: Monthly | AZ8: Monthly
A9: URL | B9: https://fred.stlouisfed.org/series/FEDFUNDS | C9: https://fred.stlouisfed.org/series/DFEDTARU | D9: https://fred.stlouisfed.org/series/DFEDTARL | E9: https://fred.stlouisfed.org/series/SOFR | F9: https://fred.stlouisfed.org/series/GS1M | G9: https://fred.stlouisfed.org/series/GS3M | H9: https://fred.stlouisfed.org/series/GS6M | I9: https://fred.stlouisfed.org/series/GS1 | J9: https://fred.stlouisfed.org/series/IR3TIB01USM156N | K9: https://data.ecb.europa.eu/data/datasets/FM/FM.D.U2.EUR.4F.KR.DFR.LEV | L9: https://data.ecb.europa.eu/data/datasets/EST/EST.B.EU000A2X2A25.WT | M9: https://data.ecb.europa.eu/data/datasets/FM/FM.M.U2.EUR.RT.MM.EURIBOR1MD_.HSTA | N9: https://data.ecb.europa.eu/data/datasets/FM/FM.M.U2.EUR.RT.MM.EURIBOR3MD_.HSTA | O9: https://data.ecb.europa.eu/data/datasets/FM/FM.M.U2.EUR.RT.MM.EURIBOR6MD_.HSTA | P9: https://data.ecb.europa.eu/data/datasets/FM/FM.M.U2.EUR.RT.MM.EURIBOR1YD_.HSTA | Q9: https://fred.stlouisfed.org/series/IR3TIB01EZM156N | R9: https://www.bankofengland.co.uk/boeapps/database/?SeriesCodes=IUMABEDR | S9: https://www.bankofengland.co.uk/boeapps/database/?SeriesCodes=IUMASOIA | T9: https://www.bankofengland.co.uk/statistics/yield-curves (files: oisddata.zip, latest-yield-curve-data.zip; sheet "3. spot, short end") | U9: https://www.bankofengland.co.uk/statistics/yield-curves (files: oisddata.zip, latest-yield-curve-data.zip; sheet "3. spot, short end") | V9: https://www.bankofengland.co.uk/statistics/yield-curves (files: oisddata.zip, latest-yield-curve-data.zip; sheet "3. spot, short end") | W9: https://www.bankofengland.co.uk/statistics/yield-curves (files: oisddata.zip, latest-yield-curve-data.zip; sheet "3. spot, short end") | X9: https://fred.stlouisfed.org/series/IR3TIB01GBM156N | Y9: https://data.norges-bank.no/api/data/IR/M.KPRA.SD.?format=csv | Z9: https://data.norges-bank.no/api/data/SHORT_RATES/M.NOWA.ON.R?format=csv | AA9: https://data.norges-bank.no/api/data/GOVT_GENERIC_RATES/M.3M.TBIL.?format=csv | AB9: https://data.norges-bank.no/api/data/GOVT_GENERIC_RATES/M.6M.TBIL.?format=csv | AC9: https://data.norges-bank.no/api/data/GOVT_GENERIC_RATES/M.12M.TBIL.?format=csv | AD9: https://fred.stlouisfed.org/series/IR3TIB01NOM156N | AE9: https://ecos.bok.or.kr/api/StatisticSearch/[KEY]/json/kr/1/1000/722Y001/M/201601/202609/0101000 | AF9: https://ecos.bok.or.kr/api/StatisticSearch/[KEY]/json/kr/1/1000/721Y001/M/201601/202609/1010000 | AG9: https://ecos.bok.or.kr/api/StatisticSearch/[KEY]/json/kr/1/1000/721Y001/M/201601/202609/2010000 | AH9: https://ecos.bok.or.kr/api/StatisticSearch/[KEY]/json/kr/1/1000/721Y001/M/201601/202609/1025000 | AI9: https://ecos.bok.or.kr/api/StatisticSearch/[KEY]/json/kr/1/1000/721Y001/M/201601/202609/1026000 | AJ9: https://ecos.bok.or.kr/api/StatisticSearch/[KEY]/json/kr/1/1000/721Y001/M/201601/202609/1027000 | AK9: https://ecos.bok.or.kr/api/StatisticSearch/[KEY]/json/kr/1/1000/721Y001/M/201601/202609/6010300 | AL9: https://ecos.bok.or.kr/api/StatisticSearch/[KEY]/json/kr/1/1000/721Y001/M/201601/202609/6010100 | AM9: https://ecos.bok.or.kr/api/StatisticSearch/[KEY]/json/kr/1/1000/721Y001/M/201601/202609/5030000 | AN9: https://fred.stlouisfed.org/series/IR3TIB01KRM156N | AO9: https://www.chinamoney.com.cn/english/bmkshibor/ (API: /ags/ms/cm-u-bk-shibor/ShiborHis) | AP9: https://www.chinamoney.com.cn/english/bmkshibor/ (API: /ags/ms/cm-u-bk-shibor/ShiborHis) | AQ9: https://www.chinamoney.com.cn/english/bmkshibor/ (API: /ags/ms/cm-u-bk-shibor/ShiborHis) | AR9: https://www.chinamoney.com.cn/english/bmkshibor/ (API: /ags/ms/cm-u-bk-shibor/ShiborHis) | AS9: https://www.chinamoney.com.cn/english/bmklpr/ (API: /ags/ms/cm-u-bk-currency/LprHis) | AT9: https://www.chinamoney.com.cn/english/bmklpr/ | AU9: https://fred.stlouisfed.org/series/IR3TIB01CNM156N | AV9: https://api.bcb.gov.br/dados/serie/bcdata.sgs.4189/dados?formato=json | AW9: https://fred.stlouisfed.org/series/IRSTCI01BRM156N | AX9: https://fred.stlouisfed.org/series/IR3TIB01JPM156N | AY9: https://fred.stlouisfed.org/series/IRSTCI01JPM156N
A10: First observation (formula) | B10: =IFERROR(_xlfn.MINIFS($A$15:$A$144,B$15:B$144,">=-1E+99"),"N/A") -> 42370 | C10: =IFERROR(_xlfn.MINIFS($A$15:$A$144,C$15:C$144,">=-1E+99"),"N/A") -> 42370 | D10: =IFERROR(_xlfn.MINIFS($A$15:$A$144,D$15:D$144,">=-1E+99"),"N/A") -> 42370 | E10: =IFERROR(_xlfn.MINIFS($A$15:$A$144,E$15:E$144,">=-1E+99"),"N/A") -> 43191 | F10: =IFERROR(_xlfn.MINIFS($A$15:$A$144,F$15:F$144,">=-1E+99"),"N/A") -> 42370 | G10: =IFERROR(_xlfn.MINIFS($A$15:$A$144,G$15:G$144,">=-1E+99"),"N/A") -> 42370 | H10: =IFERROR(_xlfn.MINIFS($A$15:$A$144,H$15:H$144,">=-1E+99"),"N/A") -> 42370 | I10: =IFERROR(_xlfn.MINIFS($A$15:$A$144,I$15:I$144,">=-1E+99"),"N/A") -> 42370 | ... AZ10: =IFERROR(_xlfn.MINIFS($A$15:$A$144,AZ$15:AZ$144,">=-1E+99"),"N/A") -> 0
A11: Last observation (formula) | B11: =IFERROR(_xlfn.MAXIFS($A$15:$A$144,B$15:B$144,">=-1E+99"),"N/A") -> 46266 | C11: =IFERROR(_xlfn.MAXIFS($A$15:$A$144,C$15:C$144,">=-1E+99"),"N/A") -> 46296 | D11: =IFERROR(_xlfn.MAXIFS($A$15:$A$144,D$15:D$144,">=-1E+99"),"N/A") -> 46296 | E11: =IFERROR(_xlfn.MAXIFS($A$15:$A$144,E$15:E$144,">=-1E+99"),"N/A") -> 46296 | F11: =IFERROR(_xlfn.MAXIFS($A$15:$A$144,F$15:F$144,">=-1E+99"),"N/A") -> 46266 | G11: =IFERROR(_xlfn.MAXIFS($A$15:$A$144,G$15:G$144,">=-1E+99"),"N/A") -> 46266 | H11: =IFERROR(_xlfn.MAXIFS($A$15:$A$144,H$15:H$144,">=-1E+99"),"N/A") -> 46266 | I11: =IFERROR(_xlfn.MAXIFS($A$15:$A$144,I$15:I$144,">=-1E+99"),"N/A") -> 46266 | ... AZ11: =IFERROR(_xlfn.MAXIFS($A$15:$A$144,AZ$15:AZ$144,">=-1E+99"),"N/A") -> 0
A12: Last value (formula) | B12: =IFERROR(INDEX(B$15:B$144,MATCH(B11,$A$15:$A$144,0)),"N/A") -> 3.75 | C12: =IFERROR(INDEX(C$15:C$144,MATCH(C11,$A$15:$A$144,0)),"N/A") -> 4 | D12: =IFERROR(INDEX(D$15:D$144,MATCH(D11,$A$15:$A$144,0)),"N/A") -> 3.75 | E12: =IFERROR(INDEX(E$15:E$144,MATCH(E11,$A$15:$A$144,0)),"N/A") -> 3.88 | F12: =IFERROR(INDEX(F$15:F$144,MATCH(F11,$A$15:$A$144,0)),"N/A") -> 3.93 | G12: =IFERROR(INDEX(G$15:G$144,MATCH(G11,$A$15:$A$144,0)),"N/A") -> 4.09 | H12: =IFERROR(INDEX(H$15:H$144,MATCH(H11,$A$15:$A$144,0)),"N/A") -> 4.18 | I12: =IFERROR(INDEX(I$15:I$144,MATCH(I11,$A$15:$A$144,0)),"N/A") -> 4.37 | ... AZ12: =IFERROR(INDEX(AZ$15:AZ$144,MATCH(AZ11,$A$15:$A$144,0)),"N/A") -> N/A
A13: Observations (count, formula) | B13: =COUNT(B$15:B$144) -> 129 | C13: =COUNT(C$15:C$144) -> 130 | D13: =COUNT(D$15:D$144) -> 130 | E13: =COUNT(E$15:E$144) -> 103 | F13: =COUNT(F$15:F$144) -> 129 | G13: =COUNT(G$15:G$144) -> 129 | H13: =COUNT(H$15:H$144) -> 129 | I13: =COUNT(I$15:I$144) -> 129 | ... AZ13: =COUNT(AZ$15:AZ$144) -> 0
A14: Month (first day) | B14: USD Fed funds effective | C14: USD Fed target upper (month-end) | D14: USD Fed target lower (month-end) | E14: USD SOFR (monthly avg) | F14: USD T-bill 1M (CMT) | G14: USD T-bill 3M (CMT) | H14: USD T-bill 6M (CMT) | I14: USD Treasury 12M (CMT) | J14: USD 3M interbank (OECD) | K14: EUR ECB deposit rate (month-end) | L14: EUR €STR (monthly avg) | M14: EUR Euribor 1M | N14: EUR Euribor 3M | O14: EUR Euribor 6M | P14: EUR Euribor 12M | Q14: EUR 3M interbank (OECD) | R14: GBP Bank Rate (monthly avg) | S14: GBP SONIA (monthly avg) | T14: GBP OIS 1M (monthly avg) | U14: GBP OIS 3M (monthly avg) | V14: GBP OIS 6M (monthly avg) | W14: GBP OIS 12M (monthly avg) | X14: GBP 3M interbank (OECD) | Y14: NOK policy rate (monthly avg) | Z14: NOK NOWA (monthly avg) | AA14: NOK T-bill 3M | AB14: NOK T-bill 6M | AC14: NOK T-bill 12M | AD14: NOK 3M interbank (OECD; NIBOR-based) | AE14: KRW BoK base rate | AF14: KRW call rate (O/N) | AG14: KRW CD 91-day | AH14: KRW KORIBOR 3M | AI14: KRW KORIBOR 6M | AJ14: KRW KORIBOR 12M | AK14: KRW MSB 91-day | AL14: KRW MSB 1Y | AM14: KRW KTB 1Y | AN14: KRW 3M interbank (OECD) | AO14: CNY Shibor 1M (monthly avg) | AP14: CNY Shibor 3M (monthly avg) | AQ14: CNY Shibor 6M (monthly avg) | AR14: CNY Shibor 1Y (monthly avg) | AS14: CNY LPR 1Y (monthly fixing) | AT14: CNY LPR 5Y (monthly fixing) | AU14: CNY 3M interbank (OECD) | AV14: BRL Selic (monthly, annualized) — reference | AW14: BRL call money (OECD) — reference | AX14: JPY 3M interbank (OECD) — reference | AY14: JPY call money (OECD) — reference | AZ14: Month status (daily-derived columns)
A15: 42370 | B15: 0.34 | C15: =IFERROR(INDEX(Rates_Daily!C$15:C$2892,MATCH(_xlfn.MAXIFS(Rates_Daily!$A$15:$A$2892,Rates_Daily!$A$15:$A$2892,"<="&EOMONTH($A15,0),Rates_Daily!C$15:C$2892,">=-1E+99"),Rates_Daily!$A$15:$A$2892,0)),"") -> 0.5 | D15: =IFERROR(INDEX(Rates_Daily!D$15:D$2892,MATCH(_xlfn.MAXIFS(Rates_Daily!$A$15:$A$2892,Rates_Daily!$A$15:$A$2892,"<="&EOMONTH($A15,0),Rates_Daily!D$15:D$2892,">=-1E+99"),Rates_Daily!$A$15:$A$2892,0)),"") -> 0.25 | E15: =IFERROR(AVERAGEIFS(Rates_Daily!B$15:B$2892,Rates_Daily!$A$15:$A$2892,">="&$A15,Rates_Daily!$A$15:$A$2892,"<="&EOMONTH($A15,0)),"") | F15: 0.23 | G15: 0.26 | H15: 0.43 | I15: 0.54 | J15: 0.57 | K15: =IFERROR(INDEX(Rates_Daily!F$15:F$2892,MATCH(_xlfn.MAXIFS(Rates_Daily!$A$15:$A$2892,Rates_Daily!$A$15:$A$2892,"<="&EOMONTH($A15,0),Rates_Daily!F$15:F$2892,">=-1E+99"),Rates_Daily!$A$15:$A$2892,0)),"") -> -0.3 | L15: =IFERROR(AVERAGEIFS(Rates_Daily!E$15:E$2892,Rates_Daily!$A$15:$A$2892,">="&$A15,Rates_Daily!$A$15:$A$2892,"<="&EOMONTH($A15,0)),"") | M15: -0.22265 | N15: -0.14615 | O15: -0.0608 | P15: 0.04235 | Q15: -0.14615 | R15: 0.5 | S15: 0.4659 | T15: =IFERROR(AVERAGEIFS(Rates_Daily!I$15:I$2892,Rates_Daily!$A$15:$A$2892,">="&$A15,Rates_Daily!$A$15:$A$2892,"<="&EOMONTH($A15,0)),"") -> 0.46296646 | U15: =IFERROR(AVERAGEIFS(Rates_Daily!J$15:J$2892,Rates_Daily!$A$15:$A$2892,">="&$A15,Rates_Daily!$A$15:$A$2892,"<="&EOMONTH($A15,0)),"") -> 0.46355702 | V15: =IFERROR(AVERAGEIFS(Rates_Daily!K$15:K$2892,Rates_Daily!$A$15:$A$2892,">="&$A15,Rates_Daily!$A$15:$A$2892,"<="&EOMONTH($A15,0)),"") -> 0.46360117 | W15: =IFERROR(AVERAGEIFS(Rates_Daily!L$15:L$2892,Rates_Daily!$A$15:$A$2892,">="&$A15,Rates_Daily!$A$15:$A$2892,"<="&EOMONTH($A15,0)),"") -> 0.4792427 | X15: 0.58976 | Y15: 0.75 | Z15: 0.74 | AD15: 1.16 | AE15: 1.5 | AF15: 1.49 | AG15: 1.67 | AH15: 1.61 | AI15: 1.64 | AJ15: 1.66 | AK15: 1.52 | AL15: 1.588 | AM15: 1.587 | AN15: 1.67 | AO15: =IFERROR(AVERAGEIFS(Rates_Daily!M$15:M$2892,Rates_Daily!$A$15:$A$2892,">="&$A15,Rates_Daily!$A$15:$A$2892,"<="&EOMONTH($A15,0)),"") -> 2.990625 | AP15: =IFERROR(AVERAGEIFS(Rates_Daily!N$15:N$2892,Rates_Daily!$A$15:$A$2892,">="&$A15,Rates_Daily!$A$15:$A$2892,"<="&EOMONTH($A15,0)),"") -> 3.048005 | AQ15: =IFERROR(AVERAGEIFS(Rates_Daily!O$15:O$2892,Rates_Daily!$A$15:$A$2892,">="&$A15,Rates_Daily!$A$15:$A$2892,"<="&EOMONTH($A15,0)),"") -> 3.14602 | AR15: =IFERROR(AVERAGEIFS(Rates_Daily!P$15:P$2892,Rates_Daily!$A$15:$A$2892,">="&$A15,Rates_Daily!$A$15:$A$2892,"<="&EOMONTH($A15,0)),"") -> 3.29871 | AU15: 3.19 | AV15: 14.15 | AW15: 14.25 | AX15: 0.169 | AY15: 0.07 | AZ15: =IF(EOMONTH($A15,0)>MAX(Rates_Daily!$A$15:$A$2892),"partial month","complete") -> complete
A16: 42401 | B16: 0.38 | C16: =IFERROR(INDEX(Rates_Daily!C$15:C$2892,MATCH(_xlfn.MAXIFS(Rates_Daily!$A$15:$A$2892,Rates_Daily!$A$15:$A$2892,"<="&EOMONTH($A16,0),Rates_Daily!C$15:C$2892,">=-1E+99"),Rates_Daily!$A$15:$A$2892,0)),"") -> 0.5 | D16: =IFERROR(INDEX(Rates_Daily!D$15:D$2892,MATCH(_xlfn.MAXIFS(Rates_Daily!$A$15:$A$2892,Rates_Daily!$A$15:$A$2892,"<="&EOMONTH($A16,0),Rates_Daily!D$15:D$2892,">=-1E+99"),Rates_Daily!$A$15:$A$2892,0)),"") -> 0.25 | E16: =IFERROR(AVERAGEIFS(Rates_Daily!B$15:B$2892,Rates_Daily!$A$15:$A$2892,">="&$A16,Rates_Daily!$A$15:$A$2892,"<="&EOMONTH($A16,0)),"") | F16: 0.26 | G16: 0.31 | H16: 0.45 | I16: 0.53 | J16: 0.54 | K16: =IFERROR(INDEX(Rates_Daily!F$15:F$2892,MATCH(_xlfn.MAXIFS(Rates_Daily!$A$15:$A$2892,Rates_Daily!$A$15:$A$2892,"<="&EOMONTH($A16,0),Rates_Daily!F$15:F$2892,">=-1E+99"),Rates_Daily!$A$15:$A$2892,0)),"") -> -0.3 | L16: =IFERROR(AVERAGEIFS(Rates_Daily!E$15:E$2892,Rates_Daily!$A$15:$A$2892,">="&$A16,Rates_Daily!$A$15:$A$2892,"<="&EOMONTH($A16,0)),"") | M16: -0.2460476 | N16: -0.1835714 | O16: -0.1152857 | P16: -0.0078571 | Q16: -0.18357143 | R16: 0.5 | S16: 0.4657 | T16: =IFERROR(AVERAGEIFS(Rates_Daily!I$15:I$2892,Rates_Daily!$A$15:$A$2892,">="&$A16,Rates_Daily!$A$15:$A$2892,"<="&EOMONTH($A16,0)),"") -> 0.46279087 | U16: =IFERROR(AVERAGEIFS(Rates_Daily!J$15:J$2892,Rates_Daily!$A$15:$A$2892,">="&$A16,Rates_Daily!$A$15:$A$2892,"<="&EOMONTH($A16,0)),"") -> 0.45800681 | V16: =IFERROR(AVERAGEIFS(Rates_Daily!K$15:K$2892,Rates_Daily!$A$15:$A$2892,">="&$A16,Rates_Daily!$A$15:$A$2892,"<="&EOMONTH($A16,0)),"") -> 0.44150895 | W16: =IFERROR(AVERAGEIFS(Rates_Daily!L$15:L$2892,Rates_Daily!$A$15:$A$2892,">="&$A16,Rates_Daily!$A$15:$A$2892,"<="&EOMONTH($A16,0)),"") -> 0.40501426 | X16: 0.59073 | Y16: 0.75 | Z16: 0.74 | AD16: 1.09 | AE16: 1.5 | AF16: 1.49 | AG16: 1.64 | AH16: 1.54 | AI16: 1.55 | AJ16: 1.56 | AK16: 1.465 | AL16: 1.47 | AM16: 1.469 | AN16: 1.64 | AO16: =IFERROR(AVERAGEIFS(Rates_Daily!M$15:M$2892,Rates_Daily!$A$15:$A$2892,">="&$A16,Rates_Daily!$A$15:$A$2892,"<="&EOMONTH($A16,0)),"") -> 2.9337778 | AP16: =IFERROR(AVERAGEIFS(Rates_Daily!N$15:N$2892,Rates_Daily!$A$15:$A$2892,">="&$A16,Rates_Daily!$A$15:$A$2892,"<="&EOMONTH($A16,0)),"") -> 2.9994167 | AQ16: =IFERROR(AVERAGEIFS(Rates_Daily!O$15:O$2892,Rates_Daily!$A$15:$A$2892,">="&$A16,Rates_Daily!$A$15:$A$2892,"<="&EOMONTH($A16,0)),"") -> 3.0810667 | AR16: =IFERROR(AVERAGEIFS(Rates_Daily!P$15:P$2892,Rates_Daily!$A$15:$A$2892,">="&$A16,Rates_Daily!$A$15:$A$2892,"<="&EOMONTH($A16,0)),"") -> 3.2355 | AU16: 2.95 | AV16: 14.15 | AW16: 14.25 | AX16: 0.098 | AY16: 0.03 | AZ16: =IF(EOMONTH($A16,0)>MAX(Rates_Daily!$A$15:$A$2892),"partial month","complete") -> complete
A17: 42430 | B17: 0.36 | C17: =IFERROR(INDEX(Rates_Daily!C$15:C$2892,MATCH(_xlfn.MAXIFS(Rates_Daily!$A$15:$A$2892,Rates_Daily!$A$15:$A$2892,"<="&EOMONTH($A17,0),Rates_Daily!C$15:C$2892,">=-1E+99"),Rates_Daily!$A$15:$A$2892,0)),"") -> 0.5 | D17: =IFERROR(INDEX(Rates_Daily!D$15:D$2892,MATCH(_xlfn.MAXIFS(Rates_Daily!$A$15:$A$2892,Rates_Daily!$A$15:$A$2892,"<="&EOMONTH($A17,0),Rates_Daily!D$15:D$2892,">=-1E+99"),Rates_Daily!$A$15:$A$2892,0)),"") -> 0.25 | E17: =IFERROR(AVERAGEIFS(Rates_Daily!B$15:B$2892,Rates_Daily!$A$15:$A$2892,">="&$A17,Rates_Daily!$A$15:$A$2892,"<="&EOMONTH($A17,0)),"") | F17: 0.25 | G17: 0.3 | H17: 0.47 | I17: 0.66 | J17: 0.55 | K17: =IFERROR(INDEX(Rates_Daily!F$15:F$2892,MATCH(_xlfn.MAXIFS(Rates_Daily!$A$15:$A$2892,Rates_Daily!$A$15:$A$2892,"<="&EOMONTH($A17,0),Rates_Daily!F$15:F$2892,">=-1E+99"),Rates_Daily!$A$15:$A$2892,0)),"") -> -0.4 | L17: =IFERROR(AVERAGEIFS(Rates_Daily!E$15:E$2892,Rates_Daily!$A$15:$A$2892,">="&$A17,Rates_Daily!$A$15:$A$2892,"<="&EOMONTH($A17,0)),"") | M17: -0.3075714 | N17: -0.2285238 | O17: -0.1335714 | P17: -0.012381 | Q17: -0.22852381 | R17: 0.5 | S17: 0.4646 | T17: =IFERROR(AVERAGEIFS(Rates_Daily!I$15:I$2892,Rates_Daily!$A$15:$A$2892,">="&$A17,Rates_Daily!$A$15:$A$2892,"<="&EOMONTH($A17,0)),"") -> 0.46261399 | U17: =IFERROR(AVERAGEIFS(Rates_Daily!J$15:J$2892,Rates_Daily!$A$15:$A$2892,">="&$A17,Rates_Daily!$A$15:$A$2892,"<="&EOMONTH($A17,0)),"") -> 0.45853117 | V17: =IFERROR(AVERAGEIFS(Rates_Daily!K$15:K$2892,Rates_Daily!$A$15:$A$2892,">="&$A17,Rates_Daily!$A$15:$A$2892,"<="&EOMONTH($A17,0)),"") -> 0.44779492 | W17: =IFERROR(AVERAGEIFS(Rates_Daily!L$15:L$2892,Rates_Daily!$A$15:$A$2892,">="&$A17,Rates_Daily!$A$15:$A$2892,"<="&EOMONTH($A17,0)),"") -> 0.43137039 | X17: 0.58825 | Y17: 0.66 | Z17: 0.67 | AD17: 1.02 | AE17: 1.5 | AF17: 1.49 | AG17: 1.63 | AH17: 1.55 | AI17: 1.56 | AJ17: 1.58 | AK17: 1.502 | AL17: 1.505 | AM17: 1.507 | AN17: 1.63 | AO17: =IFERROR(AVERAGEIFS(Rates_Daily!M$15:M$2892,Rates_Daily!$A$15:$A$2892,">="&$A17,Rates_Daily!$A$15:$A$2892,"<="&EOMONTH($A17,0)),"") -> 2.7031522 | AP17: =IFERROR(AVERAGEIFS(Rates_Daily!N$15:N$2892,Rates_Daily!$A$15:$A$2892,">="&$A17,Rates_Daily!$A$15:$A$2892,"<="&EOMONTH($A17,0)),"") -> 2.8105217 | AQ17: =IFERROR(AVERAGEIFS(Rates_Daily!O$15:O$2892,Rates_Daily!$A$15:$A$2892,">="&$A17,Rates_Daily!$A$15:$A$2892,"<="&EOMONTH($A17,0)),"") -> 2.9275391 | AR17: =IFERROR(AVERAGEIFS(Rates_Daily!P$15:P$2892,Rates_Daily!$A$15:$A$2892,">="&$A17,Rates_Daily!$A$15:$A$2892,"<="&EOMONTH($A17,0)),"") -> 3.0883696 | AU17: 2.77 | AV17: 14.15 | AW17: 14.25 | AX17: 0.098 | AY17: -0.003 | AZ17: =IF(EOMONTH($A17,0)>MAX(Rates_Daily!$A$15:$A$2892),"partial month","complete") -> complete
A18: 42461 | B18: 0.37 | C18: =IFERROR(INDEX(Rates_Daily!C$15:C$2892,MATCH(_xlfn.MAXIFS(Rates_Daily!$A$15:$A$2892,Rates_Daily!$A$15:$A$2892,"<="&EOMONTH($A18,0),Rates_Daily!C$15:C$2892,">=-1E+99"),Rates_Daily!$A$15:$A$2892,0)),"") -> 0.5 | D18: =IFERROR(INDEX(Rates_Daily!D$15:D$2892,MATCH(_xlfn.MAXIFS(Rates_Daily!$A$15:$A$2892,Rates_Daily!$A$15:$A$2892,"<="&EOMONTH($A18,0),Rates_Daily!D$15:D$2892,">=-1E+99"),Rates_Daily!$A$15:$A$2892,0)),"") -> 0.25 | E18: =IFERROR(AVERAGEIFS(Rates_Daily!B$15:B$2892,Rates_Daily!$A$15:$A$2892,">="&$A18,Rates_Daily!$A$15:$A$2892,"<="&EOMONTH($A18,0)),"") | F18: 0.19 | G18: 0.23 | H18: 0.37 | I18: 0.56 | J18: 0.55 | K18: =IFERROR(INDEX(Rates_Daily!F$15:F$2892,MATCH(_xlfn.MAXIFS(Rates_Daily!$A$15:$A$2892,Rates_Daily!$A$15:$A$2892,"<="&EOMONTH($A18,0),Rates_Daily!F$15:F$2892,">=-1E+99"),Rates_Daily!$A$15:$A$2892,0)),"") -> -0.4 | L18: =IFERROR(AVERAGEIFS(Rates_Daily!E$15:E$2892,Rates_Daily!$A$15:$A$2892,">="&$A18,Rates_Daily!$A$15:$A$2892,"<="&EOMONTH($A18,0)),"") | M18: -0.3411905 | N18: -0.2491905 | O18: -0.1379524 | P18: -0.0097619 | Q18: -0.24919048 | R18: 0.5 | S18: 0.4663 | T18: =IFERROR(AVERAGEIFS(Rates_Daily!I$15:I$2892,Rates_Daily!$A$15:$A$2892,">="&$A18,Rates_Daily!$A$15:$A$2892,"<="&EOMONTH($A18,0)),"") -> 0.46431198 | U18: =IFERROR(AVERAGEIFS(Rates_Daily!J$15:J$2892,Rates_Daily!$A$15:$A$2892,">="&$A18,Rates_Daily!$A$15:$A$2892,"<="&EOMONTH($A18,0)),"") -> 0.45719095 | V18: =IFERROR(AVERAGEIFS(Rates_Daily!K$15:K$2892,Rates_Daily!$A$15:$A$2892,">="&$A18,Rates_Daily!$A$15:$A$2892,"<="&EOMONTH($A18,0)),"") -> 0.43809501 | W18: =IFERROR(AVERAGEIFS(Rates_Daily!L$15:L$2892,Rates_Daily!$A$15:$A$2892,">="&$A18,Rates_Daily!$A$15:$A$2892,"<="&EOMONTH($A18,0)),"") -> 0.42355271 | X18: 0.5889 | Y18: 0.5 | Z18: 0.49 | AD18: 0.98 | AE18: 1.5 | AF18: 1.49 | AG18: 1.61 | AH18: 1.55 | AI18: 1.56 | AJ18: 1.57 | AK18: 1.505 | AL18: 1.494 | AM18: 1.493 | AN18: 1.61 | AO18: =IFERROR(AVERAGEIFS(Rates_Daily!M$15:M$2892,Rates_Daily!$A$15:$A$2892,">="&$A18,Rates_Daily!$A$15:$A$2892,"<="&EOMONTH($A18,0)),"") -> 2.811575 | AP18: =IFERROR(AVERAGEIFS(Rates_Daily!N$15:N$2892,Rates_Daily!$A$15:$A$2892,">="&$A18,Rates_Daily!$A$15:$A$2892,"<="&EOMONTH($A18,0)),"") -> 2.85876 | AQ18: =IFERROR(AVERAGEIFS(Rates_Daily!O$15:O$2892,Rates_Daily!$A$15:$A$2892,">="&$A18,Rates_Daily!$A$15:$A$2892,"<="&EOMONTH($A18,0)),"") -> 2.89461 | AR18: =IFERROR(AVERAGEIFS(Rates_Daily!P$15:P$2892,Rates_Daily!$A$15:$A$2892,">="&$A18,Rates_Daily!$A$15:$A$2892,"<="&EOMONTH($A18,0)),"") -> 3.04395 | AU18: 2.95 | AV18: 14.15 | AW18: 14.25 | AX18: 0.06 | AY18: -0.036 | AZ18: =IF(EOMONTH($A18,0)>MAX(Rates_Daily!$A$15:$A$2892),"partial month","complete") -> complete
A19: 42491 | B19: 0.37 | C19: =IFERROR(INDEX(Rates_Daily!C$15:C$2892,MATCH(_xlfn.MAXIFS(Rates_Daily!$A$15:$A$2892,Rates_Daily!$A$15:$A$2892,"<="&EOMONTH($A19,0),Rates_Daily!C$15:C$2892,">=-1E+99"),Rates_Daily!$A$15:$A$2892,0)),"") -> 0.5 | D19: =IFERROR(INDEX(Rates_Daily!D$15:D$2892,MATCH(_xlfn.MAXIFS(Rates_Daily!$A$15:$A$2892,Rates_Daily!$A$15:$A$2892,"<="&EOMONTH($A19,0),Rates_Daily!D$15:D$2892,">=-1E+99"),Rates_Daily!$A$15:$A$2892,0)),"") -> 0.25 | E19: =IFERROR(AVERAGEIFS(Rates_Daily!B$15:B$2892,Rates_Daily!$A$15:$A$2892,">="&$A19,Rates_Daily!$A$15:$A$2892,"<="&EOMONTH($A19,0)),"") | F19: 0.23 | G19: 0.28 | H19: 0.42 | I19: 0.59 | J19: 0.57 | K19: =IFERROR(INDEX(Rates_Daily!F$15:F$2892,MATCH(_xlfn.MAXIFS(Rates_Daily!$A$15:$A$2892,Rates_Daily!$A$15:$A$2892,"<="&EOMONTH($A19,0),Rates_Daily!F$15:F$2892,">=-1E+99"),Rates_Daily!$A$15:$A$2892,0)),"") -> -0.4 | L19: =IFERROR(AVERAGEIFS(Rates_Daily!E$15:E$2892,Rates_Daily!$A$15:$A$2892,">="&$A19,Rates_Daily!$A$15:$A$2892,"<="&EOMONTH($A19,0)),"") | M19: -0.348 | N19: -0.2571818 | O19: -0.1445 | P19: -0.0125909 | Q19: -0.25718182 | R19: 0.5 | S19: 0.4633 | T19: =IFERROR(AVERAGEIFS(Rates_Daily!I$15:I$2892,Rates_Daily!$A$15:$A$2892,">="&$A19,Rates_Daily!$A$15:$A$2892,"<="&EOMONTH($A19,0)),"") -> 0.4630296 | U19: =IFERROR(AVERAGEIFS(Rates_Daily!J$15:J$2892,Rates_Daily!$A$15:$A$2892,">="&$A19,Rates_Daily!$A$15:$A$2892,"<="&EOMONTH($A19,0)),"") -> 0.44634154 | V19: =IFERROR(AVERAGEIFS(Rates_Daily!K$15:K$2892,Rates_Daily!$A$15:$A$2892,">="&$A19,Rates_Daily!$A$15:$A$2892,"<="&EOMONTH($A19,0)),"") -> 0.42181137 | W19: =IFERROR(AVERAGEIFS(Rates_Daily!L$15:L$2892,Rates_Daily!$A$15:$A$2892,">="&$A19,Rates_Daily!$A$15:$A$2892,"<="&EOMONTH($A19,0)),"") -> 0.41266448 | X19: 0.58929 | Y19: 0.5 | Z19: 0.49 | AD19: 0.98 | AE19: 1.5 | AF19: 1.49 | AG19: 1.58 | AH19: 1.52 | AI19: 1.53 | AJ19: 1.55 | AK19: 1.487 | AL19: 1.481 | AM19: 1.48 | AN19: 1.58 | AO19: =IFERROR(AVERAGEIFS(Rates_Daily!M$15:M$2892,Rates_Daily!$A$15:$A$2892,">="&$A19,Rates_Daily!$A$15:$A$2892,"<="&EOMONTH($A19,0)),"") -> 2.8410429 | AP19: =IFERROR(AVERAGEIFS(Rates_Daily!N$15:N$2892,Rates_Daily!$A$15:$A$2892,">="&$A19,Rates_Daily!$A$15:$A$2892,"<="&EOMONTH($A19,0)),"") -> 2.9165952 | AQ19: =IFERROR(AVERAGEIFS(Rates_Daily!O$15:O$2892,Rates_Daily!$A$15:$A$2892,">="&$A19,Rates_Daily!$A$15:$A$2892,"<="&EOMONTH($A19,0)),"") -> 2.9570238 | AR19: =IFERROR(AVERAGEIFS(Rates_Daily!P$15:P$2892,Rates_Daily!$A$15:$A$2892,">="&$A19,Rates_Daily!$A$15:$A$2892,"<="&EOMONTH($A19,0)),"") -> 3.0466762 | AU19: 2.89 | AV19: 14.15 | AW19: 14.25 | AX19: 0.06 | AY19: -0.059 | AZ19: =IF(EOMONTH($A19,0)>MAX(Rates_Daily!$A$15:$A$2892),"partial month","complete") -> complete
A20: 42522 | B20: 0.38 | C20: =IFERROR(INDEX(Rates_Daily!C$15:C$2892,MATCH(_xlfn.MAXIFS(Rates_Daily!$A$15:$A$2892,Rates_Daily!$A$15:$A$2892,"<="&EOMONTH($A20,0),Rates_Daily!C$15:C$2892,">=-1E+99"),Rates_Daily!$A$15:$A$2892,0)),"") -> 0.5 | D20: =IFERROR(INDEX(Rates_Daily!D$15:D$2892,MATCH(_xlfn.MAXIFS(Rates_Daily!$A$15:$A$2892,Rates_Daily!$A$15:$A$2892,"<="&EOMONTH($A20,0),Rates_Daily!D$15:D$2892,">=-1E+99"),Rates_Daily!$A$15:$A$2892,0)),"") -> 0.25 | E20: =IFERROR(AVERAGEIFS(Rates_Daily!B$15:B$2892,Rates_Daily!$A$15:$A$2892,">="&$A20,Rates_Daily!$A$15:$A$2892,"<="&EOMONTH($A20,0)),"") | F20: 0.22 | G20: 0.27 | H20: 0.4 | I20: 0.55 | J20: 0.55 | K20: =IFERROR(INDEX(Rates_Daily!F$15:F$2892,MATCH(_xlfn.MAXIFS(Rates_Daily!$A$15:$A$2892,Rates_Daily!$A$15:$A$2892,"<="&EOMONTH($A20,0),Rates_Daily!F$15:F$2892,">=-1E+99"),Rates_Daily!$A$15:$A$2892,0)),"") -> -0.4 | L20: =IFERROR(AVERAGEIFS(Rates_Daily!E$15:E$2892,Rates_Daily!$A$15:$A$2892,">="&$A20,Rates_Daily!$A$15:$A$2892,"<="&EOMONTH($A20,0)),"") | M20: -0.3559091 | N20: -0.2679091 | O20: -0.1624091 | P20: -0.028 | Q20: -0.26790909 | R20: 0.5 | S20: 0.4598 | T20: =IFERROR(AVERAGEIFS(Rates_Daily!I$15:I$2892,Rates_Daily!$A$15:$A$2892,">="&$A20,Rates_Daily!$A$15:$A$2892,"<="&EOMONTH($A20,0)),"") -> 0.44297256 | U20: =IFERROR(AVERAGEIFS(Rates_Daily!J$15:J$2892,Rates_Daily!$A$15:$A$2892,">="&$A20,Rates_Daily!$A$15:$A$2892,"<="&EOMONTH($A20,0)),"") -> 0.39915811 | V20: =IFERROR(AVERAGEIFS(Rates_Daily!K$15:K$2892,Rates_Daily!$A$15:$A$2892,">="&$A20,Rates_Daily!$A$15:$A$2892,"<="&EOMONTH($A20,0)),"") -> 0.36546661 | W20: =IFERROR(AVERAGEIFS(Rates_Daily!L$15:L$2892,Rates_Daily!$A$15:$A$2892,">="&$A20,Rates_Daily!$A$15:$A$2892,"<="&EOMONTH($A20,0)),"") -> 0.34240853 | X20: 0.57468 | Y20: 0.5 | Z20: 0.49 | AD20: 1.02 | AE20: 1.25 | AF20: 1.28 | AG20: 1.43 | AH20: 1.37 | AI20: 1.39 | AJ20: 1.43 | AK20: 1.353 | AL20: 1.36 | AM20: 1.361 | AN20: 1.43 | AO20: =IFERROR(AVERAGEIFS(Rates_Daily!M$15:M$2892,Rates_Daily!$A$15:$A$2892,">="&$A20,Rates_Daily!$A$15:$A$2892,"<="&EOMONTH($A20,0)),"") -> 2.8597905 | AP20: =IFERROR(AVERAGEIFS(Rates_Daily!N$15:N$2892,Rates_Daily!$A$15:$A$2892,">="&$A20,Rates_Daily!$A$15:$A$2892,"<="&EOMONTH($A20,0)),"") -> 2.9540429 | AQ20: =IFERROR(AVERAGEIFS(Rates_Daily!O$15:O$2892,Rates_Daily!$A$15:$A$2892,">="&$A20,Rates_Daily!$A$15:$A$2892,"<="&EOMONTH($A20,0)),"") -> 2.9837714 | AR20: =IFERROR(AVERAGEIFS(Rates_Daily!P$15:P$2892,Rates_Daily!$A$15:$A$2892,">="&$A20,Rates_Daily!$A$15:$A$2892,"<="&EOMONTH($A20,0)),"") -> 3.050381 | AU20: 2.87 | AV20: 14.15 | AW20: 14.25 | AX20: 0.059 | AY20: -0.055 | AZ20: =IF(EOMONTH($A20,0)>MAX(Rates_Daily!$A$15:$A$2892),"partial month","complete") -> complete
A21: 42552 | B21: 0.39 | C21: =IFERROR(INDEX(Rates_Daily!C$15:C$2892,MATCH(_xlfn.MAXIFS(Rates_Daily!$A$15:$A$2892,Rates_Daily!$A$15:$A$2892,"<="&EOMONTH($A21,0),Rates_Daily!C$15:C$2892,">=-1E+99"),Rates_Daily!$A$15:$A$2892,0)),"") -> 0.5 | D21: =IFERROR(INDEX(Rates_Daily!D$15:D$2892,MATCH(_xlfn.MAXIFS(Rates_Daily!$A$15:$A$2892,Rates_Daily!$A$15:$A$2892,"<="&EOMONTH($A21,0),Rates_Daily!D$15:D$2892,">=-1E+99"),Rates_Daily!$A$15:$A$2892,0)),"") -> 0.25 | E21: =IFERROR(AVERAGEIFS(Rates_Daily!B$15:B$2892,Rates_Daily!$A$15:$A$2892,">="&$A21,Rates_Daily!$A$15:$A$2892,"<="&EOMONTH($A21,0)),"") | F21: 0.26 | G21: 0.3 | H21: 0.4 | I21: 0.51 | J21: 0.62 | K21: =IFERROR(INDEX(Rates_Daily!F$15:F$2892,MATCH(_xlfn.MAXIFS(Rates_Daily!$A$15:$A$2892,Rates_Daily!$A$15:$A$2892,"<="&EOMONTH($A21,0),Rates_Daily!F$15:F$2892,">=-1E+99"),Rates_Daily!$A$15:$A$2892,0)),"") -> -0.4 | L21: =IFERROR(AVERAGEIFS(Rates_Daily!E$15:E$2892,Rates_Daily!$A$15:$A$2892,">="&$A21,Rates_Daily!$A$15:$A$2892,"<="&EOMONTH($A21,0)),"") | M21: -0.3688095 | N21: -0.2945238 | O21: -0.1881905 | P21: -0.0560476 | Q21: -0.29452381 | R21: 0.5 | S21: 0.4577 | T21: =IFERROR(AVERAGEIFS(Rates_Daily!I$15:I$2892,Rates_Daily!$A$15:$A$2892,">="&$A21,Rates_Daily!$A$15:$A$2892,"<="&EOMONTH($A21,0)),"") -> 0.3196087 | U21: =IFERROR(AVERAGEIFS(Rates_Daily!J$15:J$2892,Rates_Daily!$A$15:$A$2892,">="&$A21,Rates_Daily!$A$15:$A$2892,"<="&EOMONTH($A21,0)),"") -> 0.23042862 | V21: =IFERROR(AVERAGEIFS(Rates_Daily!K$15:K$2892,Rates_Daily!$A$15:$A$2892,">="&$A21,Rates_Daily!$A$15:$A$2892,"<="&EOMONTH($A21,0)),"") -> 0.18159927 | W21: =IFERROR(AVERAGEIFS(Rates_Daily!L$15:L$2892,Rates_Daily!$A$15:$A$2892,">="&$A21,Rates_Daily!$A$15:$A$2892,"<="&EOMONTH($A21,0)),"") -> 0.14718204 | X21: 0.5136 | Y21: 0.5 | Z21: 0.49 | AD21: 1.01 | AE21: 1.25 | AF21: 1.23 | AG21: 1.36 | AH21: 1.27 | AI21: 1.29 | AJ21: 1.32 | AK21: 1.251 | AL21: 1.259 | AM21: 1.26 | AN21: 1.36 | AO21: =IFERROR(AVERAGEIFS(Rates_Daily!M$15:M$2892,Rates_Daily!$A$15:$A$2892,">="&$A21,Rates_Daily!$A$15:$A$2892,"<="&EOMONTH($A21,0)),"") -> 2.8154762 | AP21: =IFERROR(AVERAGEIFS(Rates_Daily!N$15:N$2892,Rates_Daily!$A$15:$A$2892,">="&$A21,Rates_Daily!$A$15:$A$2892,"<="&EOMONTH($A21,0)),"") -> 2.8958 | AQ21: =IFERROR(AVERAGEIFS(Rates_Daily!O$15:O$2892,Rates_Daily!$A$15:$A$2892,">="&$A21,Rates_Daily!$A$15:$A$2892,"<="&EOMONTH($A21,0)),"") -> 2.9655476 | AR21: =IFERROR(AVERAGEIFS(Rates_Daily!P$15:P$2892,Rates_Daily!$A$15:$A$2892,">="&$A21,Rates_Daily!$A$15:$A$2892,"<="&EOMONTH($A21,0)),"") -> 3.046381 | AU21: 2.87 | AV21: 14.15 | AW21: 14.25 | AX21: 0.058 | AY21: -0.043 | AZ21: =IF(EOMONTH($A21,0)>MAX(Rates_Daily!$A$15:$A$2892),"partial month","complete") -> complete
A22: 42583 | B22: 0.4 | C22: =IFERROR(INDEX(Rates_Daily!C$15:C$2892,MATCH(_xlfn.MAXIFS(Rates_Daily!$A$15:$A$2892,Rates_Daily!$A$15:$A$2892,"<="&EOMONTH($A22,0),Rates_Daily!C$15:C$2892,">=-1E+99"),Rates_Daily!$A$15:$A$2892,0)),"") -> 0.5 | D22: =IFERROR(INDEX(Rates_Daily!D$15:D$2892,MATCH(_xlfn.MAXIFS(Rates_Daily!$A$15:$A$2892,Rates_Daily!$A$15:$A$2892,"<="&EOMONTH($A22,0),Rates_Daily!D$15:D$2892,">=-1E+99"),Rates_Daily!$A$15:$A$2892,0)),"") -> 0.25 | E22: =IFERROR(AVERAGEIFS(Rates_Daily!B$15:B$2892,Rates_Daily!$A$15:$A$2892,">="&$A22,Rates_Daily!$A$15:$A$2892,"<="&EOMONTH($A22,0)),"") | F22: 0.26 | G22: 0.3 | H22: 0.45 | I22: 0.57 | J22: 0.73 | K22: =IFERROR(INDEX(Rates_Daily!F$15:F$2892,MATCH(_xlfn.MAXIFS(Rates_Daily!$A$15:$A$2892,Rates_Daily!$A$15:$A$2892,"<="&EOMONTH($A22,0),Rates_Daily!F$15:F$2892,">=-1E+99"),Rates_Daily!$A$15:$A$2892,0)),"") -> -0.4 | L22: =IFERROR(AVERAGEIFS(Rates_Daily!E$15:E$2892,Rates_Daily!$A$15:$A$2892,">="&$A22,Rates_Daily!$A$15:$A$2892,"<="&EOMONTH($A22,0)),"") | M22: -0.3696957 | N22: -0.2982174 | O22: -0.1886522 | P22: -0.0483043 | Q22: -0.29821739 | R22: 0.2841 | S22: 0.2478 | T22: =IFERROR(AVERAGEIFS(Rates_Daily!I$15:I$2892,Rates_Daily!$A$15:$A$2892,">="&$A22,Rates_Daily!$A$15:$A$2892,"<="&EOMONTH($A22,0)),"") -> 0.21637368 | U22: =IFERROR(AVERAGEIFS(Rates_Daily!J$15:J$2892,Rates_Daily!$A$15:$A$2892,">="&$A22,Rates_Daily!$A$15:$A$2892,"<="&EOMONTH($A22,0)),"") -> 0.1894077 | V22: =IFERROR(AVERAGEIFS(Rates_Daily!K$15:K$2892,Rates_Daily!$A$15:$A$2892,">="&$A22,Rates_Daily!$A$15:$A$2892,"<="&EOMONTH($A22,0)),"") -> 0.15521491 | W22: =IFERROR(AVERAGEIFS(Rates_Daily!L$15:L$2892,Rates_Daily!$A$15:$A$2892,">="&$A22,Rates_Daily!$A$15:$A$2892,"<="&EOMONTH($A22,0)),"") -> 0.12429846 | X22: 0.40613 | Y22: 0.5 | Z22: 0.5 | AD22: 1.08 | AE22: 1.25 | AF22: 1.23 | AG22: 1.35 | AH22: 1.27 | AI22: 1.29 | AJ22: 1.32 | AK22: 1.256 | AL22: 1.266 | AM22: 1.265 | AN22: 1.35 | AO22: =IFERROR(AVERAGEIFS(Rates_Daily!M$15:M$2892,Rates_Daily!$A$15:$A$2892,">="&$A22,Rates_Daily!$A$15:$A$2892,"<="&EOMONTH($A22,0)),"") -> 2.7121 | AP22: =IFERROR(AVERAGEIFS(Rates_Daily!N$15:N$2892,Rates_Daily!$A$15:$A$2892,">="&$A22,Rates_Daily!$A$15:$A$2892,"<="&EOMONTH($A22,0)),"") -> 2.8061826 | AQ22: =IFERROR(AVERAGEIFS(Rates_Daily!O$15:O$2892,Rates_Daily!$A$15:$A$2892,">="&$A22,Rates_Daily!$A$15:$A$2892,"<="&EOMONTH($A22,0)),"") -> 2.9031174 | AR22: =IFERROR(AVERAGEIFS(Rates_Daily!P$15:P$2892,Rates_Daily!$A$15:$A$2892,">="&$A22,Rates_Daily!$A$15:$A$2892,"<="&EOMONTH($A22,0)),"") -> 3.0278522 | AU22: 2.77 | AV22: 14.15 | AW22: 14.25 | AX22: 0.058 | AY22: -0.043 | AZ22: =IF(EOMONTH($A22,0)>MAX(Rates_Daily!$A$15:$A$2892),"partial month","complete") -> complete
A23: 42614 | B23: 0.4 | C23: =IFERROR(INDEX(Rates_Daily!C$15:C$2892,MATCH(_xlfn.MAXIFS(Rates_Daily!$A$15:$A$2892,Rates_Daily!$A$15:$A$2892,"<="&EOMONTH($A23,0),Rates_Daily!C$15:C$2892,">=-1E+99"),Rates_Daily!$A$15:$A$2892,0)),"") -> 0.5 | D23: =IFERROR(INDEX(Rates_Daily!D$15:D$2892,MATCH(_xlfn.MAXIFS(Rates_Daily!$A$15:$A$2892,Rates_Daily!$A$15:$A$2892,"<="&EOMONTH($A23,0),Rates_Daily!D$15:D$2892,">=-1E+99"),Rates_Daily!$A$15:$A$2892,0)),"") -> 0.25 | E23: =IFERROR(AVERAGEIFS(Rates_Daily!B$15:B$2892,Rates_Daily!$A$15:$A$2892,">="&$A23,Rates_Daily!$A$15:$A$2892,"<="&EOMONTH($A23,0)),"") | F23: 0.19 | G23: 0.29 | H23: 0.47 | I23: 0.59 | J23: 0.75 | K23: =IFERROR(INDEX(Rates_Daily!F$15:F$2892,MATCH(_xlfn.MAXIFS(Rates_Daily!$A$15:$A$2892,Rates_Daily!$A$15:$A$2892,"<="&EOMONTH($A23,0),Rates_Daily!F$15:F$2892,">=-1E+99"),Rates_Daily!$A$15:$A$2892,0)),"") -> -0.4 | L23: =IFERROR(AVERAGEIFS(Rates_Daily!E$15:E$2892,Rates_Daily!$A$15:$A$2892,">="&$A23,Rates_Daily!$A$15:$A$2892,"<="&EOMONTH($A23,0)),"") | M23: -0.3713636 | N23: -0.3016364 | O23: -0.1991364 | P23: -0.0570909 | Q23: -0.30163636 | R23: 0.25 | S23: 0.213 | T23: =IFERROR(AVERAGEIFS(Rates_Daily!I$15:I$2892,Rates_Daily!$A$15:$A$2892,">="&$A23,Rates_Daily!$A$15:$A$2892,"<="&EOMONTH($A23,0)),"") -> 0.20993131 | U23: =IFERROR(AVERAGEIFS(Rates_Daily!J$15:J$2892,Rates_Daily!$A$15:$A$2892,">="&$A23,Rates_Daily!$A$15:$A$2892,"<="&EOMONTH($A23,0)),"") -> 0.18764072 | V23: =IFERROR(AVERAGEIFS(Rates_Daily!K$15:K$2892,Rates_Daily!$A$15:$A$2892,">="&$A23,Rates_Daily!$A$15:$A$2892,"<="&EOMONTH($A23,0)),"") -> 0.1627346 | W23: =IFERROR(AVERAGEIFS(Rates_Daily!L$15:L$2892,Rates_Daily!$A$15:$A$2892,">="&$A23,Rates_Daily!$A$15:$A$2892,"<="&EOMONTH($A23,0)),"") -> 0.13902201 | X23: 0.37907 | Y23: 0.5 | Z23: 0.57 | AD23: 1.09 | AE23: 1.25 | AF23: 1.24 | AG23: 1.34 | AH23: 1.31 | AI23: 1.35 | AJ23: 1.39 | AK23: 1.302 | AL23: 1.328 | AM23: 1.322 | AN23: 1.34 | AO23: =IFERROR(AVERAGEIFS(Rates_Daily!M$15:M$2892,Rates_Daily!$A$15:$A$2892,">="&$A23,Rates_Daily!$A$15:$A$2892,"<="&EOMONTH($A23,0)),"") -> 2.7025857 | AP23: =IFERROR(AVERAGEIFS(Rates_Daily!N$15:N$2892,Rates_Daily!$A$15:$A$2892,">="&$A23,Rates_Daily!$A$15:$A$2892,"<="&EOMONTH($A23,0)),"") -> 2.7932762 | AQ23: =IFERROR(AVERAGEIFS(Rates_Daily!O$15:O$2892,Rates_Daily!$A$15:$A$2892,">="&$A23,Rates_Daily!$A$15:$A$2892,"<="&EOMONTH($A23,0)),"") -> 2.8836524 | AR23: =IFERROR(AVERAGEIFS(Rates_Daily!P$15:P$2892,Rates_Daily!$A$15:$A$2892,">="&$A23,Rates_Daily!$A$15:$A$2892,"<="&EOMONTH($A23,0)),"") -> 3.026619 | AU23: 2.81 | AV23: 14.15 | AW23: 14.25 | AX23: 0.056 | AY23: -0.052 | AZ23: =IF(EOMONTH($A23,0)>MAX(Rates_Daily!$A$15:$A$2892),"partial month","complete") -> complete
A24: 42644 | B24: 0.4 | C24: =IFERROR(INDEX(Rates_Daily!C$15:C$2892,MATCH(_xlfn.MAXIFS(Rates_Daily!$A$15:$A$2892,Rates_Daily!$A$15:$A$2892,"<="&EOMONTH($A24,0),Rates_Daily!C$15:C$2892,">=-1E+99"),Rates_Daily!$A$15:$A$2892,0)),"") -> 0.5 | D24: =IFERROR(INDEX(Rates_Daily!D$15:D$2892,MATCH(_xlfn.MAXIFS(Rates_Daily!$A$15:$A$2892,Rates_Daily!$A$15:$A$2892,"<="&EOMONTH($A24,0),Rates_Daily!D$15:D$2892,">=-1E+99"),Rates_Daily!$A$15:$A$2892,0)),"") -> 0.25 | E24: =IFERROR(AVERAGEIFS(Rates_Daily!B$15:B$2892,Rates_Daily!$A$15:$A$2892,">="&$A24,Rates_Daily!$A$15:$A$2892,"<="&EOMONTH($A24,0)),"") | F24: 0.24 | G24: 0.33 | H24: 0.48 | I24: 0.66 | J24: 0.72 | K24: =IFERROR(INDEX(Rates_Daily!F$15:F$2892,MATCH(_xlfn.MAXIFS(Rates_Daily!$A$15:$A$2892,Rates_Daily!$A$15:$A$2892,"<="&EOMONTH($A24,0),Rates_Daily!F$15:F$2892,">=-1E+99"),Rates_Daily!$A$15:$A$2892,0)),"") -> -0.4 | L24: =IFERROR(AVERAGEIFS(Rates_Daily!E$15:E$2892,Rates_Daily!$A$15:$A$2892,">="&$A24,Rates_Daily!$A$15:$A$2892,"<="&EOMONTH($A24,0)),"") | M24: -0.3714286 | N24: -0.309 | O24: -0.2070952 | P24: -0.0687619 | Q24: -0.309 | R24: 0.25 | S24: 0.212 | T24: =IFERROR(AVERAGEIFS(Rates_Daily!I$15:I$2892,Rates_Daily!$A$15:$A$2892,">="&$A24,Rates_Daily!$A$15:$A$2892,"<="&EOMONTH($A24,0)),"") -> 0.20737669 | U24: =IFERROR(AVERAGEIFS(Rates_Daily!J$15:J$2892,Rates_Daily!$A$15:$A$2892,">="&$A24,Rates_Daily!$A$15:$A$2892,"<="&EOMONTH($A24,0)),"") -> 0.19666952 | V24: =IFERROR(AVERAGEIFS(Rates_Daily!K$15:K$2892,Rates_Daily!$A$15:$A$2892,">="&$A24,Rates_Daily!$A$15:$A$2892,"<="&EOMONTH($A24,0)),"") -> 0.18714855 | W24: =IFERROR(AVERAGEIFS(Rates_Daily!L$15:L$2892,Rates_Daily!$A$15:$A$2892,">="&$A24,Rates_Daily!$A$15:$A$2892,"<="&EOMONTH($A24,0)),"") -> 0.18006002 | X24: 0.3975 | Y24: 0.5 | Z24: 0.49 | AD24: 1.11 | AE24: 1.25 | AF24: 1.23 | AG24: 1.35 | AH24: 1.37 | AI24: 1.44 | AJ24: 1.49 | AK24: 1.345 | AL24: 1.379 | AM24: 1.369 | AN24: 1.35 | AO24: =IFERROR(AVERAGEIFS(Rates_Daily!M$15:M$2892,Rates_Daily!$A$15:$A$2892,">="&$A24,Rates_Daily!$A$15:$A$2892,"<="&EOMONTH($A24,0)),"") -> 2.7243611 | AP24: =IFERROR(AVERAGEIFS(Rates_Daily!N$15:N$2892,Rates_Daily!$A$15:$A$2892,">="&$A24,Rates_Daily!$A$15:$A$2892,"<="&EOMONTH($A24,0)),"") -> 2.8082778 | AQ24: =IFERROR(AVERAGEIFS(Rates_Daily!O$15:O$2892,Rates_Daily!$A$15:$A$2892,">="&$A24,Rates_Daily!$A$15:$A$2892,"<="&EOMONTH($A24,0)),"") -> 2.8901222 | AR24: =IFERROR(AVERAGEIFS(Rates_Daily!P$15:P$2892,Rates_Daily!$A$15:$A$2892,">="&$A24,Rates_Daily!$A$15:$A$2892,"<="&EOMONTH($A24,0)),"") -> 3.0286389 | AU24: 2.91 | AV24: 14.05 | AW24: 14.15 | AX24: 0.056 | AY24: -0.037 | AZ24: =IF(EOMONTH($A24,0)>MAX(Rates_Daily!$A$15:$A$2892),"partial month","complete") -> complete
A25: 42675 | B25: 0.41 | C25: =IFERROR(INDEX(Rates_Daily!C$15:C$2892,MATCH(_xlfn.MAXIFS(Rates_Daily!$A$15:$A$2892,Rates_Daily!$A$15:$A$2892,"<="&EOMONTH($A25,0),Rates_Daily!C$15:C$2892,">=-1E+99"),Rates_Daily!$A$15:$A$2892,0)),"") -> 0.5 | D25: =IFERROR(INDEX(Rates_Daily!D$15:D$2892,MATCH(_xlfn.MAXIFS(Rates_Daily!$A$15:$A$2892,Rates_Daily!$A$15:$A$2892,"<="&EOMONTH($A25,0),Rates_Daily!D$15:D$2892,">=-1E+99"),Rates_Daily!$A$15:$A$2892,0)),"") -> 0.25 | E25: =IFERROR(AVERAGEIFS(Rates_Daily!B$15:B$2892,Rates_Daily!$A$15:$A$2892,">="&$A25,Rates_Daily!$A$15:$A$2892,"<="&EOMONTH($A25,0)),"") | F25: 0.3 | G25: 0.45 | H25: 0.58 | I25: 0.74 | J25: 0.71 | K25: =IFERROR(INDEX(Rates_Daily!F$15:F$2892,MATCH(_xlfn.MAXIFS(Rates_Daily!$A$15:$A$2892,Rates_Daily!$A$15:$A$2892,"<="&EOMONTH($A25,0),Rates_Daily!F$15:F$2892,">=-1E+99"),Rates_Daily!$A$15:$A$2892,0)),"") -> -0.4 | L25: =IFERROR(AVERAGEIFS(Rates_Daily!E$15:E$2892,Rates_Daily!$A$15:$A$2892,">="&$A25,Rates_Daily!$A$15:$A$2892,"<="&EOMONTH($A25,0)),"") | M25: -0.3727727 | N25: -0.3126818 | O25: -0.2148182 | P25: -0.0740455 | Q25: -0.31268182 | R25: 0.25 | S25: 0.2108 | T25: =IFERROR(AVERAGEIFS(Rates_Daily!I$15:I$2892,Rates_Daily!$A$15:$A$2892,">="&$A25,Rates_Daily!$A$15:$A$2892,"<="&EOMONTH($A25,0)),"") -> 0.20799043 | U25: =IFERROR(AVERAGEIFS(Rates_Daily!J$15:J$2892,Rates_Daily!$A$15:$A$2892,">="&$A25,Rates_Daily!$A$15:$A$2892,"<="&EOMONTH($A25,0)),"") -> 0.20247342 | V25: =IFERROR(AVERAGEIFS(Rates_Daily!K$15:K$2892,Rates_Daily!$A$15:$A$2892,">="&$A25,Rates_Daily!$A$15:$A$2892,"<="&EOMONTH($A25,0)),"") -> 0.20057654 | W25: =IFERROR(AVERAGEIFS(Rates_Daily!L$15:L$2892,Rates_Daily!$A$15:$A$2892,">="&$A25,Rates_Daily!$A$15:$A$2892,"<="&EOMONTH($A25,0)),"") -> 0.21224826 | X25: 0.39773 | Y25: 0.5 | Z25: 0.5 | AD25: 1.1 | AE25: 1.25 | AF25: 1.23 | AG25: 1.42 | AH25: 1.48 | AI25: 1.57 | AJ25: 1.61 | AK25: 1.42 | AL25: 1.517 | AM25: 1.511 | AN25: 1.42 | AO25: =IFERROR(AVERAGEIFS(Rates_Daily!M$15:M$2892,Rates_Daily!$A$15:$A$2892,">="&$A25,Rates_Daily!$A$15:$A$2892,"<="&EOMONTH($A25,0)),"") -> 2.7789545 | AP25: =IFERROR(AVERAGEIFS(Rates_Daily!N$15:N$2892,Rates_Daily!$A$15:$A$2892,">="&$A25,Rates_Daily!$A$15:$A$2892,"<="&EOMONTH($A25,0)),"") -> 2.9201045 | AQ25: =IFERROR(AVERAGEIFS(Rates_Daily!O$15:O$2892,Rates_Daily!$A$15:$A$2892,">="&$A25,Rates_Daily!$A$15:$A$2892,"<="&EOMONTH($A25,0)),"") -> 2.9573773 | AR25: =IFERROR(AVERAGEIFS(Rates_Daily!P$15:P$2892,Rates_Daily!$A$15:$A$2892,">="&$A25,Rates_Daily!$A$15:$A$2892,"<="&EOMONTH($A25,0)),"") -> 3.0678818 | AU25: 3.35 | AV25: 13.9 | AW25: 14 | AX25: 0.056 | AY25: -0.049 | AZ25: =IF(EOMONTH($A25,0)>MAX(Rates_Daily!$A$15:$A$2892),"partial month","complete") -> complete
A26: 42705 | B26: 0.54 | C26: =IFERROR(INDEX(Rates_Daily!C$15:C$2892,MATCH(_xlfn.MAXIFS(Rates_Daily!$A$15:$A$2892,Rates_Daily!$A$15:$A$2892,"<="&EOMONTH($A26,0),Rates_Daily!C$15:C$2892,">=-1E+99"),Rates_Daily!$A$15:$A$2892,0)),"") -> 0.75 | D26: =IFERROR(INDEX(Rates_Daily!D$15:D$2892,MATCH(_xlfn.MAXIFS(Rates_Daily!$A$15:$A$2892,Rates_Daily!$A$15:$A$2892,"<="&EOMONTH($A26,0),Rates_Daily!D$15:D$2892,">=-1E+99"),Rates_Daily!$A$15:$A$2892,0)),"") -> 0.5 | E26: =IFERROR(AVERAGEIFS(Rates_Daily!B$15:B$2892,Rates_Daily!$A$15:$A$2892,">="&$A26,Rates_Daily!$A$15:$A$2892,"<="&EOMONTH($A26,0)),"") | F26: 0.42 | G26: 0.51 | H26: 0.64 | I26: 0.87 | J26: 0.87 | K26: =IFERROR(INDEX(Rates_Daily!F$15:F$2892,MATCH(_xlfn.MAXIFS(Rates_Daily!$A$15:$A$2892,Rates_Daily!$A$15:$A$2892,"<="&EOMONTH($A26,0),Rates_Daily!F$15:F$2892,">=-1E+99"),Rates_Daily!$A$15:$A$2892,0)),"") -> -0.4 | L26: =IFERROR(AVERAGEIFS(Rates_Daily!E$15:E$2892,Rates_Daily!$A$15:$A$2892,">="&$A26,Rates_Daily!$A$15:$A$2892,"<="&EOMONTH($A26,0)),"") | M26: -0.370381 | N26: -0.3157619 | O26: -0.2179048 | P26: -0.0804286 | Q26: -0.3157619 | R26: 0.25 | S26: 0.2125 | T26: =IFERROR(AVERAGEIFS(Rates_Daily!I$15:I$2892,Rates_Daily!$A$15:$A$2892,">="&$A26,Rates_Daily!$A$15:$A$2892,"<="&EOMONTH($A26,0)),"") -> 0.20546483 | U26: =IFERROR(AVERAGEIFS(Rates_Daily!J$15:J$2892,Rates_Daily!$A$15:$A$2892,">="&$A26,Rates_Daily!$A$15:$A$2892,"<="&EOMONTH($A26,0)),"") -> 0.20899051 | V26: =IFERROR(AVERAGEIFS(Rates_Daily!K$15:K$2892,Rates_Daily!$A$15:$A$2892,">="&$A26,Rates_Daily!$A$15:$A$2892,"<="&EOMONTH($A26,0)),"") -> 0.21334651 | W26: =IFERROR(AVERAGEIFS(Rates_Daily!L$15:L$2892,Rates_Daily!$A$15:$A$2892,">="&$A26,Rates_Daily!$A$15:$A$2892,"<="&EOMONTH($A26,0)),"") -> 0.23129726 | X26: 0.37226 | Y26: 0.5 | Z26: 0.51 | AD26: 1.16 | AE26: 1.25 | AF26: 1.22 | AG26: 1.54 | AH26: 1.51 | AI26: 1.61 | AJ26: 1.69 | AK26: 1.422 | AL26: 1.573 | AM26: 1.576 | AN26: 1.54 | AO26: =IFERROR(AVERAGEIFS(Rates_Daily!M$15:M$2892,Rates_Daily!$A$15:$A$2892,">="&$A26,Rates_Daily!$A$15:$A$2892,"<="&EOMONTH($A26,0)),"") -> 3.1321818 | AP26: =IFERROR(AVERAGEIFS(Rates_Daily!N$15:N$2892,Rates_Daily!$A$15:$A$2892,">="&$A26,Rates_Daily!$A$15:$A$2892,"<="&EOMONTH($A26,0)),"") -> 3.1734818 | AQ26: =IFERROR(AVERAGEIFS(Rates_Daily!O$15:O$2892,Rates_Daily!$A$15:$A$2892,">="&$A26,Rates_Daily!$A$15:$A$2892,"<="&EOMONTH($A26,0)),"") -> 3.1918727 | AR26: =IFERROR(AVERAGEIFS(Rates_Daily!P$15:P$2892,Rates_Daily!$A$15:$A$2892,">="&$A26,Rates_Daily!$A$15:$A$2892,"<="&EOMONTH($A26,0)),"") -> 3.2844364 | AU26: 4.77 | AV26: 13.65 | AW26: 13.75 | AX26: 0.056 | AY26: -0.044 | AZ26: =IF(EOMONTH($A26,0)>MAX(Rates_Daily!$A$15:$A$2892),"partial month","complete") -> complete
... A50: 43435 | B50: 2.27 | C50: =IFERROR(INDEX(Rates_Daily!C$15:C$2892,MATCH(_xlfn.MAXIFS(Rates_Daily!$A$15:$A$2892,Rates_Daily!$A$15:$A$2892,"<="&EOMONTH($A50,0),Rates_Daily!C$15:C$2892,">=-1E+99"),Rates_Daily!$A$15:$A$2892,0)),"") -> 2.5 | D50: =IFERROR(INDEX(Rates_Daily!D$15:D$2892,MATCH(_xlfn.MAXIFS(Rates_Daily!$A$15:$A$2892,Rates_Daily!$A$15:$A$2892,"<="&EOMONTH($A50,0),Rates_Daily!D$15:D$2892,">=-1E+99"),Rates_Daily!$A$15:$A$2892,0)),"") -> 2.25 | E50: =IFERROR(AVERAGEIFS(Rates_Daily!B$15:B$2892,Rates_Daily!$A$15:$A$2892,">="&$A50,Rates_Daily!$A$15:$A$2892,"<="&EOMONTH($A50,0)),"") -> 2.3505263 | F50: 2.37 | G50: 2.41 | H50: 2.54 | I50: 2.66 | J50: 2.69 | K50: =IFERROR(INDEX(Rates_Daily!F$15:F$2892,MATCH(_xlfn.MAXIFS(Rates_Daily!$A$15:$A$2892,Rates_Daily!$A$15:$A$2892,"<="&EOMONTH($A50,0),Rates_Daily!F$15:F$2892,">=-1E+99"),Rates_Daily!$A$15:$A$2892,0)),"") -> -0.4 | L50: =IFERROR(AVERAGEIFS(Rates_Daily!E$15:E$2892,Rates_Daily!$A$15:$A$2892,">="&$A50,Rates_Daily!$A$15:$A$2892,"<="&EOMONTH($A50,0)),"") | M50: -0.3670526 | N50: -0.3118947 | O50: -0.2408421 | P50: -0.1286842 | Q50: -0.31189474 | R50: 0.75 | S50: 0.7026 | T50: =IFERROR(AVERAGEIFS(Rates_Daily!I$15:I$2892,Rates_Daily!$A$15:$A$2892,">="&$A50,Rates_Daily!$A$15:$A$2892,"<="&EOMONTH($A50,0)),"") -> 0.69585311 | U50: =IFERROR(AVERAGEIFS(Rates_Daily!J$15:J$2892,Rates_Daily!$A$15:$A$2892,">="&$A50,Rates_Daily!$A$15:$A$2892,"<="&EOMONTH($A50,0)),"") -> 0.70559688 | V50: =IFERROR(AVERAGEIFS(Rates_Daily!K$15:K$2892,Rates_Daily!$A$15:$A$2892,">="&$A50,Rates_Daily!$A$15:$A$2892,"<="&EOMONTH($A50,0)),"") -> 0.7278855 | W50: =IFERROR(AVERAGEIFS(Rates_Daily!L$15:L$2892,Rates_Daily!$A$15:$A$2892,">="&$A50,Rates_Daily!$A$15:$A$2892,"<="&EOMONTH($A50,0)),"") -> 0.77951886 | X50: 0.90444 | Y50: 0.75 | Z50: 0.91 | AD50: 1.28 | AE50: 1.75 | AF50: 1.77 | AG50: 1.91 | AH50: 1.89 | AI50: 1.99 | AJ50: 2.02 | AK50: 1.751 | AL50: 1.854 | AM50: 1.776 | AN50: 1.91 | AO50: =IFERROR(AVERAGEIFS(Rates_Daily!M$15:M$2892,Rates_Daily!$A$15:$A$2892,">="&$A50,Rates_Daily!$A$15:$A$2892,"<="&EOMONTH($A50,0)),"") -> 3.0485238 | AP50: =IFERROR(AVERAGEIFS(Rates_Daily!N$15:N$2892,Rates_Daily!$A$15:$A$2892,">="&$A50,Rates_Daily!$A$15:$A$2892,"<="&EOMONTH($A50,0)),"") -> 3.1983333 | AQ50: =IFERROR(AVERAGEIFS(Rates_Daily!O$15:O$2892,Rates_Daily!$A$15:$A$2892,">="&$A50,Rates_Daily!$A$15:$A$2892,"<="&EOMONTH($A50,0)),"") -> 3.2810952 | AR50: =IFERROR(AVERAGEIFS(Rates_Daily!P$15:P$2892,Rates_Daily!$A$15:$A$2892,">="&$A50,Rates_Daily!$A$15:$A$2892,"<="&EOMONTH($A50,0)),"") -> 3.5219048 | AU50: 3.87 | AV50: 6.4 | AW50: 6.5 | AX50: 0.05 | AY50: -0.068 | AZ50: =IF(EOMONTH($A50,0)>MAX(Rates_Daily!$A$15:$A$2892),"partial month","complete") -> complete
A51: 43466 | B51: 2.4 | C51: =IFERROR(INDEX(Rates_Daily!C$15:C$2892,MATCH(_xlfn.MAXIFS(Rates_Daily!$A$15:$A$2892,Rates_Daily!$A$15:$A$2892,"<="&EOMONTH($A51,0),Rates_Daily!C$15:C$2892,">=-1E+99"),Rates_Daily!$A$15:$A$2892,0)),"") -> 2.5 | D51: =IFERROR(INDEX(Rates_Daily!D$15:D$2892,MATCH(_xlfn.MAXIFS(Rates_Daily!$A$15:$A$2892,Rates_Daily!$A$15:$A$2892,"<="&EOMONTH($A51,0),Rates_Daily!D$15:D$2892,">=-1E+99"),Rates_Daily!$A$15:$A$2892,0)),"") -> 2.25 | E51: =IFERROR(AVERAGEIFS(Rates_Daily!B$15:B$2892,Rates_Daily!$A$15:$A$2892,">="&$A51,Rates_Daily!$A$15:$A$2892,"<="&EOMONTH($A51,0)),"") -> 2.472381 | F51: 2.4 | G51: 2.42 | H51: 2.51 | I51: 2.58 | J51: 2.59 | K51: =IFERROR(INDEX(Rates_Daily!F$15:F$2892,MATCH(_xlfn.MAXIFS(Rates_Daily!$A$15:$A$2892,Rates_Daily!$A$15:$A$2892,"<="&EOMONTH($A51,0),Rates_Daily!F$15:F$2892,">=-1E+99"),Rates_Daily!$A$15:$A$2892,0)),"") -> -0.4 | L51: =IFERROR(AVERAGEIFS(Rates_Daily!E$15:E$2892,Rates_Daily!$A$15:$A$2892,">="&$A51,Rates_Daily!$A$15:$A$2892,"<="&EOMONTH($A51,0)),"") | M51: -0.3663636 | N51: -0.308 | O51: -0.2363636 | P51: -0.1158636 | Q51: -0.308 | R51: 0.75 | S51: 0.7053 | T51: =IFERROR(AVERAGEIFS(Rates_Daily!I$15:I$2892,Rates_Daily!$A$15:$A$2892,">="&$A51,Rates_Daily!$A$15:$A$2892,"<="&EOMONTH($A51,0)),"") -> 0.70457995 | U51: =IFERROR(AVERAGEIFS(Rates_Daily!J$15:J$2892,Rates_Daily!$A$15:$A$2892,">="&$A51,Rates_Daily!$A$15:$A$2892,"<="&EOMONTH($A51,0)),"") -> 0.71194818 | V51: =IFERROR(AVERAGEIFS(Rates_Daily!K$15:K$2892,Rates_Daily!$A$15:$A$2892,">="&$A51,Rates_Daily!$A$15:$A$2892,"<="&EOMONTH($A51,0)),"") -> 0.73305512 | W51: =IFERROR(AVERAGEIFS(Rates_Daily!L$15:L$2892,Rates_Daily!$A$15:$A$2892,">="&$A51,Rates_Daily!$A$15:$A$2892,"<="&EOMONTH($A51,0)),"") -> 0.78150407 | X51: 0.91822 | Y51: 0.75 | Z51: 0.74 | AA51: 0.861 | AB51: 0.933 | AC51: 0.998 | AD51: 1.26 | AE51: 1.75 | AF51: 1.75 | AG51: 1.87 | AH51: 1.86 | AI51: 1.91 | AJ51: 1.94 | AK51: 1.747 | AL51: 1.808 | AM51: 1.733 | AN51: 1.87 | AO51: =IFERROR(AVERAGEIFS(Rates_Daily!M$15:M$2892,Rates_Daily!$A$15:$A$2892,">="&$A51,Rates_Daily!$A$15:$A$2892,"<="&EOMONTH($A51,0)),"") -> 2.8461364 | AP51: =IFERROR(AVERAGEIFS(Rates_Daily!N$15:N$2892,Rates_Daily!$A$15:$A$2892,">="&$A51,Rates_Daily!$A$15:$A$2892,"<="&EOMONTH($A51,0)),"") -> 2.9984091 | AQ51: =IFERROR(AVERAGEIFS(Rates_Daily!O$15:O$2892,Rates_Daily!$A$15:$A$2892,">="&$A51,Rates_Daily!$A$15:$A$2892,"<="&EOMONTH($A51,0)),"") -> 3.1133182 | AR51: =IFERROR(AVERAGEIFS(Rates_Daily!P$15:P$2892,Rates_Daily!$A$15:$A$2892,">="&$A51,Rates_Daily!$A$15:$A$2892,"<="&EOMONTH($A51,0)),"") -> 3.3505 | AU51: 3.24 | AV51: 6.4 | AW51: 6.5 | AX51: 0.03 | AY51: -0.064 | AZ51: =IF(EOMONTH($A51,0)>MAX(Rates_Daily!$A$15:$A$2892),"partial month","complete") -> complete
A52: 43497 | B52: 2.4 | C52: =IFERROR(INDEX(Rates_Daily!C$15:C$2892,MATCH(_xlfn.MAXIFS(Rates_Daily!$A$15:$A$2892,Rates_Daily!$A$15:$A$2892,"<="&EOMONTH($A52,0),Rates_Daily!C$15:C$2892,">=-1E+99"),Rates_Daily!$A$15:$A$2892,0)),"") -> 2.5 | D52: =IFERROR(INDEX(Rates_Daily!D$15:D$2892,MATCH(_xlfn.MAXIFS(Rates_Daily!$A$15:$A$2892,Rates_Daily!$A$15:$A$2892,"<="&EOMONTH($A52,0),Rates_Daily!D$15:D$2892,">=-1E+99"),Rates_Daily!$A$15:$A$2892,0)),"") -> 2.25 | E52: =IFERROR(AVERAGEIFS(Rates_Daily!B$15:B$2892,Rates_Daily!$A$15:$A$2892,">="&$A52,Rates_Daily!$A$15:$A$2892,"<="&EOMONTH($A52,0)),"") -> 2.4042105 | F52: 2.43 | G52: 2.44 | H52: 2.5 | I52: 2.55 | J52: 2.49 | K52: =IFERROR(INDEX(Rates_Daily!F$15:F$2892,MATCH(_xlfn.MAXIFS(Rates_Daily!$A$15:$A$2892,Rates_Daily!$A$15:$A$2892,"<="&EOMONTH($A52,0),Rates_Daily!F$15:F$2892,">=-1E+99"),Rates_Daily!$A$15:$A$2892,0)),"") -> -0.4 | L52: =IFERROR(AVERAGEIFS(Rates_Daily!E$15:E$2892,Rates_Daily!$A$15:$A$2892,">="&$A52,Rates_Daily!$A$15:$A$2892,"<="&EOMONTH($A52,0)),"") | M52: -0.3677 | N52: -0.30845 | O52: -0.2318 | P52: -0.1084 | Q52: -0.30845 | R52: 0.75 | S52: 0.7061 | T52: =IFERROR(AVERAGEIFS(Rates_Daily!I$15:I$2892,Rates_Daily!$A$15:$A$2892,">="&$A52,Rates_Daily!$A$15:$A$2892,"<="&EOMONTH($A52,0)),"") -> 0.70449171 | U52: =IFERROR(AVERAGEIFS(Rates_Daily!J$15:J$2892,Rates_Daily!$A$15:$A$2892,">="&$A52,Rates_Daily!$A$15:$A$2892,"<="&EOMONTH($A52,0)),"") -> 0.70482052 | V52: =IFERROR(AVERAGEIFS(Rates_Daily!K$15:K$2892,Rates_Daily!$A$15:$A$2892,">="&$A52,Rates_Daily!$A$15:$A$2892,"<="&EOMONTH($A52,0)),"") -> 0.71848227 | W52: =IFERROR(AVERAGEIFS(Rates_Daily!L$15:L$2892,Rates_Daily!$A$15:$A$2892,">="&$A52,Rates_Daily!$A$15:$A$2892,"<="&EOMONTH($A52,0)),"") -> 0.75450841 | X52: 0.87598 | Y52: 0.75 | Z52: 0.75 | AA52: 1.006 | AB52: 1.026 | AC52: 1.055 | AD52: 1.27 | AE52: 1.75 | AF52: 1.76 | AG52: 1.87 | AH52: 1.86 | AI52: 1.91 | AJ52: 1.94 | AK52: 1.758 | AL52: 1.831 | AM52: 1.76 | AN52: 1.87 | AO52: =IFERROR(AVERAGEIFS(Rates_Daily!M$15:M$2892,Rates_Daily!$A$15:$A$2892,">="&$A52,Rates_Daily!$A$15:$A$2892,"<="&EOMONTH($A52,0)),"") -> 2.7174118 | AP52: =IFERROR(AVERAGEIFS(Rates_Daily!N$15:N$2892,Rates_Daily!$A$15:$A$2892,">="&$A52,Rates_Daily!$A$15:$A$2892,"<="&EOMONTH($A52,0)),"") -> 2.8118235 | AQ52: =IFERROR(AVERAGEIFS(Rates_Daily!O$15:O$2892,Rates_Daily!$A$15:$A$2892,">="&$A52,Rates_Daily!$A$15:$A$2892,"<="&EOMONTH($A52,0)),"") -> 2.9102353 | AR52: =IFERROR(AVERAGEIFS(Rates_Daily!P$15:P$2892,Rates_Daily!$A$15:$A$2892,">="&$A52,Rates_Daily!$A$15:$A$2892,"<="&EOMONTH($A52,0)),"") -> 3.1164118 | AU52: 2.91 | AV52: 6.4 | AW52: 6.5 | AX52: 0.03 | AY52: -0.055 | AZ52: =IF(EOMONTH($A52,0)>MAX(Rates_Daily!$A$15:$A$2892),"partial month","complete") -> complete
A53: 43525 | B53: 2.41 | C53: =IFERROR(INDEX(Rates_Daily!C$15:C$2892,MATCH(_xlfn.MAXIFS(Rates_Daily!$A$15:$A$2892,Rates_Daily!$A$15:$A$2892,"<="&EOMONTH($A53,0),Rates_Daily!C$15:C$2892,">=-1E+99"),Rates_Daily!$A$15:$A$2892,0)),"") -> 2.5 | D53: =IFERROR(INDEX(Rates_Daily!D$15:D$2892,MATCH(_xlfn.MAXIFS(Rates_Daily!$A$15:$A$2892,Rates_Daily!$A$15:$A$2892,"<="&EOMONTH($A53,0),Rates_Daily!D$15:D$2892,">=-1E+99"),Rates_Daily!$A$15:$A$2892,0)),"") -> 2.25 | E53: =IFERROR(AVERAGEIFS(Rates_Daily!B$15:B$2892,Rates_Daily!$A$15:$A$2892,">="&$A53,Rates_Daily!$A$15:$A$2892,"<="&EOMONTH($A53,0)),"") -> 2.4171429 | F53: 2.45 | G53: 2.45 | H53: 2.51 | I53: 2.49 | J53: 2.48 | K53: =IFERROR(INDEX(Rates_Daily!F$15:F$2892,MATCH(_xlfn.MAXIFS(Rates_Daily!$A$15:$A$2892,Rates_Daily!$A$15:$A$2892,"<="&EOMONTH($A53,0),Rates_Daily!F$15:F$2892,">=-1E+99"),Rates_Daily!$A$15:$A$2892,0)),"") -> -0.4 | L53: =IFERROR(AVERAGEIFS(Rates_Daily!E$15:E$2892,Rates_Daily!$A$15:$A$2892,">="&$A53,Rates_Daily!$A$15:$A$2892,"<="&EOMONTH($A53,0)),"") | M53: -0.3674762 | N53: -0.3091905 | O53: -0.2302381 | P53: -0.1087619 | Q53: -0.30919048 | R53: 0.75 | S53: 0.7053 | T53: =IFERROR(AVERAGEIFS(Rates_Daily!I$15:I$2892,Rates_Daily!$A$15:$A$2892,">="&$A53,Rates_Daily!$A$15:$A$2892,"<="&EOMONTH($A53,0)),"") -> 0.7024166 | U53: =IFERROR(AVERAGEIFS(Rates_Daily!J$15:J$2892,Rates_Daily!$A$15:$A$2892,">="&$A53,Rates_Daily!$A$15:$A$2892,"<="&EOMONTH($A53,0)),"") -> 0.70177324 | V53: =IFERROR(AVERAGEIFS(Rates_Daily!K$15:K$2892,Rates_Daily!$A$15:$A$2892,">="&$A53,Rates_Daily!$A$15:$A$2892,"<="&EOMONTH($A53,0)),"") -> 0.70843372 | W53: =IFERROR(AVERAGEIFS(Rates_Daily!L$15:L$2892,Rates_Daily!$A$15:$A$2892,">="&$A53,Rates_Daily!$A$15:$A$2892,"<="&EOMONTH($A53,0)),"") -> 0.73423394 | X53: 0.84 | Y53: 0.82 | Z53: 0.85 | AA53: 1.06 | AB53: 1.082 | AC53: 1.121 | AD53: 1.34 | AE53: 1.75 | AF53: 1.76 | AG53: 1.9 | AH53: 1.87 | AI53: 1.91 | AJ53: 1.94 | AK53: 1.767 | AL53: 1.831 | AM53: 1.769 | AN53: 1.9 | AO53: =IFERROR(AVERAGEIFS(Rates_Daily!M$15:M$2892,Rates_Daily!$A$15:$A$2892,">="&$A53,Rates_Daily!$A$15:$A$2892,"<="&EOMONTH($A53,0)),"") -> 2.7884381 | AP53: =IFERROR(AVERAGEIFS(Rates_Daily!N$15:N$2892,Rates_Daily!$A$15:$A$2892,">="&$A53,Rates_Daily!$A$15:$A$2892,"<="&EOMONTH($A53,0)),"") -> 2.7906429 | AQ53: =IFERROR(AVERAGEIFS(Rates_Daily!O$15:O$2892,Rates_Daily!$A$15:$A$2892,">="&$A53,Rates_Daily!$A$15:$A$2892,"<="&EOMONTH($A53,0)),"") -> 2.8545714 | AR53: =IFERROR(AVERAGEIFS(Rates_Daily!P$15:P$2892,Rates_Daily!$A$15:$A$2892,">="&$A53,Rates_Daily!$A$15:$A$2892,"<="&EOMONTH($A53,0)),"") -> 3.0699524 | AU53: 3.08 | AV53: 6.4 | AW53: 6.5 | AX53: 0.05 | AY53: -0.041 | AZ53: =IF(EOMONTH($A53,0)>MAX(Rates_Daily!$A$15:$A$2892),"partial month","complete") -> complete
A54: 43556 | B54: 2.42 | C54: =IFERROR(INDEX(Rates_Daily!C$15:C$2892,MATCH(_xlfn.MAXIFS(Rates_Daily!$A$15:$A$2892,Rates_Daily!$A$15:$A$2892,"<="&EOMONTH($A54,0),Rates_Daily!C$15:C$2892,">=-1E+99"),Rates_Daily!$A$15:$A$2892,0)),"") -> 2.5 | D54: =IFERROR(INDEX(Rates_Daily!D$15:D$2892,MATCH(_xlfn.MAXIFS(Rates_Daily!$A$15:$A$2892,Rates_Daily!$A$15:$A$2892,"<="&EOMONTH($A54,0),Rates_Daily!D$15:D$2892,">=-1E+99"),Rates_Daily!$A$15:$A$2892,0)),"") -> 2.25 | E54: =IFERROR(AVERAGEIFS(Rates_Daily!B$15:B$2892,Rates_Daily!$A$15:$A$2892,">="&$A54,Rates_Daily!$A$15:$A$2892,"<="&EOMONTH($A54,0)),"") -> 2.4761905 | F54: 2.43 | G54: 2.43 | H54: 2.46 | I54: 2.42 | J54: 2.47 | K54: =IFERROR(INDEX(Rates_Daily!F$15:F$2892,MATCH(_xlfn.MAXIFS(Rates_Daily!$A$15:$A$2892,Rates_Daily!$A$15:$A$2892,"<="&EOMONTH($A54,0),Rates_Daily!F$15:F$2892,">=-1E+99"),Rates_Daily!$A$15:$A$2892,0)),"") -> -0.4 | L54: =IFERROR(AVERAGEIFS(Rates_Daily!E$15:E$2892,Rates_Daily!$A$15:$A$2892,">="&$A54,Rates_Daily!$A$15:$A$2892,"<="&EOMONTH($A54,0)),"") | M54: -0.36725 | N54: -0.31045 | O54: -0.23075 | P54: -0.1122 | Q54: -0.31045 | R54: 0.75 | S54: 0.7081 | T54: =IFERROR(AVERAGEIFS(Rates_Daily!I$15:I$2892,Rates_Daily!$A$15:$A$2892,">="&$A54,Rates_Daily!$A$15:$A$2892,"<="&EOMONTH($A54,0)),"") -> 0.70601179 | U54: =IFERROR(AVERAGEIFS(Rates_Daily!J$15:J$2892,Rates_Daily!$A$15:$A$2892,">="&$A54,Rates_Daily!$A$15:$A$2892,"<="&EOMONTH($A54,0)),"") -> 0.70389406 | V54: =IFERROR(AVERAGEIFS(Rates_Daily!K$15:K$2892,Rates_Daily!$A$15:$A$2892,">="&$A54,Rates_Daily!$A$15:$A$2892,"<="&EOMONTH($A54,0)),"") -> 0.7103996 | W54: =IFERROR(AVERAGEIFS(Rates_Daily!L$15:L$2892,Rates_Daily!$A$15:$A$2892,">="&$A54,Rates_Daily!$A$15:$A$2892,"<="&EOMONTH($A54,0)),"") -> 0.73189876 | X54: 0.82 | Y54: 1 | Z54: 1 | AA54: 1.101 | AB54: 1.145 | AC54: 1.218 | AD54: 1.4 | AE54: 1.75 | AF54: 1.75 | AG54: 1.86 | AH54: 1.84 | AI54: 1.86 | AJ54: 1.87 | AK54: 1.755 | AL54: 1.77 | AM54: 1.751 | AN54: 1.86 | AO54: =IFERROR(AVERAGEIFS(Rates_Daily!M$15:M$2892,Rates_Daily!$A$15:$A$2892,">="&$A54,Rates_Daily!$A$15:$A$2892,"<="&EOMONTH($A54,0)),"") -> 2.7621364 | AP54: =IFERROR(AVERAGEIFS(Rates_Daily!N$15:N$2892,Rates_Daily!$A$15:$A$2892,">="&$A54,Rates_Daily!$A$15:$A$2892,"<="&EOMONTH($A54,0)),"") -> 2.8130455 | AQ54: =IFERROR(AVERAGEIFS(Rates_Daily!O$15:O$2892,Rates_Daily!$A$15:$A$2892,">="&$A54,Rates_Daily!$A$15:$A$2892,"<="&EOMONTH($A54,0)),"") -> 2.8689091 | AR54: =IFERROR(AVERAGEIFS(Rates_Daily!P$15:P$2892,Rates_Daily!$A$15:$A$2892,">="&$A54,Rates_Daily!$A$15:$A$2892,"<="&EOMONTH($A54,0)),"") -> 3.0861818 | AU54: 3 | AV54: 6.4 | AW54: 6.5 | AX54: 0.05 | AY54: -0.067 | AZ54: =IF(EOMONTH($A54,0)>MAX(Rates_Daily!$A$15:$A$2892),"partial month","complete") -> complete
A55: 43586 | B55: 2.39 | C55: =IFERROR(INDEX(Rates_Daily!C$15:C$2892,MATCH(_xlfn.MAXIFS(Rates_Daily!$A$15:$A$2892,Rates_Daily!$A$15:$A$2892,"<="&EOMONTH($A55,0),Rates_Daily!C$15:C$2892,">=-1E+99"),Rates_Daily!$A$15:$A$2892,0)),"") -> 2.5 | D55: =IFERROR(INDEX(Rates_Daily!D$15:D$2892,MATCH(_xlfn.MAXIFS(Rates_Daily!$A$15:$A$2892,Rates_Daily!$A$15:$A$2892,"<="&EOMONTH($A55,0),Rates_Daily!D$15:D$2892,">=-1E+99"),Rates_Daily!$A$15:$A$2892,0)),"") -> 2.25 | E55: =IFERROR(AVERAGEIFS(Rates_Daily!B$15:B$2892,Rates_Daily!$A$15:$A$2892,">="&$A55,Rates_Daily!$A$15:$A$2892,"<="&EOMONTH($A55,0)),"") -> 2.4204545 | F55: 2.4 | G55: 2.4 | H55: 2.42 | I55: 2.34 | J55: 2.44 | K55: =IFERROR(INDEX(Rates_Daily!F$15:F$2892,MATCH(_xlfn.MAXIFS(Rates_Daily!$A$15:$A$2892,Rates_Daily!$A$15:$A$2892,"<="&EOMONTH($A55,0),Rates_Daily!F$15:F$2892,">=-1E+99"),Rates_Daily!$A$15:$A$2892,0)),"") -> -0.4 | L55: =IFERROR(AVERAGEIFS(Rates_Daily!E$15:E$2892,Rates_Daily!$A$15:$A$2892,">="&$A55,Rates_Daily!$A$15:$A$2892,"<="&EOMONTH($A55,0)),"") | M55: -0.369 | N55: -0.3118636 | O55: -0.2373636 | P55: -0.1339091 | Q55: -0.31186364 | R55: 0.75 | S55: 0.7094 | T55: =IFERROR(AVERAGEIFS(Rates_Daily!I$15:I$2892,Rates_Daily!$A$15:$A$2892,">="&$A55,Rates_Daily!$A$15:$A$2892,"<="&EOMONTH($A55,0)),"") -> 0.71009968 | U55: =IFERROR(AVERAGEIFS(Rates_Daily!J$15:J$2892,Rates_Daily!$A$15:$A$2892,">="&$A55,Rates_Daily!$A$15:$A$2892,"<="&EOMONTH($A55,0)),"") -> 0.7123896 | V55: =IFERROR(AVERAGEIFS(Rates_Daily!K$15:K$2892,Rates_Daily!$A$15:$A$2892,">="&$A55,Rates_Daily!$A$15:$A$2892,"<="&EOMONTH($A55,0)),"") -> 0.71793695 | W55: =IFERROR(AVERAGEIFS(Rates_Daily!L$15:L$2892,Rates_Daily!$A$15:$A$2892,">="&$A55,Rates_Daily!$A$15:$A$2892,"<="&EOMONTH($A55,0)),"") -> 0.73047678 | X55: 0.8 | Y55: 1 | Z55: 1 | AA55: 1.163 | AB55: 1.207 | AC55: 1.235 | AD55: 1.46 | AE55: 1.75 | AF55: 1.75 | AG55: 1.84 | AH55: 1.8 | AI55: 1.82 | AJ55: 1.83 | AK55: 1.718 | AL55: 1.715 | AM55: 1.711 | AN55: 1.84 | AO55: =IFERROR(AVERAGEIFS(Rates_Daily!M$15:M$2892,Rates_Daily!$A$15:$A$2892,">="&$A55,Rates_Daily!$A$15:$A$2892,"<="&EOMONTH($A55,0)),"") -> 2.7630952 | AP55: =IFERROR(AVERAGEIFS(Rates_Daily!N$15:N$2892,Rates_Daily!$A$15:$A$2892,">="&$A55,Rates_Daily!$A$15:$A$2892,"<="&EOMONTH($A55,0)),"") -> 2.9065714 | AQ55: =IFERROR(AVERAGEIFS(Rates_Daily!O$15:O$2892,Rates_Daily!$A$15:$A$2892,">="&$A55,Rates_Daily!$A$15:$A$2892,"<="&EOMONTH($A55,0)),"") -> 2.9532857 | AR55: =IFERROR(AVERAGEIFS(Rates_Daily!P$15:P$2892,Rates_Daily!$A$15:$A$2892,">="&$A55,Rates_Daily!$A$15:$A$2892,"<="&EOMONTH($A55,0)),"") -> 3.1733333 | AU55: 3.15 | AV55: 6.4 | AW55: 6.5 | AX55: 0.049 | AY55: -0.049 | AZ55: =IF(EOMONTH($A55,0)>MAX(Rates_Daily!$A$15:$A$2892),"partial month","complete") -> complete
A56: 43617 | B56: 2.38 | C56: =IFERROR(INDEX(Rates_Daily!C$15:C$2892,MATCH(_xlfn.MAXIFS(Rates_Daily!$A$15:$A$2892,Rates_Daily!$A$15:$A$2892,"<="&EOMONTH($A56,0),Rates_Daily!C$15:C$2892,">=-1E+99"),Rates_Daily!$A$15:$A$2892,0)),"") -> 2.5 | D56: =IFERROR(INDEX(Rates_Daily!D$15:D$2892,MATCH(_xlfn.MAXIFS(Rates_Daily!$A$15:$A$2892,Rates_Daily!$A$15:$A$2892,"<="&EOMONTH($A56,0),Rates_Daily!D$15:D$2892,">=-1E+99"),Rates_Daily!$A$15:$A$2892,0)),"") -> 2.25 | E56: =IFERROR(AVERAGEIFS(Rates_Daily!B$15:B$2892,Rates_Daily!$A$15:$A$2892,">="&$A56,Rates_Daily!$A$15:$A$2892,"<="&EOMONTH($A56,0)),"") -> 2.393 | F56: 2.22 | G56: 2.22 | H56: 2.17 | I56: 2 | J56: 2.3 | K56: =IFERROR(INDEX(Rates_Daily!F$15:F$2892,MATCH(_xlfn.MAXIFS(Rates_Daily!$A$15:$A$2892,Rates_Daily!$A$15:$A$2892,"<="&EOMONTH($A56,0),Rates_Daily!F$15:F$2892,">=-1E+99"),Rates_Daily!$A$15:$A$2892,0)),"") -> -0.4 | L56: =IFERROR(AVERAGEIFS(Rates_Daily!E$15:E$2892,Rates_Daily!$A$15:$A$2892,">="&$A56,Rates_Daily!$A$15:$A$2892,"<="&EOMONTH($A56,0)),"") | M56: -0.3848 | N56: -0.3289 | O56: -0.279 | P56: -0.19025 | Q56: -0.3289 | R56: 0.75 | S56: 0.7085 | T56: =IFERROR(AVERAGEIFS(Rates_Daily!I$15:I$2892,Rates_Daily!$A$15:$A$2892,">="&$A56,Rates_Daily!$A$15:$A$2892,"<="&EOMONTH($A56,0)),"") -> 0.70915683 | U56: =IFERROR(AVERAGEIFS(Rates_Daily!J$15:J$2892,Rates_Daily!$A$15:$A$2892,">="&$A56,Rates_Daily!$A$15:$A$2892,"<="&EOMONTH($A56,0)),"") -> 0.70893247 | V56: =IFERROR(AVERAGEIFS(Rates_Daily!K$15:K$2892,Rates_Daily!$A$15:$A$2892,">="&$A56,Rates_Daily!$A$15:$A$2892,"<="&EOMONTH($A56,0)),"") -> 0.69881401 | W56: =IFERROR(AVERAGEIFS(Rates_Daily!L$15:L$2892,Rates_Daily!$A$15:$A$2892,">="&$A56,Rates_Daily!$A$15:$A$2892,"<="&EOMONTH($A56,0)),"") -> 0.67033291 | X56: 0.78 | Y56: 1.08 | Z56: 1.18 | AA56: 1.086 | AB56: 1.131 | AC56: 1.159 | AD56: 1.51 | AE56: 1.75 | AF56: 1.76 | AG56: 1.8 | AH56: 1.72 | AI56: 1.72 | AJ56: 1.71 | AK56: 1.596 | AL56: 1.566 | AM56: 1.56 | AN56: 1.8 | AO56: =IFERROR(AVERAGEIFS(Rates_Daily!M$15:M$2892,Rates_Daily!$A$15:$A$2892,">="&$A56,Rates_Daily!$A$15:$A$2892,"<="&EOMONTH($A56,0)),"") -> 2.8291053 | AP56: =IFERROR(AVERAGEIFS(Rates_Daily!N$15:N$2892,Rates_Daily!$A$15:$A$2892,">="&$A56,Rates_Daily!$A$15:$A$2892,"<="&EOMONTH($A56,0)),"") -> 2.8859474 | AQ56: =IFERROR(AVERAGEIFS(Rates_Daily!O$15:O$2892,Rates_Daily!$A$15:$A$2892,">="&$A56,Rates_Daily!$A$15:$A$2892,"<="&EOMONTH($A56,0)),"") -> 2.9358947 | AR56: =IFERROR(AVERAGEIFS(Rates_Daily!P$15:P$2892,Rates_Daily!$A$15:$A$2892,">="&$A56,Rates_Daily!$A$15:$A$2892,"<="&EOMONTH($A56,0)),"") -> 3.191 | AU56: 3.6 | AV56: 6.4 | AW56: 6.5 | AX56: 0.049 | AY56: -0.062 | AZ56: =IF(EOMONTH($A56,0)>MAX(Rates_Daily!$A$15:$A$2892),"partial month","complete") -> complete
A57: 43647 | B57: 2.4 | C57: =IFERROR(INDEX(Rates_Daily!C$15:C$2892,MATCH(_xlfn.MAXIFS(Rates_Daily!$A$15:$A$2892,Rates_Daily!$A$15:$A$2892,"<="&EOMONTH($A57,0),Rates_Daily!C$15:C$2892,">=-1E+99"),Rates_Daily!$A$15:$A$2892,0)),"") -> 2.5 | D57: =IFERROR(INDEX(Rates_Daily!D$15:D$2892,MATCH(_xlfn.MAXIFS(Rates_Daily!$A$15:$A$2892,Rates_Daily!$A$15:$A$2892,"<="&EOMONTH($A57,0),Rates_Daily!D$15:D$2892,">=-1E+99"),Rates_Daily!$A$15:$A$2892,0)),"") -> 2.25 | E57: =IFERROR(AVERAGEIFS(Rates_Daily!B$15:B$2892,Rates_Daily!$A$15:$A$2892,">="&$A57,Rates_Daily!$A$15:$A$2892,"<="&EOMONTH($A57,0)),"") -> 2.4495455 | F57: 2.15 | G57: 2.15 | H57: 2.08 | I57: 1.96 | J57: 2.22 | K57: =IFERROR(INDEX(Rates_Daily!F$15:F$2892,MATCH(_xlfn.MAXIFS(Rates_Daily!$A$15:$A$2892,Rates_Daily!$A$15:$A$2892,"<="&EOMONTH($A57,0),Rates_Daily!F$15:F$2892,">=-1E+99"),Rates_Daily!$A$15:$A$2892,0)),"") -> -0.4 | L57: =IFERROR(AVERAGEIFS(Rates_Daily!E$15:E$2892,Rates_Daily!$A$15:$A$2892,">="&$A57,Rates_Daily!$A$15:$A$2892,"<="&EOMONTH($A57,0)),"") | M57: -0.3951304 | N57: -0.3648696 | O57: -0.3473913 | P57: -0.2833043 | Q57: -0.36486957 | R57: 0.75 | S57: 0.709 | T57: =IFERROR(AVERAGEIFS(Rates_Daily!I$15:I$2892,Rates_Daily!$A$15:$A$2892,">="&$A57,Rates_Daily!$A$15:$A$2892,"<="&EOMONTH($A57,0)),"") -> 0.70745662 | U57: =IFERROR(AVERAGEIFS(Rates_Daily!J$15:J$2892,Rates_Daily!$A$15:$A$2892,">="&$A57,Rates_Daily!$A$15:$A$2892,"<="&EOMONTH($A57,0)),"") -> 0.69418856 | V57: =IFERROR(AVERAGEIFS(Rates_Daily!K$15:K$2892,Rates_Daily!$A$15:$A$2892,">="&$A57,Rates_Daily!$A$15:$A$2892,"<="&EOMONTH($A57,0)),"") -> 0.65332101 | W57: =IFERROR(AVERAGEIFS(Rates_Daily!L$15:L$2892,Rates_Daily!$A$15:$A$2892,">="&$A57,Rates_Daily!$A$15:$A$2892,"<="&EOMONTH($A57,0)),"") -> 0.58166101 | X57: 0.77 | Y57: 1.25 | Z57: 1.25 | AA57: 1.21 | AB57: 1.271 | AC57: 1.259 | AD57: 1.57 | AE57: 1.5 | AF57: 1.63 | AG57: 1.68 | AH57: 1.63 | AI57: 1.61 | AJ57: 1.58 | AK57: 1.516 | AL57: 1.467 | AM57: 1.478 | AN57: 1.68 | AO57: =IFERROR(AVERAGEIFS(Rates_Daily!M$15:M$2892,Rates_Daily!$A$15:$A$2892,">="&$A57,Rates_Daily!$A$15:$A$2892,"<="&EOMONTH($A57,0)),"") -> 2.543087 | AP57: =IFERROR(AVERAGEIFS(Rates_Daily!N$15:N$2892,Rates_Daily!$A$15:$A$2892,">="&$A57,Rates_Daily!$A$15:$A$2892,"<="&EOMONTH($A57,0)),"") -> 2.6233913 | AQ57: =IFERROR(AVERAGEIFS(Rates_Daily!O$15:O$2892,Rates_Daily!$A$15:$A$2892,">="&$A57,Rates_Daily!$A$15:$A$2892,"<="&EOMONTH($A57,0)),"") -> 2.713 | AR57: =IFERROR(AVERAGEIFS(Rates_Daily!P$15:P$2892,Rates_Daily!$A$15:$A$2892,">="&$A57,Rates_Daily!$A$15:$A$2892,"<="&EOMONTH($A57,0)),"") -> 3.0947391 | AU57: 3.16 | AV57: 6.4 | AW57: 6.5 | AX57: 0.049 | AY57: -0.071 | AZ57: =IF(EOMONTH($A57,0)>MAX(Rates_Daily!$A$15:$A$2892),"partial month","complete") -> complete
